Workbook

Sheet DAMASO
A1: DATOS BASICOS
A2: SISTEMA | B2: 1 | C2: 1=SEBD/2=SM
A3: SEXO | B3: M
A4: FECHA DE NACIMIENTO | B4: 22564
A5: FECHA DE PRIMERA CUOTA | B5: 29860
A6: EDAD ENTRADA | B6: =+DATEDIF(B4,B5,"Y") -> 19
A7: EDAD ACTUAL | B7: =2024-YEAR(B4) -> 63
A8: EDAD DE JUBILACION | B8: 65
A9: SALARIO MENSUAL HOY
A10: TASA CRECIMIENTO SALARIAL | B10: 0.015
A11: % CUOTA APLICADO ANTES VIGENCIA NVA LEY | B11: 0.15 | I11: BENEFICIO DE JUBILACION CSS | S11: BENEFICIO ACTUARIAL JUSTO
A12: % CUOTA EMPLEADO EMPLEADOR NUEVA LEY | B12: 0.15 | I12: CUOTAS APORTADAS | N12: =+SUM(AE29:AE77) -> 541 | S12: EDAD JUBILACION | X12: =+B8 -> 65
A13: % XIII EMPLEADO EMPLEADOR NUEVA LEY | B13: 0.15 | I13: CUOTAS EN EXCESO A DENSIDAD MIN | N13: =+N12-B16 -> 301 | S13: FONDO AHORRADO COP ANTES VIGENCIA NVA LEY | X13: =+VLOOKUP(X12,$J$29:$Q$77,8,FALSE) -> 217009.7
A14: TASA DE RETORNO INVERSIONES ANTES VIG LEY | B14: 0.04 | I14: TASA DE REEMPLAZO SEBD LEY 51 | N14: =+$B$17+INT(N13/12)*$B$18 -> 0.9125 | S14: FACTOR DESCUENTO | X14: =+IF($B$3="M",VLOOKUP(X12,descuento!$A$6:$B$32,2,FALSE),VLOOKUP(X12,descuento!$C$6:$D$32,2,FALSE)) -> 1
A15: TASA RETORNO INVERSIONES PROMEDIO | B15: 0.05 | I15: SALARIO PROMEDIO mejores 10 años | N15: =+VLOOKUP(N17,W20:X22,2,0) -> 30657.333 | S15: FONDO AHORRADO COP DESPUES VIGENCIA NVA LEY | X15: =+VLOOKUP(X12,$T$29:$AA$77,8,FALSE) -> 11502.345
A16: DENSIDAD MINIMA DE CUOTAS LEY 51 | B16: 240 | I16: PENSION ANNUAL A RECIBIR | N16: =+N17*12 -> 24000 | S16: FONDO TOTAL APLICABLE | X16: =+X15+X13*X14 -> 228512.05
A17: TASA DE REEMPLAZO INICIAL LEY 51 | B17: 0.6 | I17: PENSION MENSUAL A RECIBIR | N17: =+MAX(W20:W22) -> 2000 | S17: FACTOR PENSION X MIL | X17: =+VLOOKUP(X12,'bases renta'!$K$20:$L$65,2,FALSE) -> 5.4399911
A18: TASA DE REEMPLAZO ADICIONAL LEY 51 | B18: 0.0125 | I18: TASA DE REEMPLAZO SEBD LEY 51 | N18: =+N16/N15 -> 0.78284695 | S18: PENSION ACTUARIAL JUSTA MENSUAL | X18: =+X17*X16*0.001 -> 1243.1035
A19: SALMAX MENSUAL COTIZADO ANTES VIG NVA LEY | B19: 2500 | S19: PENSION ACTUARIAL ANNUAL JUSTA | X19: =+X18*12 -> 14917.242
A20: PENSION MAXIMA LEY51 | B20: 2500 | S20: PROMEDIO DE LOS MEJORES 10 AÑOS | W20: =+IF($N$14*X20/12>1500,1500,$N$14*X20/12) -> 1500 | X20: {=+AVERAGE(LARGE($AF$29:$AF$77,ROW(INDIRECT("1:10"))))} -> 31481.2
S21: PROMEDIO DE LOS MEJORES 15 AÑOS | W21: =+IF($N$14*X21/12>2000,2000,$N$14*X21/12) -> 2000 | X21: {=IF(AND(N12>300,AVERAGE(LARGE($AF$29:$AF$77,ROW(INDIRECT("1:15"))))>=24000),AVERAGE(LARGE($AF$29:$AF$77,ROW(INDIRECT("1:15")))),0)} -> 30657.333
S22: PROMEDIO DE LOS MEJORES 20 AÑOS | W22: =+IF($N$14*X22/12>2500,2500,$N$14*X22/12) -> 0 | X22: {=IF(AND(N12>360,AVERAGE(LARGE($AF$29:$AF$77,ROW(INDIRECT("1:20"))))>=30000),AVERAGE(LARGE($AF$29:$AF$77,ROW(INDIRECT("1:20")))),0)} -> 0
S24: TASA REEMPLAZO SISTEMA | X24: =+X19/VLOOKUP(N17,W20:X22,2,0) -> 0.48657989
I26: ACUMULACION ANTES VIGENCIA NUEVA LEY | S26: ACUMULACION DESPUES VIGENCIA NUEVA LEY | AC26: SALARIOS PARA CALCULO PROMEDIO MEJORES | AH26: DISMINUCION DEL FONDO CON PENSION JUSTA
B27: AÑO | C27: EDAD INI AÑO | D27: CREC. SALARIO | E27: SALARIO MENSUAL | F27: CUOTAS APORTADAS | G27: SALARIO ANUAL | I27: AÑO | J27: EDAD FIN AÑO | K27: INDICADOR | L27: TASA O-P SALARIO | M27: SALARIO ANNUAL CON MAX 2500 MENSUAL | N27: CUENTA INICIAL | O27: APORTES | P27: INTERESES | Q27: CUENTA FINAL | S27: AÑO | T27: EDAD FIN AÑO | U27: INDICADOR | V27: TASA O-P SALARIO | W27: TASA O-P XIII | X27: CUENTA INICIAL | Y27: APORTES | Z27: INTERESES | AA27: CUENTA FINAL | AC27: AÑO | AD27: EDAD | AE27: CUOTAS APORTADAS | AF27: SALARIO COTIZADO PARA PROMEDIO | AH27: AÑO | AI27: EDAD FIN AÑO | AJ27: CUENTA INICIAL | AK27: PENSION ANUAL PAGADA JUSTA | AL27: INTERES | AM27: CUENTA FINAL
AM28: =+X16 -> 228512.05
B29: =+YEAR(B5) -> 1981 | C29: =+B6 -> 19 | D29: 1 | E29: =+IFERROR(G29/F29,0) -> 140 | F29: 3 | G29: 420 | I29: =+B29 -> 1981 | J29: =+C29+1 -> 20 | K29: =+IF(C29<$B$7,1,0) -> 1 | L29: =B11 -> 0.15 | M29: =+IF($B$2=1,IF(G29<=2500*12,G29,2500*12),G29) -> 420 | N29: =+Q28 -> 0 | O29: =+L29*M29*$K29 -> 63 | P29: =+N29*$B$14 -> 0 | Q29: =+(N29+O29+P29) -> 63 | S29: =+I29 -> 1981 | T29: =+J29 -> 20 | U29: =+IF($C29>=$B$7,1,0) -> 0 | V29: =+$B$12*U29 -> 0 | W29: =+U29*$B$13 -> 0 | X29: =+AA28 -> 0 | Y29: =+(G29*V29)*U29 -> 0 | Z29: =+X29*$B$15*U29 -> 0 | AA29: =+(X29+Y29+Z29) -> 0 | AC29: =+B29 -> 1981 | AD29: =+C29 -> 19 | AE29: =+IF(T29<=$X$12,1,0)*F29 -> 3 | AF29: =+IF(T29>$X$12,0,IF($B$2=1,IF($AD29<$B$7,IF(G29<=$B$19*12,G29,$B$19*12),G29),G29)) -> 420 | AH29: 1 | AI29: =+X12 -> 65 | AJ29: =+AM28 -> 228512.05 | AK29: =+X19 -> 14917.242 | AL29: =+(AJ29-AK29)*$B$15 -> 10679.74 | AM29: =+AJ29-AK29+AL29 -> 224274.54
B30: =+B29+1 -> 1982 | C30: =+C29+1 -> 20 | D30: =+D29*(1+$B$10) -> 1.015 | E30: =+IFERROR(G30/F30,0) -> 164.5 | F30: 10 | G30: 1645 | I30: =+B30 -> 1982 | J30: =+C30+1 -> 21 | K30: =+IF(C30<$B$7,1,0) -> 1 | L30: =+L29 -> 0.15 | M30: =+IF($B$2=1,IF(G30<=2500*12,G30,2500*12),G30) -> 1645 | N30: =+Q29 -> 63 | O30: =+L30*M30*$K30 -> 246.75 | P30: =+N30*$B$14 -> 2.52 | Q30: =+(N30+O30+P30) -> 312.27 | S30: =+I30 -> 1982 | T30: =+J30 -> 21 | U30: =+IF($C30>=$B$7,1,0) -> 0 | V30: =+$B$12*U30 -> 0 | W30: =+U30*$B$13 -> 0 | X30: =+AA29 -> 0 | Y30: =+(G30*V30)*U30 -> 0 | Z30: =+X30*$B$15*U30 -> 0 | AA30: =+(X30+Y30+Z30) -> 0 | AC30: =+AC29+1 -> 1982 | AD30: =+C30 -> 20 | AE30: =+IF(T30<=$X$12,1,0)*F30 -> 10 | AF30: =+IF(T30>$X$12,0,IF($B$2=1,IF($AD30<$B$7,IF(G30<=$B$19*12,G30,$B$19*12),G30),G30)) -> 1645 | AH30: =+AH29+1 -> 2 | AI30: =+AI29+1 -> 66 | AJ30: =+AM29 -> 224274.54 | AK30: =+AK29 -> 14917.242 | AL30: =+(AJ30-AK30)*$B$15 -> 10467.865 | AM30: =+AJ30-AK30+AL30 -> 219825.17
B31: =+B30+1 -> 1983 | C31: =+C30+1 -> 21 | D31: =+D30*(1+$B$10) -> 1.030225 | E31: =+IFERROR(G31/F31,0) -> 194.16667 | F31: 12 | G31: 2330 | I31: =+B31 -> 1983 | J31: =+C31+1 -> 22 | K31: =+IF(C31<$B$7,1,0) -> 1 | L31: =+L30 -> 0.15 | M31: =+IF($B$2=1,IF(G31<=2500*12,G31,2500*12),G31) -> 2330 | N31: =+Q30 -> 312.27 | O31: =+L31*M31*$K31 -> 349.5 | P31: =+N31*$B$14 -> 12.4908 | Q31: =+(N31+O31+P31) -> 674.2608 | S31: =+I31 -> 1983 | T31: =+J31 -> 22 | U31: =+IF($C31>=$B$7,1,0) -> 0 | V31: =+$B$12*U31 -> 0 | W31: =+U31*$B$13 -> 0 | X31: =+AA30 -> 0 | Y31: =+(G31*V31)*U31 -> 0 | Z31: =+X31*$B$15*U31 -> 0 | AA31: =+(X31+Y31+Z31) -> 0 | AC31: =+AC30+1 -> 1983 | AD31: =+C31 -> 21 | AE31: =+IF(T31<=$X$12,1,0)*F31 -> 12 | AF31: =+IF(T31>$X$12,0,IF($B$2=1,IF($AD31<$B$7,IF(G31<=$B$19*12,G31,$B$19*12),G31),G31)) -> 2330 | AH31: =+AH30+1 -> 3 | AI31: =+AI30+1 -> 67 | AJ31: =+AM30 -> 219825.17 | AK31: =+AK30 -> 14917.242 | AL31: =+(AJ31-AK31)*$B$15 -> 10245.396 | AM31: =+AJ31-AK31+AL31 -> 215153.32
B32: =+B31+1 -> 1984 | C32: =+C31+1 -> 22 | D32: =+D31*(1+$B$10) -> 1.0456784 | E32: =+IFERROR(G32/F32,0) -> 204.66667 | F32: 12 | G32: 2456 | I32: =+B32 -> 1984 | J32: =+C32+1 -> 23 | K32: =+IF(C32<$B$7,1,0) -> 1 | L32: =+L31 -> 0.15 | M32: =+IF($B$2=1,IF(G32<=2500*12,G32,2500*12),G32) -> 2456 | N32: =+Q31 -> 674.2608 | O32: =+L32*M32*$K32 -> 368.4 | P32: =+N32*$B$14 -> 26.970432 | Q32: =+(N32+O32+P32) -> 1069.6312 | S32: =+I32 -> 1984 | T32: =+J32 -> 23 | U32: =+IF($C32>=$B$7,1,0) -> 0 | V32: =+$B$12*U32 -> 0 | W32: =+U32*$B$13 -> 0 | X32: =+AA31 -> 0 | Y32: =+(G32*V32)*U32 -> 0 | Z32: =+X32*$B$15*U32 -> 0 | AA32: =+(X32+Y32+Z32) -> 0 | AC32: =+AC31+1 -> 1984 | AD32: =+C32 -> 22 | AE32: =+IF(T32<=$X$12,1,0)*F32 -> 12 | AF32: =+IF(T32>$X$12,0,IF($B$2=1,IF($AD32<$B$7,IF(G32<=$B$19*12,G32,$B$19*12),G32),G32)) -> 2456 | AH32: =+AH31+1 -> 4 | AI32: =+AI31+1 -> 68 | AJ32: =+AM31 -> 215153.32 | AK32: =+AK31 -> 14917.242 | AL32: =+(AJ32-AK32)*$B$15 -> 10011.804 | AM32: =+AJ32-AK32+AL32 -> 210247.88
B33: =+B32+1 -> 1985 | C33: =+C32+1 -> 23 | D33: =+D32*(1+$B$10) -> 1.0613636 | E33: =+IFERROR(G33/F33,0) -> 196.33333 | F33: 12 | G33: 2356 | I33: =+B33 -> 1985 | J33: =+C33+1 -> 24 | K33: =+IF(C33<$B$7,1,0) -> 1 | L33: =+L32 -> 0.15 | M33: =+IF($B$2=1,IF(G33<=2500*12,G33,2500*12),G33) -> 2356 | N33: =+Q32 -> 1069.6312 | O33: =+L33*M33*$K33 -> 353.4 | P33: =+N33*$B$14 -> 42.785249 | Q33: =+(N33+O33+P33) -> 1465.8165 | S33: =+I33 -> 1985 | T33: =+J33 -> 24 | U33: =+IF($C33>=$B$7,1,0) -> 0 | V33: =+$B$12*U33 -> 0 | W33: =+U33*$B$13 -> 0 | X33: =+AA32 -> 0 | Y33: =+(G33*V33)*U33 -> 0 | Z33: =+X33*$B$15*U33 -> 0 | AA33: =+(X33+Y33+Z33) -> 0 | AC33: =+AC32+1 -> 1985 | AD33: =+C33 -> 23 | AE33: =+IF(T33<=$X$12,1,0)*F33 -> 12 | AF33: =+IF(T33>$X$12,0,IF($B$2=1,IF($AD33<$B$7,IF(G33<=$B$19*12,G33,$B$19*12),G33),G33)) -> 2356 | AH33: =+AH32+1 -> 5 | AI33: =+AI32+1 -> 69 | AJ33: =+AM32 -> 210247.88 | AK33: =+AK32 -> 14917.242 | AL33: =+(AJ33-AK33)*$B$15 -> 9766.5321 | AM33: =+AJ33-AK33+AL33 -> 205097.17
B34: =+B33+1 -> 1986 | C34: =+C33+1 -> 24 | D34: =+D33*(1+$B$10) -> 1.077284 | E34: =+IFERROR(G34/F34,0) -> 206.08333 | F34: 12 | G34: 2473 | I34: =+B34 -> 1986 | J34: =+C34+1 -> 25 | K34: =+IF(C34<$B$7,1,0) -> 1 | L34: =+L33 -> 0.15 | M34: =+IF($B$2=1,IF(G34<=2500*12,G34,2500*12),G34) -> 2473 | N34: =+Q33 -> 1465.8165 | O34: =+L34*M34*$K34 -> 370.95 | P34: =+N34*$B$14 -> 58.632659 | Q34: =+(N34+O34+P34) -> 1895.3991 | S34: =+I34 -> 1986 | T34: =+J34 -> 25 | U34: =+IF($C34>=$B$7,1,0) -> 0 | V34: =+$B$12*U34 -> 0 | W34: =+U34*$B$13 -> 0 | X34: =+AA33 -> 0 | Y34: =+(G34*V34)*U34 -> 0 | Z34: =+X34*$B$15*U34 -> 0 | AA34: =+(X34+Y34+Z34) -> 0 | AC34: =+AC33+1 -> 1986 | AD34: =+C34 -> 24 | AE34: =+IF(T34<=$X$12,1,0)*F34 -> 12 | AF34: =+IF(T34>$X$12,0,IF($B$2=1,IF($AD34<$B$7,IF(G34<=$B$19*12,G34,$B$19*12),G34),G34)) -> 2473 | AH34: =+AH33+1 -> 6 | AI34: =+AI33+1 -> 70 | AJ34: =+AM33 -> 205097.17 | AK34: =+AK33 -> 14917.242 | AL34: =+(AJ34-AK34)*$B$15 -> 9508.9966 | AM34: =+AJ34-AK34+AL34 -> 199688.93
B35: =+B34+1 -> 1987 | C35: =+C34+1 -> 25 | D35: =+D34*(1+$B$10) -> 1.0934433 | E35: =+IFERROR(G35/F35,0) -> 276.66667 | F35: 12 | G35: 3320 | I35: =+B35 -> 1987 | J35: =+C35+1 -> 26 | K35: =+IF(C35<$B$7,1,0) -> 1 | L35: =+L34 -> 0.15 | M35: =+IF($B$2=1,IF(G35<=2500*12,G35,2500*12),G35) -> 3320 | N35: =+Q34 -> 1895.3991 | O35: =+L35*M35*$K35 -> 498 | P35: =+N35*$B$14 -> 75.815966 | Q35: =+(N35+O35+P35) -> 2469.2151 | S35: =+I35 -> 1987 | T35: =+J35 -> 26 | U35: =+IF($C35>=$B$7,1,0) -> 0 | V35: =+$B$12*U35 -> 0 | W35: =+U35*$B$13 -> 0 | X35: =+AA34 -> 0 | Y35: =+(G35*V35)*U35 -> 0 | Z35: =+X35*$B$15*U35 -> 0 | AA35: =+(X35+Y35+Z35) -> 0 | AC35: =+AC34+1 -> 1987 | AD35: =+C35 -> 25 | AE35: =+IF(T35<=$X$12,1,0)*F35 -> 12 | AF35: =+IF(T35>$X$12,0,IF($B$2=1,IF($AD35<$B$7,IF(G35<=$B$19*12,G35,$B$19*12),G35),G35)) -> 3320 | AH35: =+AH34+1 -> 7 | AI35: =+AI34+1 -> 71 | AJ35: =+AM34 -> 199688.93 | AK35: =+AK34 -> 14917.242 | AL35: =+(AJ35-AK35)*$B$15 -> 9238.5844 | AM35: =+AJ35-AK35+AL35 -> 194010.27
B36: =+B35+1 -> 1988 | C36: =+C35+1 -> 26 | D36: =+D35*(1+$B$10) -> 1.1098449 | E36: =+IFERROR(G36/F36,0) -> 300.25 | F36: 12 | G36: 3603 | I36: =+B36 -> 1988 | J36: =+C36+1 -> 27 | K36: =+IF(C36<$B$7,1,0) -> 1 | L36: =+L35 -> 0.15 | M36: =+IF($B$2=1,IF(G36<=2500*12,G36,2500*12),G36) -> 3603 | N36: =+Q35 -> 2469.2151 | O36: =+L36*M36*$K36 -> 540.45 | P36: =+N36*$B$14 -> 98.768604 | Q36: =+(N36+O36+P36) -> 3108.4337 | S36: =+I36 -> 1988 | T36: =+J36 -> 27 | U36: =+IF($C36>=$B$7,1,0) -> 0 | V36: =+$B$12*U36 -> 0 | W36: =+U36*$B$13 -> 0 | X36: =+AA35 -> 0 | Y36: =+(G36*V36)*U36 -> 0 | Z36: =+X36*$B$15*U36 -> 0 | AA36: =+(X36+Y36+Z36) -> 0 | AC36: =+AC35+1 -> 1988 | AD36: =+C36 -> 26 | AE36: =+IF(T36<=$X$12,1,0)*F36 -> 12 | AF36: =+IF(T36>$X$12,0,IF($B$2=1,IF($AD36<$B$7,IF(G36<=$B$19*12,G36,$B$19*12),G36),G36)) -> 3603 | AH36: =+AH35+1 -> 8 | AI36: =+AI35+1 -> 72 | AJ36: =+AM35 -> 194010.27 | AK36: =+AK35 -> 14917.242 | AL36: =+(AJ36-AK36)*$B$15 -> 8954.6515 | AM36: =+AJ36-AK36+AL36 -> 188047.68
B37: =+B36+1 -> 1989 | C37: =+C36+1 -> 27 | D37: =+D36*(1+$B$10) -> 1.1264926 | E37: =+IFERROR(G37/F37,0) -> 300.25 | F37: 12 | G37: 3603 | I37: =+B37 -> 1989 | J37: =+C37+1 -> 28 | K37: =+IF(C37<$B$7,1,0) -> 1 | L37: =+L36 -> 0.15 | M37: =+IF($B$2=1,IF(G37<=2500*12,G37,2500*12),G37) -> 3603 | N37: =+Q36 -> 3108.4337 | O37: =+L37*M37*$K37 -> 540.45 | P37: =+N37*$B$14 -> 124.33735 | Q37: =+(N37+O37+P37) -> 3773.2211 | S37: =+I37 -> 1989 | T37: =+J37 -> 28 | U37: =+IF($C37>=$B$7,1,0) -> 0 | V37: =+$B$12*U37 -> 0 | W37: =+U37*$B$13 -> 0 | X37: =+AA36 -> 0 | Y37: =+(G37*V37)*U37 -> 0 | Z37: =+X37*$B$15*U37 -> 0 | AA37: =+(X37+Y37+Z37) -> 0 | AC37: =+AC36+1 -> 1989 | AD37: =+C37 -> 27 | AE37: =+IF(T37<=$X$12,1,0)*F37 -> 12 | AF37: =+IF(T37>$X$12,0,IF($B$2=1,IF($AD37<$B$7,IF(G37<=$B$19*12,G37,$B$19*12),G37),G37)) -> 3603 | AH37: =+AH36+1 -> 9 | AI37: =+AI36+1 -> 73 | AJ37: =+AM36 -> 188047.68 | AK37: =+AK36 -> 14917.242 | AL37: =+(AJ37-AK37)*$B$15 -> 8656.522 | AM37: =+AJ37-AK37+AL37 -> 181786.96
B38: =+B37+1 -> 1990 | C38: =+C37+1 -> 28 | D38: =+D37*(1+$B$10) -> 1.14339 | E38: =+IFERROR(G38/F38,0) -> 302.75 | F38: 12 | G38: 3633 | I38: =+B38 -> 1990 | J38: =+C38+1 -> 29 | K38: =+IF(C38<$B$7,1,0) -> 1 | L38: =+L37 -> 0.15 | M38: =+IF($B$2=1,IF(G38<=2500*12,G38,2500*12),G38) -> 3633 | N38: =+Q37 -> 3773.2211 | O38: =+L38*M38*$K38 -> 544.95 | P38: =+N38*$B$14 -> 150.92884 | Q38: =+(N38+O38+P38) -> 4469.0999 | S38: =+I38 -> 1990 | T38: =+J38 -> 29 | U38: =+IF($C38>=$B$7,1,0) -> 0 | V38: =+$B$12*U38 -> 0 | W38: =+U38*$B$13 -> 0 | X38: =+AA37 -> 0 | Y38: =+(G38*V38)*U38 -> 0 | Z38: =+X38*$B$15*U38 -> 0 | AA38: =+(X38+Y38+Z38) -> 0 | AC38: =+AC37+1 -> 1990 | AD38: =+C38 -> 28 | AE38: =+IF(T38<=$X$12,1,0)*F38 -> 12 | AF38: =+IF(T38>$X$12,0,IF($B$2=1,IF($AD38<$B$7,IF(G38<=$B$19*12,G38,$B$19*12),G38),G38)) -> 3633 | AH38: =+AH37+1 -> 10 | AI38: =+AI37+1 -> 74 | AJ38: =+AM37 -> 181786.96 | AK38: =+AK37 -> 14917.242 | AL38: =+(AJ38-AK38)*$B$15 -> 8343.486 | AM38: =+AJ38-AK38+AL38 -> 175213.21
B39: =+B38+1 -> 1991 | C39: =+C38+1 -> 29 | D39: =+D38*(1+$B$10) -> 1.1605408 | E39: =+IFERROR(G39/F39,0) -> 330.25 | F39: 12 | G39: 3963 | I39: =+B39 -> 1991 | J39: =+C39+1 -> 30 | K39: =+IF(C39<$B$7,1,0) -> 1 | L39: =+L38 -> 0.15 | M39: =+IF($B$2=1,IF(G39<=2500*12,G39,2500*12),G39) -> 3963 | N39: =+Q38 -> 4469.0999 | O39: =+L39*M39*$K39 -> 594.45 | P39: =+N39*$B$14 -> 178.764 | Q39: =+(N39+O39+P39) -> 5242.3139 | S39: =+I39 -> 1991 | T39: =+J39 -> 30 | U39: =+IF($C39>=$B$7,1,0) -> 0 | V39: =+$B$12*U39 -> 0 | W39: =+U39*$B$13 -> 0 | X39: =+AA38 -> 0 | Y39: =+(G39*V39)*U39 -> 0 | Z39: =+X39*$B$15*U39 -> 0 | AA39: =+(X39+Y39+Z39) -> 0 | AC39: =+AC38+1 -> 1991 | AD39: =+C39 -> 29 | AE39: =+IF(T39<=$X$12,1,0)*F39 -> 12 | AF39: =+IF(T39>$X$12,0,IF($B$2=1,IF($AD39<$B$7,IF(G39<=$B$19*12,G39,$B$19*12),G39),G39)) -> 3963 | AH39: =+AH38+1 -> 11 | AI39: =+AI38+1 -> 75 | AJ39: =+AM38 -> 175213.21 | AK39: =+AK38 -> 14917.242 | AL39: =+(AJ39-AK39)*$B$15 -> 8014.7982 | AM39: =+AJ39-AK39+AL39 -> 168310.76
B40: =+B39+1 -> 1992 | C40: =+C39+1 -> 30 | D40: =+D39*(1+$B$10) -> 1.1779489 | E40: =+IFERROR(G40/F40,0) -> 371.75 | F40: 12 | G40: 4461 | I40: =+B40 -> 1992 | J40: =+C40+1 -> 31 | K40: =+IF(C40<$B$7,1,0) -> 1 | L40: =+L39 -> 0.15 | M40: =+IF($B$2=1,IF(G40<=2500*12,G40,2500*12),G40) -> 4461 | N40: =+Q39 -> 5242.3139 | O40: =+L40*M40*$K40 -> 669.15 | P40: =+N40*$B$14 -> 209.69256 | Q40: =+(N40+O40+P40) -> 6121.1565 | S40: =+I40 -> 1992 | T40: =+J40 -> 31 | U40: =+IF($C40>=$B$7,1,0) -> 0 | V40: =+$B$12*U40 -> 0 | W40: =+U40*$B$13 -> 0 | X40: =+AA39 -> 0 | Y40: =+(G40*V40)*U40 -> 0 | Z40: =+X40*$B$15*U40 -> 0 | AA40: =+(X40+Y40+Z40) -> 0 | AC40: =+AC39+1 -> 1992 | AD40: =+C40 -> 30 | AE40: =+IF(T40<=$X$12,1,0)*F40 -> 12 | AF40: =+IF(T40>$X$12,0,IF($B$2=1,IF($AD40<$B$7,IF(G40<=$B$19*12,G40,$B$19*12),G40),G40)) -> 4461 | AH40: =+AH39+1 -> 12 | AI40: =+AI39+1 -> 76 | AJ40: =+AM39 -> 168310.76 | AK40: =+AK39 -> 14917.242 | AL40: =+(AJ40-AK40)*$B$15 -> 7669.676 | AM40: =+AJ40-AK40+AL40 -> 161063.2
B41: =+B40+1 -> 1993 | C41: =+C40+1 -> 31 | D41: =+D40*(1+$B$10) -> 1.1956182 | E41: =+IFERROR(G41/F41,0) -> 512.5 | F41: 12 | G41: 6150 | I41: =+B41 -> 1993 | J41: =+C41+1 -> 32 | K41: =+IF(C41<$B$7,1,0) -> 1 | L41: =+L40 -> 0.15 | M41: =+IF($B$2=1,IF(G41<=2500*12,G41,2500*12),G41) -> 6150 | N41: =+Q40 -> 6121.1565 | O41: =+L41*M41*$K41 -> 922.5 | P41: =+N41*$B$14 -> 244.84626 | Q41: =+(N41+O41+P41) -> 7288.5027 | S41: =+I41 -> 1993 | T41: =+J41 -> 32 | U41: =+IF($C41>=$B$7,1,0) -> 0 | V41: =+$B$12*U41 -> 0 | W41: =+U41*$B$13 -> 0 | X41: =+AA40 -> 0 | Y41: =+(G41*V41)*U41 -> 0 | Z41: =+X41*$B$15*U41 -> 0 | AA41: =+(X41+Y41+Z41) -> 0 | AC41: =+AC40+1 -> 1993 | AD41: =+C41 -> 31 | AE41: =+IF(T41<=$X$12,1,0)*F41 -> 12 | AF41: =+IF(T41>$X$12,0,IF($B$2=1,IF($AD41<$B$7,IF(G41<=$B$19*12,G41,$B$19*12),G41),G41)) -> 6150 | AH41: =+AH40+1 -> 13 | AI41: =+AI40+1 -> 77 | AJ41: =+AM40 -> 161063.2 | AK41: =+AK40 -> 14917.242 | AL41: =+(AJ41-AK41)*$B$15 -> 7307.2977 | AM41: =+AJ41-AK41+AL41 -> 153453.25
... B53: =+B52+1 -> 2005 | C53: =+C52+1 -> 43 | D53: =+D52*(1+$B$10) -> 1.4295028 | E53: =+IFERROR(G53/F53,0) -> 1637.5 | F53: 12 | G53: 19650 | I53: =+B53 -> 2005 | J53: =+C53+1 -> 44 | K53: =+IF(C53<$B$7,1,0) -> 1 | L53: =+L52 -> 0.15 | M53: =+IF($B$2=1,IF(G53<=2500*12,G53,2500*12),G53) -> 19650 | N53: =+Q52 -> 35312.775 | O53: =+L53*M53*$K53 -> 2947.5 | P53: =+N53*$B$14 -> 1412.511 | Q53: =+(N53+O53+P53) -> 39672.786 | S53: =+I53 -> 2005 | T53: =+J53 -> 44 | U53: =+IF($C53>=$B$7,1,0) -> 0 | V53: =+$B$12*U53 -> 0 | W53: =+U53*$B$13 -> 0 | X53: =+AA52 -> 0 | Y53: =+(G53*V53)*U53 -> 0 | Z53: =+X53*$B$15*U53 -> 0 | AA53: =+(X53+Y53+Z53) -> 0 | AC53: =+AC52+1 -> 2005 | AD53: =+C53 -> 43 | AE53: =+IF(T53<=$X$12,1,0)*F53 -> 12 | AF53: =+IF(T53>$X$12,0,IF($B$2=1,IF($AD53<$B$7,IF(G53<=$B$19*12,G53,$B$19*12),G53),G53)) -> 19650 | AH53: =+AH52+1 -> 25 | AI53: =+AI52+1 -> 89 | AJ53: =+AM52 -> 39934.753 | AK53: =+AK52 -> 14917.242 | AL53: =+(AJ53-AK53)*$B$15 -> 1250.8756 | AM53: =+AJ53-AK53+AL53 -> 26268.387
B54: =+B53+1 -> 2006 | C54: =+C53+1 -> 44 | D54: =+D53*(1+$B$10) -> 1.4509454 | E54: =+D54*E53/D53 -> 1662.0625 | F54: 12 | G54: 21245 | I54: =+B54 -> 2006 | J54: =+C54+1 -> 45 | K54: =+IF(C54<$B$7,1,0) -> 1 | L54: =+L53 -> 0.15 | M54: =+IF($B$2=1,IF(G54<=2500*12,G54,2500*12),G54) -> 21245 | N54: =+Q53 -> 39672.786 | O54: =+L54*M54*$K54 -> 3186.75 | P54: =+N54*$B$14 -> 1586.9114 | Q54: =+(N54+O54+P54) -> 44446.448 | S54: =+I54 -> 2006 | T54: =+J54 -> 45 | U54: =+IF($C54>=$B$7,1,0) -> 0 | V54: =+$B$12*U54 -> 0 | W54: =+U54*$B$13 -> 0 | X54: =+AA53 -> 0 | Y54: =+(G54*V54)*U54 -> 0 | Z54: =+X54*$B$15*U54 -> 0 | AA54: =+(X54+Y54+Z54) -> 0 | AC54: =+AC53+1 -> 2006 | AD54: =+C54 -> 44 | AE54: =+IF(T54<=$X$12,1,0)*F54 -> 12 | AF54: =+IF(T54>$X$12,0,IF($B$2=1,IF($AD54<$B$7,IF(G54<=$B$19*12,G54,$B$19*12),G54),G54)) -> 21245 | AH54: =+AH53+1 -> 26 | AI54: =+AI53+1 -> 90 | AJ54: =+AM53 -> 26268.387 | AK54: =+AK53 -> 14917.242 | AL54: =+(AJ54-AK54)*$B$15 -> 567.55724 | AM54: =+AJ54-AK54+AL54 -> 11918.702
B55: =+B54+1 -> 2007 | C55: =+C54+1 -> 45 | D55: =+D54*(1+$B$10) -> 1.4727095 | E55: =+G55/12 -> 2567 | F55: 12 | G55: 30804 | I55: =+B55 -> 2007 | J55: =+C55+1 -> 46 | K55: =+IF(C55<$B$7,1,0) -> 1 | L55: =+L54 -> 0.15 | M55: =+IF($B$2=1,IF(G55<=2500*12,G55,2500*12),G55) -> 30000 | N55: =+Q54 -> 44446.448 | O55: =+L55*M55*$K55 -> 4500 | P55: =+N55*$B$14 -> 1777.8579 | Q55: =+(N55+O55+P55) -> 50724.306 | S55: =+I55 -> 2007 | T55: =+J55 -> 46 | U55: =+IF($C55>=$B$7,1,0) -> 0 | V55: =+$B$12*U55 -> 0 | W55: =+U55*$B$13 -> 0 | X55: =+AA54 -> 0 | Y55: =+(G55*V55)*U55 -> 0 | Z55: =+X55*$B$15*U55 -> 0 | AA55: =+(X55+Y55+Z55) -> 0 | AC55: =+AC54+1 -> 2007 | AD55: =+C55 -> 45 | AE55: =+IF(T55<=$X$12,1,0)*F55 -> 12 | AF55: =+IF(T55>$X$12,0,IF($B$2=1,IF($AD55<$B$7,IF(G55<=$B$19*12,G55,$B$19*12),G55),G55)) -> 30000 | AH55: =+AH54+1 -> 27 | AI55: =+AI54+1 -> 91 | AJ55: =+AM54 -> 11918.702 | AK55: =+AK54 -> 14917.242 | AL55: =+(AJ55-AK55)*$B$15 -> -149.92699 | AM55: =+AJ55-AK55+AL55 -> -3148.4667
B56: =+B55+1 -> 2008 | C56: =+C55+1 -> 46 | D56: =+D55*(1+$B$10) -> 1.4948002 | E56: =+G56/12 -> 2327 | F56: 12 | G56: 27924 | I56: =+B56 -> 2008 | J56: =+C56+1 -> 47 | K56: =+IF(C56<$B$7,1,0) -> 1 | L56: =+L55 -> 0.15 | M56: =+IF($B$2=1,IF(G56<=2500*12,G56,2500*12),G56) -> 27924 | N56: =+Q55 -> 50724.306 | O56: =+L56*M56*$K56 -> 4188.6 | P56: =+N56*$B$14 -> 2028.9722 | Q56: =+(N56+O56+P56) -> 56941.878 | S56: =+I56 -> 2008 | T56: =+J56 -> 47 | U56: =+IF($C56>=$B$7,1,0) -> 0 | V56: =+$B$12*U56 -> 0 | W56: =+U56*$B$13 -> 0 | X56: =+AA55 -> 0 | Y56: =+(G56*V56)*U56 -> 0 | Z56: =+X56*$B$15*U56 -> 0 | AA56: =+(X56+Y56+Z56) -> 0 | AC56: =+AC55+1 -> 2008 | AD56: =+C56 -> 46 | AE56: =+IF(T56<=$X$12,1,0)*F56 -> 12 | AF56: =+IF(T56>$X$12,0,IF($B$2=1,IF($AD56<$B$7,IF(G56<=$B$19*12,G56,$B$19*12),G56),G56)) -> 27924 | AH56: =+AH55+1 -> 28 | AI56: =+AI55+1 -> 92 | AJ56: =+AM55 -> -3148.4667 | AK56: =+AK55 -> 14917.242 | AL56: =+(AJ56-AK56)*$B$15 -> -903.28543 | AM56: =+AJ56-AK56+AL56 -> -18968.994
B57: =+B56+1 -> 2009 | C57: =+C56+1 -> 47 | D57: =+D56*(1+$B$10) -> 1.5172222 | E57: =+G57/12 -> 2124.5 | F57: 12 | G57: 25494 | I57: =+B57 -> 2009 | J57: =+C57+1 -> 48 | K57: =+IF(C57<$B$7,1,0) -> 1 | L57: =+L56 -> 0.15 | M57: =+IF($B$2=1,IF(G57<=2500*12,G57,2500*12),G57) -> 25494 | N57: =+Q56 -> 56941.878 | O57: =+L57*M57*$K57 -> 3824.1 | P57: =+N57*$B$14 -> 2277.6751 | Q57: =+(N57+O57+P57) -> 63043.653 | S57: =+I57 -> 2009 | T57: =+J57 -> 48 | U57: =+IF($C57>=$B$7,1,0) -> 0 | V57: =+$B$12*U57 -> 0 | W57: =+U57*$B$13 -> 0 | X57: =+AA56 -> 0 | Y57: =+(G57*V57)*U57 -> 0 | Z57: =+X57*$B$15*U57 -> 0 | AA57: =+(X57+Y57+Z57) -> 0 | AC57: =+AC56+1 -> 2009 | AD57: =+C57 -> 47 | AE57: =+IF(T57<=$X$12,1,0)*F57 -> 12 | AF57: =+IF(T57>$X$12,0,IF($B$2=1,IF($AD57<$B$7,IF(G57<=$B$19*12,G57,$B$19*12),G57),G57)) -> 25494 | AH57: =+AH56+1 -> 29 | AI57: =+AI56+1 -> 93 | AJ57: =+AM56 -> -18968.994 | AK57: =+AK56 -> 14917.242 | AL57: =+(AJ57-AK57)*$B$15 -> -1694.3118 | AM57: =+AJ57-AK57+AL57 -> -35580.548
B58: =+B57+1 -> 2010 | C58: =+C57+1 -> 48 | D58: =+D57*(1+$B$10) -> 1.5399805 | E58: =+G58/12 -> 2398.4167 | F58: 12 | G58: 28781 | I58: =+B58 -> 2010 | J58: =+C58+1 -> 49 | K58: =+IF(C58<$B$7,1,0) -> 1 | L58: =+L57 -> 0.15 | M58: =+IF($B$2=1,IF(G58<=2500*12,G58,2500*12),G58) -> 28781 | N58: =+Q57 -> 63043.653 | O58: =+L58*M58*$K58 -> 4317.15 | P58: =+N58*$B$14 -> 2521.7461 | Q58: =+(N58+O58+P58) -> 69882.549 | S58: =+I58 -> 2010 | T58: =+J58 -> 49 | U58: =+IF($C58>=$B$7,1,0) -> 0 | V58: =+$B$12*U58 -> 0 | W58: =+U58*$B$13 -> 0 | X58: =+AA57 -> 0 | Y58: =+(G58*V58)*U58 -> 0 | Z58: =+X58*$B$15*U58 -> 0 | AA58: =+(X58+Y58+Z58) -> 0 | AC58: =+AC57+1 -> 2010 | AD58: =+C58 -> 48 | AE58: =+IF(T58<=$X$12,1,0)*F58 -> 12 | AF58: =+IF(T58>$X$12,0,IF($B$2=1,IF($AD58<$B$7,IF(G58<=$B$19*12,G58,$B$19*12),G58),G58)) -> 28781 | AH58: =+AH57+1 -> 30 | AI58: =+AI57+1 -> 94 | AJ58: =+AM57 -> -35580.548 | AK58: =+AK57 -> 14917.242 | AL58: =+(AJ58-AK58)*$B$15 -> -2524.8895 | AM58: =+AJ58-AK58+AL58 -> -53022.679
B59: =+B58+1 -> 2011 | C59: =+C58+1 -> 49 | D59: =+D58*(1+$B$10) -> 1.5630802 | E59: =+G59/12 -> 2160.5833 | F59: 12 | G59: 25927 | I59: =+B59 -> 2011 | J59: =+C59+1 -> 50 | K59: =+IF(C59<$B$7,1,0) -> 1 | L59: =+L58 -> 0.15 | M59: =+IF($B$2=1,IF(G59<=2500*12,G59,2500*12),G59) -> 25927 | N59: =+Q58 -> 69882.549 | O59: =+L59*M59*$K59 -> 3889.05 | P59: =+N59*$B$14 -> 2795.302 | Q59: =+(N59+O59+P59) -> 76566.901 | S59: =+I59 -> 2011 | T59: =+J59 -> 50 | U59: =+IF($C59>=$B$7,1,0) -> 0 | V59: =+$B$12*U59 -> 0 | W59: =+U59*$B$13 -> 0 | X59: =+AA58 -> 0 | Y59: =+(G59*V59)*U59 -> 0 | Z59: =+X59*$B$15*U59 -> 0 | AA59: =+(X59+Y59+Z59) -> 0 | AC59: =+AC58+1 -> 2011 | AD59: =+C59 -> 49 | AE59: =+IF(T59<=$X$12,1,0)*F59 -> 12 | AF59: =+IF(T59>$X$12,0,IF($B$2=1,IF($AD59<$B$7,IF(G59<=$B$19*12,G59,$B$19*12),G59),G59)) -> 25927 | AH59: =+AH58+1 -> 31 | AI59: =+AI58+1 -> 95 | AJ59: =+AM58 -> -53022.679 | AK59: =+AK58 -> 14917.242 | AL59: =+(AJ59-AK59)*$B$15 -> -3396.996 | AM59: =+AJ59-AK59+AL59 -> -71336.917
B60: =+B59+1 -> 2012 | C60: =+C59+1 -> 50 | D60: =+D59*(1+$B$10) -> 1.5865264 | E60: =+G60/12 -> 2317 | F60: 12 | G60: 27804 | I60: =+B60 -> 2012 | J60: =+C60+1 -> 51 | K60: =+IF(C60<$B$7,1,0) -> 1 | L60: =+L59 -> 0.15 | M60: =+IF($B$2=1,IF(G60<=2500*12,G60,2500*12),G60) -> 27804 | N60: =+Q59 -> 76566.901 | O60: =+L60*M60*$K60 -> 4170.6 | P60: =+N60*$B$14 -> 3062.676 | Q60: =+(N60+O60+P60) -> 83800.177 | S60: =+I60 -> 2012 | T60: =+J60 -> 51 | U60: =+IF($C60>=$B$7,1,0) -> 0 | V60: =+$B$12*U60 -> 0 | W60: =+U60*$B$13 -> 0 | X60: =+AA59 -> 0 | Y60: =+(G60*V60)*U60 -> 0 | Z60: =+X60*$B$15*U60 -> 0 | AA60: =+(X60+Y60+Z60) -> 0 | AC60: =+AC59+1 -> 2012 | AD60: =+C60 -> 50 | AE60: =+IF(T60<=$X$12,1,0)*F60 -> 12 | AF60: =+IF(T60>$X$12,0,IF($B$2=1,IF($AD60<$B$7,IF(G60<=$B$19*12,G60,$B$19*12),G60),G60)) -> 27804 | AH60: =+AH59+1 -> 32 | AI60: =+AI59+1 -> 96 | AJ60: =+AM59 -> -71336.917 | AK60: =+AK59 -> 14917.242 | AL60: =+(AJ60-AK60)*$B$15 -> -4312.7079 | AM60: =+AJ60-AK60+AL60 -> -90566.866
B61: =+B60+1 -> 2013 | C61: =+C60+1 -> 51 | D61: =+D60*(1+$B$10) -> 1.6103243 | E61: =+G61/12 -> 2374.5 | F61: 12 | G61: 28494 | I61: =+B61 -> 2013 | J61: =+C61+1 -> 52 | K61: =+IF(C61<$B$7,1,0) -> 1 | L61: =+L60 -> 0.15 | M61: =+IF($B$2=1,IF(G61<=2500*12,G61,2500*12),G61) -> 28494 | N61: =+Q60 -> 83800.177 | O61: =+L61*M61*$K61 -> 4274.1 | P61: =+N61*$B$14 -> 3352.0071 | Q61: =+(N61+O61+P61) -> 91426.284 | S61: =+I61 -> 2013 | T61: =+J61 -> 52 | U61: =+IF($C61>=$B$7,1,0) -> 0 | V61: =+$B$12*U61 -> 0 | W61: =+U61*$B$13 -> 0 | X61: =+AA60 -> 0 | Y61: =+(G61*V61)*U61 -> 0 | Z61: =+X61*$B$15*U61 -> 0 | AA61: =+(X61+Y61+Z61) -> 0 | AC61: =+AC60+1 -> 2013 | AD61: =+C61 -> 51 | AE61: =+IF(T61<=$X$12,1,0)*F61 -> 12 | AF61: =+IF(T61>$X$12,0,IF($B$2=1,IF($AD61<$B$7,IF(G61<=$B$19*12,G61,$B$19*12),G61),G61)) -> 28494 | AH61: =+AH60+1 -> 33 | AI61: =+AI60+1 -> 97 | AJ61: =+AM60 -> -90566.866 | AK61: =+AK60 -> 14917.242 | AL61: =+(AJ61-AK61)*$B$15 -> -5274.2054 | AM61: =+AJ61-AK61+AL61 -> -110758.31
B62: =+B61+1 -> 2014 | C62: =+C61+1 -> 52 | D62: =+D61*(1+$B$10) -> 1.6344792 | E62: =+G62/12 -> 2374.5 | F62: 12 | G62: 28494 | I62: =+B62 -> 2014 | J62: =+C62+1 -> 53 | K62: =+IF(C62<$B$7,1,0) -> 1 | L62: =+L61 -> 0.15 | M62: =+IF($B$2=1,IF(G62<=2500*12,G62,2500*12),G62) -> 28494 | N62: =+Q61 -> 91426.284 | O62: =+L62*M62*$K62 -> 4274.1 | P62: =+N62*$B$14 -> 3657.0514 | Q62: =+(N62+O62+P62) -> 99357.435 | S62: =+I62 -> 2014 | T62: =+J62 -> 53 | U62: =+IF($C62>=$B$7,1,0) -> 0 | V62: =+$B$12*U62 -> 0 | W62: =+U62*$B$13 -> 0 | X62: =+AA61 -> 0 | Y62: =+(G62*V62)*U62 -> 0 | Z62: =+X62*$B$15*U62 -> 0 | AA62: =+(X62+Y62+Z62) -> 0 | AC62: =+AC61+1 -> 2014 | AD62: =+C62 -> 52 | AE62: =+IF(T62<=$X$12,1,0)*F62 -> 12 | AF62: =+IF(T62>$X$12,0,IF($B$2=1,IF($AD62<$B$7,IF(G62<=$B$19*12,G62,$B$19*12),G62),G62)) -> 28494 | AH62: =+AH61+1 -> 34 | AI62: =+AI61+1 -> 98 | AJ62: =+AM61 -> -110758.31 | AK62: =+AK61 -> 14917.242 | AL62: =+(AJ62-AK62)*$B$15 -> -6283.7778 | AM62: =+AJ62-AK62+AL62 -> -131959.33
B63: =+B62+1 -> 2015 | C63: =+C62+1 -> 53 | D63: =+D62*(1+$B$10) -> 1.6589964 | E63: =+G63/12 -> 2439.9167 | F63: 12 | G63: 29279 | I63: =+B63 -> 2015 | J63: =+C63+1 -> 54 | K63: =+IF(C63<$B$7,1,0) -> 1 | L63: =+L62 -> 0.15 | M63: =+IF($B$2=1,IF(G63<=2500*12,G63,2500*12),G63) -> 29279 | N63: =+Q62 -> 99357.435 | O63: =+L63*M63*$K63 -> 4391.85 | P63: =+N63*$B$14 -> 3974.2974 | Q63: =+(N63+O63+P63) -> 107723.58 | S63: =+I63 -> 2015 | T63: =+J63 -> 54 | U63: =+IF($C63>=$B$7,1,0) -> 0 | V63: =+$B$12*U63 -> 0 | W63: =+U63*$B$13 -> 0 | X63: =+AA62 -> 0 | Y63: =+(G63*V63)*U63 -> 0 | Z63: =+X63*$B$15*U63 -> 0 | AA63: =+(X63+Y63+Z63) -> 0 | AC63: =+AC62+1 -> 2015 | AD63: =+C63 -> 53 | AE63: =+IF(T63<=$X$12,1,0)*F63 -> 12 | AF63: =+IF(T63>$X$12,0,IF($B$2=1,IF($AD63<$B$7,IF(G63<=$B$19*12,G63,$B$19*12),G63),G63)) -> 29279 | AH63: =+AH62+1 -> 35 | AI63: =+AI62+1 -> 99 | AJ63: =+AM62 -> -131959.33 | AK63: =+AK62 -> 14917.242 | AL63: =+(AJ63-AK63)*$B$15 -> -7343.8288 | AM63: =+AJ63-AK63+AL63 -> -154220.4
B64: =+B63+1 -> 2016 | C64: =+C63+1 -> 54 | D64: =+D63*(1+$B$10) -> 1.6838813 | E64: =+G64/12 -> 2374.5 | F64: 12 | G64: 28494 | I64: =+B64 -> 2016 | J64: =+C64+1 -> 55 | K64: =+IF(C64<$B$7,1,0) -> 1 | L64: =+L63 -> 0.15 | M64: =+IF($B$2=1,IF(G64<=2500*12,G64,2500*12),G64) -> 28494 | N64: =+Q63 -> 107723.58 | O64: =+L64*M64*$K64 -> 4274.1 | P64: =+N64*$B$14 -> 4308.9433 | Q64: =+(N64+O64+P64) -> 116306.63 | S64: =+I64 -> 2016 | T64: =+J64 -> 55 | U64: =+IF($C64>=$B$7,1,0) -> 0 | V64: =+$B$12*U64 -> 0 | W64: =+U64*$B$13 -> 0 | X64: =+AA63 -> 0 | Y64: =+(G64*V64)*U64 -> 0 | Z64: =+X64*$B$15*U64 -> 0 | AA64: =+(X64+Y64+Z64) -> 0 | AC64: =+AC63+1 -> 2016 | AD64: =+C64 -> 54 | AE64: =+IF(T64<=$X$12,1,0)*F64 -> 12 | AF64: =+IF(T64>$X$12,0,IF($B$2=1,IF($AD64<$B$7,IF(G64<=$B$19*12,G64,$B$19*12),G64),G64)) -> 28494 | AH64: =+AH63+1 -> 36 | AI64: =+AI63+1 -> 100 | AJ64: =+AM63 -> -154220.4 | AK64: =+AK63 -> 14917.242 | AL64: =+(AJ64-AK64)*$B$15 -> -8456.8823 | AM64: =+AJ64-AK64+AL64 -> -177594.53
B65: =+B64+1 -> 2017 | C65: =+C64+1 -> 55 | D65: =+D64*(1+$B$10) -> 1.7091395 | E65: =+G65/12 -> 2706.1667 | F65: 12 | G65: 32474 | I65: =+B65 -> 2017 | J65: =+C65+1 -> 56 | K65: =+IF(C65<$B$7,1,0) -> 1 | L65: =+L64 -> 0.15 | M65: =+IF($B$2=1,IF(G65<=2500*12,G65,2500*12),G65) -> 30000 | N65: =+Q64 -> 116306.63 | O65: =+L65*M65*$K65 -> 4500 | P65: =+N65*$B$14 -> 4652.265 | Q65: =+(N65+O65+P65) -> 125458.89 | S65: =+I65 -> 2017 | T65: =+J65 -> 56 | U65: =+IF($C65>=$B$7,1,0) -> 0 | V65: =+$B$12*U65 -> 0 | W65: =+U65*$B$13 -> 0 | X65: =+AA64 -> 0 | Y65: =+(G65*V65)*U65 -> 0 | Z65: =+X65*$B$15*U65 -> 0 | AA65: =+(X65+Y65+Z65) -> 0 | AC65: =+AC64+1 -> 2017 | AD65: =+C65 -> 55 | AE65: =+IF(T65<=$X$12,1,0)*F65 -> 12 | AF65: =+IF(T65>$X$12,0,IF($B$2=1,IF($AD65<$B$7,IF(G65<=$B$19*12,G65,$B$19*12),G65),G65)) -> 30000 | AH65: =+AH64+1 -> 37 | AI65: =+AI64+1 -> 101 | AJ65: =+AM64 -> -177594.53 | AK65: =+AK64 -> 14917.242 | AL65: =+(AJ65-AK65)*$B$15 -> -9625.5885 | AM65: =+AJ65-AK65+AL65 -> -202137.36
B66: =+B65+1 -> 2018 | C66: =+C65+1 -> 56 | D66: =+D65*(1+$B$10) -> 1.7347766 | E66: =+G66/12 -> 3110.75 | F66: 12 | G66: 37329 | I66: =+B66 -> 2018 | J66: =+C66+1 -> 57 | K66: =+IF(C66<$B$7,1,0) -> 1 | L66: =+L65 -> 0.15 | M66: =+IF($B$2=1,IF(G66<=2500*12,G66,2500*12),G66) -> 30000 | N66: =+Q65 -> 125458.89 | O66: =+L66*M66*$K66 -> 4500 | P66: =+N66*$B$14 -> 5018.3556 | Q66: =+(N66+O66+P66) -> 134977.25 | S66: =+I66 -> 2018 | T66: =+J66 -> 57 | U66: =+IF($C66>=$B$7,1,0) -> 0 | V66: =+$B$12*U66 -> 0 | W66: =+U66*$B$13 -> 0 | X66: =+AA65 -> 0 | Y66: =+(G66*V66)*U66 -> 0 | Z66: =+X66*$B$15*U66 -> 0 | AA66: =+(X66+Y66+Z66) -> 0 | AC66: =+AC65+1 -> 2018 | AD66: =+C66 -> 56 | AE66: =+IF(T66<=$X$12,1,0)*F66 -> 12 | AF66: =+IF(T66>$X$12,0,IF($B$2=1,IF($AD66<$B$7,IF(G66<=$B$19*12,G66,$B$19*12),G66),G66)) -> 30000 | AH66: =+AH65+1 -> 38 | AI66: =+AI65+1 -> 102 | AJ66: =+AM65 -> -202137.36 | AK66: =+AK65 -> 14917.242 | AL66: =+(AJ66-AK66)*$B$15 -> -10852.73 | AM66: =+AJ66-AK66+AL66 -> -227907.33
... B71: =+B70+1 -> 2023 | C71: =+C70+1 -> 61 | D71: =+D70*(1+$B$10) -> 1.8688471 | E71: =+G71/12 -> 3117.1667 | F71: 12 | G71: 37406 | I71: =+B71 -> 2023 | J71: =+C71+1 -> 62 | K71: =+IF(C71<$B$7,1,0) -> 1 | L71: =+L70 -> 0.15 | M71: =+IF($B$2=1,IF(G71<=2500*12,G71,2500*12),G71) -> 30000 | N71: =+Q70 -> 177013.38 | O71: =+L71*M71*$K71 -> 4500 | P71: =+N71*$B$14 -> 7080.535 | Q71: =+(N71+O71+P71) -> 188593.91 | S71: =+I71 -> 2023 | T71: =+J71 -> 62 | U71: =+IF($C71>=$B$7,1,0) -> 0 | V71: =+$B$12*U71 -> 0 | W71: =+U71*$B$13 -> 0 | X71: =+AA70 -> 0 | Y71: =+(G71*V71)*U71 -> 0 | Z71: =+X71*$B$15*U71 -> 0 | AA71: =+(X71+Y71+Z71) -> 0 | AC71: =+AC70+1 -> 2023 | AD71: =+C71 -> 61 | AE71: =+IF(T71<=$X$12,1,0)*F71 -> 12 | AF71: =+IF(T71>$X$12,0,IF($B$2=1,IF($AD71<$B$7,IF(G71<=$B$19*12,G71,$B$19*12),G71),G71)) -> 30000 | AH71: =+AH70+1 -> 43 | AI71: =+AI70+1 -> 107 | AJ71: =+AM70 -> -344532.72 | AK71: =+AK70 -> 14917.242 | AL71: =+(AJ71-AK71)*$B$15 -> -17972.498 | AM71: =+AJ71-AK71+AL71 -> -377422.46
B72: =+B71+1 -> 2024 | C72: =+C71+1 -> 62 | D72: =+D71*(1+$B$10) -> 1.8968798 | E72: =+E71 -> 3117.1667 | F72: 12 | G72: =+G71 -> 37406 | I72: =+B72 -> 2024 | J72: =+C72+1 -> 63 | K72: =+IF(C72<$B$7,1,0) -> 1 | L72: =+L71 -> 0.15 | M72: =+IF($B$2=1,IF(G72<=2500*12,G72,2500*12),G72) -> 30000 | N72: =+Q71 -> 188593.91 | O72: =+L72*M72*$K72 -> 4500 | P72: =+N72*$B$14 -> 7543.7564 | Q72: =+(N72+O72+P72) -> 200637.67 | S72: =+I72 -> 2024 | T72: =+J72 -> 63 | U72: =+IF($C72>=$B$7,1,0) -> 0 | V72: =+$B$12*U72 -> 0 | W72: =+U72*$B$13 -> 0 | X72: =+AA71 -> 0 | Y72: =+(G72*V72)*U72 -> 0 | Z72: =+X72*$B$15*U72 -> 0 | AA72: =+(X72+Y72+Z72) -> 0 | AC72: =+AC71+1 -> 2024 | AD72: =+C72 -> 62 | AE72: =+IF(T72<=$X$12,1,0)*F72 -> 12 | AF72: =+IF(T72>$X$12,0,IF($B$2=1,IF($AD72<$B$7,IF(G72<=$B$19*12,G72,$B$19*12),G72),G72)) -> 30000 | AH72: =+AH71+1 -> 44 | AI72: =+AI71+1 -> 108 | AJ72: =+AM71 -> -377422.46 | AK72: =+AK71 -> 14917.242 | AL72: =+(AJ72-AK72)*$B$15 -> -19616.985 | AM72: =+AJ72-AK72+AL72 -> -411956.69
B73: =+B72+1 -> 2025 | C73: =+C72+1 -> 63 | D73: =+D72*(1+$B$10) -> 1.925333 | E73: =+E72 -> 3117.1667 | F73: 12 | G73: =+G72 -> 37406 | I73: =+B73 -> 2025 | J73: =+C73+1 -> 64 | K73: =+IF(C73<$B$7,1,0) -> 0 | L73: =+L72 -> 0.15 | M73: =+IF($B$2=1,IF(G73<=2500*12,G73,2500*12),G73) -> 30000 | N73: =+Q72 -> 200637.67 | O73: =+L73*M73*$K73 -> 0 | P73: =+N73*$B$14 -> 8025.5067 | Q73: =+(N73+O73+P73) -> 208663.17 | S73: =+I73 -> 2025 | T73: =+J73 -> 64 | U73: =+IF($C73>=$B$7,1,0) -> 1 | V73: =+$B$12*U73 -> 0.15 | W73: =+U73*$B$13 -> 0.15 | X73: =+AA72 -> 0 | Y73: =+(G73*V73)*U73 -> 5610.9 | Z73: =+X73*$B$15*U73 -> 0 | AA73: =+(X73+Y73+Z73) -> 5610.9 | AC73: =+AC72+1 -> 2025 | AD73: =+C73 -> 63 | AE73: =+IF(T73<=$X$12,1,0)*F73 -> 12 | AF73: =+IF(T73>$X$12,0,IF($B$2=1,IF($AD73<$B$7,IF(G73<=$B$19*12,G73,$B$19*12),G73),G73)) -> 37406 | AH73: =+AH72+1 -> 45 | AI73: =+AI72+1 -> 109 | AJ73: =+AM72 -> -411956.69 | AK73: =+AK72 -> 14917.242 | AL73: =+(AJ73-AK73)*$B$15 -> -21343.696 | AM73: =+AJ73-AK73+AL73 -> -448217.63
B74: =+B73+1 -> 2026 | C74: =+C73+1 -> 64 | D74: =+D73*(1+$B$10) -> 1.954213 | E74: =+E73 -> 3117.1667 | F74: 12 | G74: =+G73 -> 37406 | I74: =+B74 -> 2026 | J74: =+C74+1 -> 65 | K74: =+IF(C74<$B$7,1,0) -> 0 | L74: =+L73 -> 0.15 | M74: =+IF($B$2=1,IF(G74<=2500*12,G74,2500*12),G74) -> 30000 | N74: =+Q73 -> 208663.17 | O74: =+L74*M74*$K74 -> 0 | P74: =+N74*$B$14 -> 8346.5269 | Q74: =+(N74+O74+P74) -> 217009.7 | S74: =+I74 -> 2026 | T74: =+J74 -> 65 | U74: =+IF($C74>=$B$7,1,0) -> 1 | V74: =+$B$12*U74 -> 0.15 | W74: =+U74*$B$13 -> 0.15 | X74: =+AA73 -> 5610.9 | Y74: =+(G74*V74)*U74 -> 5610.9 | Z74: =+X74*$B$15*U74 -> 280.545 | AA74: =+(X74+Y74+Z74) -> 11502.345 | AC74: =+AC73+1 -> 2026 | AD74: =+C74 -> 64 | AE74: =+IF(T74<=$X$12,1,0)*F74 -> 12 | AF74: =+IF(T74>$X$12,0,IF($B$2=1,IF($AD74<$B$7,IF(G74<=$B$19*12,G74,$B$19*12),G74),G74)) -> 37406 | AH74: =+AH73+1 -> 46 | AI74: =+AI73+1 -> 110 | AJ74: =+AM73 -> -448217.63 | AK74: =+AK73 -> 14917.242 | AL74: =+(AJ74-AK74)*$B$15 -> -23156.743 | AM74: =+AJ74-AK74+AL74 -> -486291.61
B75: =+B74+1 -> 2027 | C75: =+C74+1 -> 65 | D75: =+D74*(1+$B$10) -> 1.9835262 | E75: =+E74 -> 3117.1667 | F75: 12 | G75: =+G74 -> 37406 | I75: =+B75 -> 2027 | J75: =+C75+1 -> 66 | K75: =+IF(C75<$B$7,1,0) -> 0 | L75: =+L74 -> 0.15 | M75: =+IF($B$2=1,IF(G75<=2500*12,G75,2500*12),G75) -> 30000 | N75: =+Q74 -> 217009.7 | O75: =+L75*M75*$K75 -> 0 | P75: =+N75*$B$14 -> 8680.388 | Q75: =+(N75+O75+P75) -> 225690.09 | S75: =+I75 -> 2027 | T75: =+J75 -> 66 | U75: =+IF($C75>=$B$7,1,0) -> 1 | V75: =+$B$12*U75 -> 0.15 | W75: =+U75*$B$13 -> 0.15 | X75: =+AA74 -> 11502.345 | Y75: =+(G75*V75)*U75 -> 5610.9 | Z75: =+X75*$B$15*U75 -> 575.11725 | AA75: =+(X75+Y75+Z75) -> 17688.362 | AC75: =+AC74+1 -> 2027 | AD75: =+C75 -> 65 | AE75: =+IF(T75<=$X$12,1,0)*F75 -> 0 | AF75: =+IF(T75>$X$12,0,IF($B$2=1,IF($AD75<$B$7,IF(G75<=$B$19*12,G75,$B$19*12),G75),G75)) -> 0 | AH75: =+AH74+1 -> 47 | AI75: =+AI74+1 -> 111 | AJ75: =+AM74 -> -486291.61 | AK75: =+AK74 -> 14917.242 | AL75: =+(AJ75-AK75)*$B$15 -> -25060.443 | AM75: =+AJ75-AK75+AL75 -> -526269.29
B76: =+B75+1 -> 2028 | C76: =+C75+1 -> 66 | D76: =+D75*(1+$B$10) -> 2.0132791 | E76: =+E75 -> 3117.1667 | F76: 12 | G76: =+G75 -> 37406 | I76: =+B76 -> 2028 | J76: =+C76+1 -> 67 | K76: =+IF(C76<$B$7,1,0) -> 0 | L76: =+L75 -> 0.15 | M76: =+IF($B$2=1,IF(G76<=2500*12,G76,2500*12),G76) -> 30000 | N76: =+Q75 -> 225690.09 | O76: =+L76*M76*$K76 -> 0 | P76: =+N76*$B$14 -> 9027.6035 | Q76: =+(N76+O76+P76) -> 234717.69 | S76: =+I76 -> 2028 | T76: =+J76 -> 67 | U76: =+IF($C76>=$B$7,1,0) -> 1 | V76: =+$B$12*U76 -> 0.15 | W76: =+U76*$B$13 -> 0.15 | X76: =+AA75 -> 17688.362 | Y76: =+(G76*V76)*U76 -> 5610.9 | Z76: =+X76*$B$15*U76 -> 884.41811 | AA76: =+(X76+Y76+Z76) -> 24183.68 | AC76: =+AC75+1 -> 2028 | AD76: =+C76 -> 66 | AE76: =+IF(T76<=$X$12,1,0)*F76 -> 0 | AF76: =+IF(T76>$X$12,0,IF($B$2=1,IF($AD76<$B$7,IF(G76<=$B$19*12,G76,$B$19*12),G76),G76)) -> 0 | AH76: =+AH75+1 -> 48 | AI76: =+AI75+1 -> 112 | AJ76: =+AM75 -> -526269.29 | AK76: =+AK75 -> 14917.242 | AL76: =+(AJ76-AK76)*$B$15 -> -27059.327 | AM76: =+AJ76-AK76+AL76 -> -568245.86
B77: =+B76+1 -> 2029 | C77: =+C76+1 -> 67 | D77: =+D76*(1+$B$10) -> 2.0434783 | E77: =+E76 -> 3117.1667 | F77: 12 | G77: =+G76 -> 37406 | I77: =+B77 -> 2029 | J77: =+C77+1 -> 68 | K77: =+IF(C77<$B$7,1,0) -> 0 | L77: =+L76 -> 0.15 | M77: =+IF($B$2=1,IF(G77<=2500*12,G77,2500*12),G77) -> 30000 | N77: =+Q76 -> 234717.69 | O77: =+L77*M77*$K77 -> 0 | P77: =+N77*$B$14 -> 9388.7077 | Q77: =+(N77+O77+P77) -> 244106.4 | S77: =+I77 -> 2029 | T77: =+J77 -> 68 | U77: =+IF($C77>=$B$7,1,0) -> 1 | V77: =+$B$12*U77 -> 0.15 | W77: =+U77*$B$13 -> 0.15 | X77: =+AA76 -> 24183.68 | Y77: =+(G77*V77)*U77 -> 5610.9 | Z77: =+X77*$B$15*U77 -> 1209.184 | AA77: =+(X77+Y77+Z77) -> 31003.764 | AC77: =+AC76+1 -> 2029 | AD77: =+C77 -> 67 | AE77: =+IF(T77<=$X$12,1,0)*F77 -> 0 | AF77: =+IF(T77>$X$12,0,IF($B$2=1,IF($AD77<$B$7,IF(G77<=$B$19*12,G77,$B$19*12),G77),G77)) -> 0 | AH77: =+AH76+1 -> 49 | AI77: =+AI76+1 -> 113 | AJ77: =+AM76 -> -568245.86 | AK77: =+AK76 -> 14917.242 | AL77: =+(AJ77-AK77)*$B$15 -> -29158.155 | AM77: =+AJ77-AK77+AL77 -> -612321.26

Sheet salidaformulas
A2: SEXO | B2: M
A3: EDAD ENTRADA | B3: 22 | E3: TIPO DE SISTEMA | F3: COMPONENTE 1 | G3: COMPONENTE 2 | H3: personas aprox
A4: EDAD DE JUBILACION | B4: 62 | E4: SISTEMA DE BENEFICIO DEFINIDO | F4: COMPONENTE SOLIDARIO | H4: 600K | I4: SOLIDARIO> EL BENEFICIO SE CALCULA CON UNA FORMULA SENCILLA, PERO QUE PUEDE HACER QUE EL SISTEMA QUIEBRE SINO HAY SUSTENTO PARA EL FINANCIAMIENTO
A5: AÑOS EN SISTEMA | B5: =+B4-B3 -> 40 | E5: SISTEMA MIXTO | F5: COMPONENTE SOLIDARIO | G5: AHORRO | H5: 600K | I5: AHORRO> EL BENEFICIO SE CALCULA CONFORME A LO QUE ESTA ACUMULADO EN LA CUENTA DE AHORRO
A6: INTERES | B6: 0.04 | E6: SISTEMA CUENTA INDIVIDUAL | G6: AHORRO
A7: FACTOR PENSIONAMIENTO MANCOMUNADO | B7: 5.1543312
A9: A SALARIO MENSUAL | B9: B CUOTAS PROMEDIO PAGADAS POR AÑO | C9: C AÑOS EN EL SISTEMA | D9: D CUOTAS TOTALES PAGADAS =B*C | E9: E AÑOS DE TRABAJO FORMALES | F9: F SALARIO ANNUAL =B*A | G9: G SALARIO PRIMER PILAR o SOLIDARIO =$500*B | H9: H SALARIO SEGUNDO PILAR o COMP AHORRO =F-G | I9: I CUOTA ANUAL TOTAL =15%*F | J9: J CUOTA ANUAL CUENTA INDIVIDUAL 2do Pilar Ahorro =10%*H | K9: K PROMEDIO ANUAL MEJORES 10 AÑOS TOTAL | L9: L PROMEDIO ANUAL MEJORES 10 AÑOS 1er PILAR | M9: M PENSION MENSUAL COMPONENTE BD 1ER PILAR =(60%*L+ (1.25%*(E-20)*L))/12 | N9: N CUENTA INDIVIDUAL ACUMULADA 2DO PILAR SMIXTO Ley 51 al 4% A EDAD JUBILACION. Ver Nota** | O9: O PENSION COMPONENTE AHORRO 2do PILAR =(N/1000)*factor Pensionamiento | P9: P CUENTA INDIVIDUAL ACUMULADA TOTAL NUEVA LEY 462 al 4% A EDAD DE JUBILACION. VER NOTA ** | Q9: Q JUBILACIÓN P NUEVA LEY 462 =(P/1000)*factor Pensionamiento | R9: R JUBILACION SEGUN LEY 51 SISTEMA MIXTO =M+O | S9: S JUBILACIÓN LEY 51 SEBD =(60%*K+ (1.25%*(E-20)*K))/12 | T9: T TASA DE REEMPLAZO NUEVA LEY=Q/K | U9: U TASAS DE REEMPLAZO Ley 51 Mixto=R/K | V9: V TASAS DE REEMPLAZO Ley 51 SEBD=S/K | W9: AÑOS EN EL SISTEMA | X9: AÑOS DE TRABAJO FORMALES
A10: 700 | B10: 6 | C10: =+B5 -> 40 | D10: =+B10*C10 -> 240 | E10: =+D10/12 -> 20 | F10: =+B10*A10 -> 4200 | G10: =+IF(A10>500,500*B10,A10*B10) -> 3000 | H10: =+F10-G10 -> 1200 | I10: =0.15*F10 -> 630 | J10: =+H10*0.1 -> 120 | K10: =+F10 -> 4200 | L10: =+G10 -> 3000 | M10: =(60%*G10+1.25%*(E10-20)*G10)/12 -> 150 | N10: =+(((1+$B$6)^C10-1)/$B$6)*J10 -> 11403.062 | O10: =+N10*0.001*$B$7 -> 58.775157 | P10: =+(((1+$B$6)^C10-1)/$B$6)*I10 -> 59866.075 | Q10: =+P10*0.001*$B$7 -> 308.56958 | R10: =+O10+M10 -> 208.77516 | S10: =(60%*F10+1.25%*(E10-20)*F10)/12 -> 210 | T10: =+IFERROR((Q10*12)/$K10,0) -> 0.88162736 | U10: =+IFERROR((R10*12)/$K10,0) -> 0.59650045 | V10: =+IFERROR(S10*12/K10,0) -> 0.6 | W10: =+C10 -> 40 | X10: =+E10 -> 20
A11: =+A10 -> 700 | B11: 7.5 | C11: =+C10 -> 40 | D11: =+B11*C11 -> 300 | E11: =+D11/12 -> 25 | F11: =+B11*A11 -> 5250 | G11: =+IF(A11>500,500*B11,A11*B11) -> 3750 | H11: =+F11-G11 -> 1500 | I11: =0.15*F11 -> 787.5 | J11: =+H11*0.1 -> 150 | K11: =+F11 -> 5250 | L11: =+G11 -> 3750 | M11: =(60%*G11+1.25%*(E11-20)*G11)/12 -> 207.03125 | N11: =+(((1+$B$6)^C11-1)/$B$6)*J11 -> 14253.827 | O11: =+N11*0.001*$B$7 -> 73.468947 | P11: =+(((1+$B$6)^C11-1)/$B$6)*I11 -> 74832.594 | Q11: =+P11*0.001*$B$7 -> 385.71197 | R11: =+O11+M11 -> 280.5002 | S11: =(60%*F11+1.25%*(E11-20)*F11)/12 -> 289.84375 | T11: =+IFERROR((Q11*12)/$K11,0) -> 0.88162736 | U11: =+IFERROR((R11*12)/$K11,0) -> 0.64114331 | V11: =+IFERROR(S11*12/K11,0) -> 0.6625 | W11: =+C11 -> 40 | X11: =+E11 -> 25
A12: =+A11 -> 700 | B12: 9 | C12: =+C11 -> 40 | D12: =+B12*C12 -> 360 | E12: =+D12/12 -> 30 | F12: =+B12*A12 -> 6300 | G12: =+IF(A12>500,500*B12,A12*B12) -> 4500 | H12: =+F12-G12 -> 1800 | I12: =0.15*F12 -> 945 | J12: =+H12*0.1 -> 180 | K12: =+F12 -> 6300 | L12: =+G12 -> 4500 | M12: =(60%*G12+1.25%*(E12-20)*G12)/12 -> 271.875 | N12: =+(((1+$B$6)^C12-1)/$B$6)*J12 -> 17104.593 | O12: =+N12*0.001*$B$7 -> 88.162736 | P12: =+(((1+$B$6)^C12-1)/$B$6)*I12 -> 89799.112 | Q12: =+P12*0.001*$B$7 -> 462.85437 | R12: =+O12+M12 -> 360.03774 | S12: =(60%*F12+1.25%*(E12-20)*F12)/12 -> 380.625 | T12: =+IFERROR((Q12*12)/$K12,0) -> 0.88162736 | U12: =+IFERROR((R12*12)/$K12,0) -> 0.68578616 | V12: =+IFERROR(S12*12/K12,0) -> 0.725 | W12: =+C12 -> 40 | X12: =+E12 -> 30
A13: =+A12 -> 700 | B13: 10.5 | C13: =+C12 -> 40 | D13: =+B13*C13 -> 420 | E13: =+D13/12 -> 35 | F13: =+B13*A13 -> 7350 | G13: =+IF(A13>500,500*B13,A13*B13) -> 5250 | H13: =+F13-G13 -> 2100 | I13: =0.15*F13 -> 1102.5 | J13: =+H13*0.1 -> 210 | K13: =+F13 -> 7350 | L13: =+G13 -> 5250 | M13: =(60%*G13+1.25%*(E13-20)*G13)/12 -> 344.53125 | N13: =+(((1+$B$6)^C13-1)/$B$6)*J13 -> 19955.358 | O13: =+N13*0.001*$B$7 -> 102.85653 | P13: =+(((1+$B$6)^C13-1)/$B$6)*I13 -> 104765.63 | Q13: =+P13*0.001*$B$7 -> 539.99676 | R13: =+O13+M13 -> 447.38778 | S13: =(60%*F13+1.25%*(E13-20)*F13)/12 -> 482.34375 | T13: =+IFERROR((Q13*12)/$K13,0) -> 0.88162736 | U13: =+IFERROR((R13*12)/$K13,0) -> 0.73042902 | V13: =+IFERROR(S13*12/K13,0) -> 0.7875 | W13: =+C13 -> 40 | X13: =+E13 -> 35
A14: =+A13 -> 700 | B14: 12 | C14: =+C13 -> 40 | D14: =+B14*C14 -> 480 | E14: =+D14/12 -> 40 | F14: =+B14*A14 -> 8400 | G14: =+IF(A14>500,500*B14,A14*B14) -> 6000 | H14: =+F14-G14 -> 2400 | I14: =0.15*F14 -> 1260 | J14: =+H14*0.1 -> 240 | K14: =+F14 -> 8400 | L14: =+G14 -> 6000 | M14: =(60%*G14+1.25%*(E14-20)*G14)/12 -> 425 | N14: =+(((1+$B$6)^C14-1)/$B$6)*J14 -> 22806.124 | O14: =+N14*0.001*$B$7 -> 117.55031 | P14: =+(((1+$B$6)^C14-1)/$B$6)*I14 -> 119732.15 | Q14: =+P14*0.001*$B$7 -> 617.13915 | R14: =+O14+M14 -> 542.55031 | S14: =(60%*F14+1.25%*(E14-20)*F14)/12 -> 595 | T14: =+IFERROR((Q14*12)/$K14,0) -> 0.88162736 | U14: =+IFERROR((R14*12)/$K14,0) -> 0.77507188 | V14: =+IFERROR(S14*12/K14,0) -> 0.85 | W14: =+C14 -> 40 | X14: =+E14 -> 40
A17: Nota>**

Sheet calculo 20
B1: DATOS BASICOS | BH1: BENEFICIO DE JUBILACION CSS SEBD
B2: SISTEMA | F2: 1 | BH2: CUOTAS APORTADAS | BM2: =+SUM(K28:K76) -> 240
B3: SEXO | F3: =+salidaformulas!B2 -> M | Q3: MIXTO | AA3: CAPITALIZACIÓN SOLIDARIA | BH3: CUOTAS EN EXCESO A DENSIDAD MIN | BM3: =+IF(BM2>240,BM2-F13,0) -> 0
B4: EDAD ENTRADA | F4: =+salidaformulas!B3 -> 22 | I4: SOLIDARIO | BH4: TASA DE REEMPLAZO AJUSTADA SEBD LEY 51 | BM4: =IF(F7<=7,BN4,BN4*AF13) -> 0.6 | BN4: =IF(AND(BM2>=180,BM2<240),($F$14+INT(BM3/12)*$F$15)*BM2/240,IF(BM2<180,0,($F$14+INT(BM3/12)*$F$15))) -> 0.6
B5: EDAD ACTUAL DIA DE REFORMA | F5: =+F4 -> 22 | J5: Mej. Salario Anual | K5: Mej Salario Anual | S5: Mej. Salario Anual | T5: Mej Salario Anual | BH5: PENSION ANNUAL A RECIBIR | BM5: =+BM6*12 -> 3180
B6: EDAD DE JUBILACION | F6: =+salidaformulas!B4 -> 62 | I6: Mejores Años | J6: TOTAL | K6: Primer Pilar | R6: Mejores Años | S6: TOTAL | T6: Primer Pilar | BH6: PENSION MENSUAL A RECIBIR | BM6: =IF(BM2>=240,MAX(MAX(BL8:BL10),265),MAX(BL8:BL10)) -> 265
B7: AÑOS PARA JUBILARSE | F7: =+F6-F5 -> 40 | I7: 1 | J7: =LARGE($G$28:$G$65,I7) -> 4200 | K7: =LARGE($L$28:$L$65,I7) -> 3000 | R7: 1 | S7: =+J7 -> 4200 | T7: =+K7 -> 3000 | BL7: PENSION | BM7: PROM. ANUAL | BN7: PROM.MENSUAL
B8: % CUOTA APLICADO ANTES VIGENCIA NVA LEY | F8: 0.15 | I8: 2 | J8: =LARGE($G$28:$G$65,I8) -> 4200 | K8: =LARGE($L$28:$L$65,I8) -> 3000 | R8: 2 | S8: =+J8 -> 4200 | T8: =+K8 -> 3000 | BH8: CALCULO DE LOS MEJORES 10 AÑOS | BL8: =+IF($BM$4*BM8/12>1500,1500,$BM$4*BM8/12) -> 210 | BM8: {=+AVERAGE(LARGE($G$28:$G$76,ROW(INDIRECT("1:10"))))} -> 4200
B9: % CUOTA EMPLEADO EMPLEADOR NUEVA LEY | F9: 0.135 | I9: 3 | J9: =LARGE($G$28:$G$65,I9) -> 4200 | K9: =LARGE($L$28:$L$65,I9) -> 3000 | R9: 3 | S9: =+J9 -> 4200 | T9: =+K9 -> 3000 | BH9: CALCULO DE LOS MEJORES 15 AÑOS (300 CUOTAS Y PROM>=$2,000) | BL9: =+IF($BM$4*BM9/12>2000,2000,$BM$4*BM9/12) -> 0 | BM9: {=IF(AND(BM2>300,AVERAGE(LARGE($G$28:$G$76,ROW(INDIRECT("1:15"))))>=24000),AVERAGE(LARGE($G$28:$G$76,ROW(INDIRECT("1:15")))),0)} -> 0
B10: % XIII EMPLEADO EMPLEADOR NUEVA LEY | F10: 0.18 | I10: 4 | J10: =LARGE($G$28:$G$65,I10) -> 4200 | K10: =LARGE($L$28:$L$65,I10) -> 3000 | R10: 4 | S10: =+J10 -> 4200 | T10: =+K10 -> 3000 | AA10: SCGS-CUANDO VIENE DEL SEBD o SM | BH10: CALCULO DE LOS MEJORES 20 AÑOS (360 cuotas y prom>=$2,500) | BL10: =+IF($BM$4*BM10/12>2500,2500,$BM$4*BM10/12) -> 0 | BM10: {=IF(AND(BM2>360,AVERAGE(LARGE($G$28:$G$76,ROW(INDIRECT("1:20"))))>=30000),AVERAGE(LARGE($G$28:$G$76,ROW(INDIRECT("1:20")))),0)} -> 0
B11: TASA DE RETORNO INVERSIONES ANTES VIG LEY | F11: 0.04 | I11: 5 | J11: =LARGE($G$28:$G$65,I11) -> 4200 | K11: =LARGE($L$28:$L$65,I11) -> 3000 | R11: 5 | S11: =+J11 -> 4200 | T11: =+K11 -> 3000 | AA11: EDAD JUBILACION | AF11: =+F6 -> 62 | AK11: RESULTADO COMPARATIVO | AO11: MONTO | AP11: REEMPLAZO MEJ.AÑOS | BH11: TASA DE REEMPLAZO FINAL DE ESTE CALCULO | BM11: =+BM5/VLOOKUP(MAX(BL8:BL10),BL8:BM10,2,0) -> 0.75714286
B12: TASA RETORNO INVERSIONES PROMEDIO | F12: 0.04 | I12: 6 | J12: =LARGE($G$28:$G$65,I12) -> 4200 | K12: =LARGE($L$28:$L$65,I12) -> 3000 | R12: 6 | S12: =+J12 -> 4200 | T12: =+K12 -> 3000 | AA12: FONDO AHORRADO COP ANTES VIGENCIA NVA LEY | AF12: =+VLOOKUP(AF11,$AB$28:$AI$76,8,FALSE) -> 0 | AG12: R | AK12: PENSION A RECIBIR DEL SEBD | AO12: =+L18 -> 210 | AP12: =+AO12/(J16/12) -> 0.6
A13: A | B13: DENSIDAD MINIMA DE CUOTAS LEY 51 | F13: 240 | I13: 7 | J13: =LARGE($G$28:$G$65,I13) -> 4200 | K13: =LARGE($L$28:$L$65,I13) -> 3000 | R13: 7 | S13: =+J13 -> 4200 | T13: =+K13 -> 3000 | W13: VP | X13: RA*ax | AA13: FACTOR DESCUENTO | AF13: =+IF(AND($B$20=1,$F$2<>1),100%,IF($F$3="M",VLOOKUP(AF11,descuento!$A$6:$B$32,2,FALSE),VLOOKUP(AF11,descuento!$C$6:$D$32,2,FALSE))) -> 1 | AK13: PENSION A RECIBIR SISTEMA MIXTO | AO13: =+U22 -> 208.77516 | AP13: =+AO13/(S17/12) -> 0.59650045 | AV13: FONDO TOTAL APLICABLE | BB13: =+VLOOKUP(AF11,$AW$28:$BE$76,9,FALSE) -> 59866.075 | BH13: BENEFICIO DEL SISTEMA MIXTO
A14: B | B14: TASA DE REEMPLAZO INICIAL LEY 51 | F14: 0.6 | I14: 8 | J14: =LARGE($G$28:$G$65,I14) -> 4200 | K14: =LARGE($L$28:$L$65,I14) -> 3000 | R14: 8 | S14: =+J14 -> 4200 | T14: =+K14 -> 3000 | W14: VP/ax | X14: 12*RM | AA14: FONDO AHORRADO COP DESPUES VIGENCIA NVA LEY | AF14: =+VLOOKUP(AF11,$AL$28:$AT$76,9,FALSE) -> 59866.075 | AG14: S | AK14: PENSION A RECIBIR DEL SCGS | AO14: =+AF17 -> 308.56958 | AP14: =+AO14/(S16/12) -> 0.88162736 | AV14: FACTOR PENSION X MIL | BB14: =+AF16 -> 5.1543312
A15: C | B15: TASA DE REEMPLAZO ADICIONAL LEY 51 | F15: 0.0125 | I15: 9 | J15: =LARGE($G$28:$G$65,I15) -> 4200 | K15: =LARGE($L$28:$L$65,I15) -> 3000 | R15: 9 | S15: =+J15 -> 4200 | T15: =+K15 -> 3000 | W15: vp * (1/ax) | AA15: FONDO TOTAL APLICABLE | AF15: =+AF14+AF12*AF13 -> 59866.075 | AG15: T=R+S | AK15: PENSION A RECIBIR SI ENTRA NUEVO | AO15: =+BB15 -> 308.56958 | AP15: =+AO15/(S17/12) -> 0.88162736 | AV15: PENSION SCGS MENSUAL | BB15: =+BB13*0.001*BB14 -> 308.56958 | BH15: PROMEDIO ANUAL MEJORES 10 AÑOS PRIMER PILAR | BM15: {=+AVERAGE(LARGE($L$28:$L$76,ROW(INDIRECT("1:10"))))} -> 3000
B16: SALMAX MENSUAL COTIZADO ANTES VIG NVA LEY | F16: 2500 | I16: 10 | J16: =LARGE($G$28:$G$65,I16) -> 4200 | K16: =LARGE($L$28:$L$65,I16) -> 3000 | R16: 10 | S16: =+J16 -> 4200 | T16: =+K16 -> 3000 | AA16: FACTOR PENSION X MIL | AF16: =+VLOOKUP(AF11,'bases renta'!$K$20:$L$65,2,FALSE) -> 5.1543312 | AG16: U | AV16: REEMPLAZO MEJ.AÑOS | BB16: =+BB15/(J17/12) -> 0.88162736 | BH16: PENSION MENSUAL A RECIBIR PRIMER PILAR | BM16: =+BM15*BM4/12 -> 150
B17: PORCENTAJE DE CUOTA OP DESCONTADA SMP | F17: 0.035 | H17: F | I17: PROMEDIO ANUAL | J17: =+AVERAGE(J7:J16) -> 4200 | K17: =+AVERAGE(K7:K16) -> 3000 | Q17: F | R17: PROMEDIO ANUAL | S17: =+J17 -> 4200 | T17: =+K17 -> 3000 | U17: J | AA17: PENSION SCGS MENSUAL | AF17: =+AF15*0.001*AF16 -> 308.56958 | AG17: V=(T/1000)*U | BH17: AHORRO PENSIONAL EDAD JUBILACION | BM17: =+VLOOKUP(AF11,$R$28:$Y$76,8,FALSE) -> 11403.062
B18: CRECIMIENTO SALARIAL CADA DOS AÑOS | F18: 0 | I18: CUOTAS | J18: =+BM2 -> 240 | K18: PENSION MENSUAL SEBD | L18: =+MIN(J17*J20/12,F16) -> 210 | M18: G=(F*E)/12 | R18: CUOTAS | S18: =+J18 -> 240 | T18: PENSION MENSUAL 1er pilarBD | U18: =+(K17*S20)/12 -> 150 | V18: K=(E*J)/12 | W18: REEMPLAZO MEJ.AÑOS | X18: =+U22/(J17/12) -> 0.59650045 | Y18: P=O/(E/12) | AA18: REEMPLAZO MEJ.AÑOS | AF18: =+AF17/(J17/12) -> 0.88162736 | AG18: W=V/(E/12) | BH18: FACTOR DE PENSIONAMIENTO XMIL | BM18: =+AF16 -> 5.1543312
B19: SALARIO INICIAL | F19: =+salidaformulas!A10 -> 700 | H19: D | I19: EXCESO DENSIDAD | J19: =+BM3 -> 0 | K19: SALARIO PROMEDIO TOTAL MENSUAL COTIZADO | L19: =+F23 -> 350 | M19: H | R19: EXCESO DENSIDAD | S19: =+J19 -> 0 | T19: AHORRO PERSONAL | U19: =+BM17 -> 11403.062 | V19: L | W19: SALARIO PROMEDIO TOTAL MENSUAL COTIZADO | X19: =+L19 -> 350 | Y19: =+M19 -> H | AA19: SALARIO PROMEDIO TOTAL MENSUAL COTIZADO | AF19: =+X19 -> 350 | AG19: H | BH19: PENSION MENSUAL 2do PILAR | BM19: =+(BM17/1000)*BM18 -> 58.775157
B20: cuotas pagadas por año | F20: 6 | H20: E=B+C*D | I20: REEMPLAZO MEJ.AÑOS | J20: =+BM4 -> 0.6 | K20: TASA BRUTA REEMPLAZO | L20: =+L18/L19 -> 0.6 | M20: I=G/H | Q20: E | R20: REEMPLAZO MEJ.AÑOS | S20: =+J20 -> 0.6 | T20: FACTOR PENSIONAMIENTO VITALICIO | U20: =+BM18 -> 5.1543312 | V20: M | W20: TASA BRUTA REEMPLAZO | X20: =+U22/L19 -> 0.59650045 | Y20: Q=O/H | AA20: TASA BRUTA REEMPLAZO | AF20: =+AF17/L19 -> 0.88162736 | AG20: X=V/H | BH20: PENSION FINAL SISTEMA MIXTO | BM20: =IF(BM2>=240,MAX(BM16+BM19,265),BM16+BM19) -> 265
C21: TOTAL CUOTAS MENSUALES | F21: =+SUMIF(F28:F76,">0") -> 240 | G21: =+F21/12 -> 20 | T21: PENSION MENSUAL 2do PILAR | U21: =+U19*0.001*U20 -> 58.775157 | V21: N=(L/1000)*M | BH21: TASA DE REEMPLAZO FINAL DE ESTE CALCULO | BM21: =+BM20*12/VLOOKUP(MAX($BL$8:$BL$10),$BL$8:$BN$10,2,0) -> 0.75714286
C22: SALARIO PROMEDIO ANNUAL | F22: =+AVERAGEIF(G28:G76,">0") -> 4200 | T22: PENSION TOTAL A RECIBIR | U22: =+U21+U18 -> 208.77516 | V22: O=N+K
C23: PROMEDIO MENSUALIZADO | F23: =+F22/12 -> 350 | T23: tasa capitalizacion mixto | U23: 0.04
B24: Tabla 1 | I24: Tabla 2 | Q24: Tabla 3 | AA24: Tabla 4 | AK24: Tabla 5 | AV24: Tabla 6
B25: Datos Básicos | I25: SALARIOS PARA CALCULO PROMEDIO MEJORES | Q25: SISTEMA DE ACUMULACION DEL SISTEMA MIXTO | AA25: ACUMULACION SCGS ANTES DE LA ENTRADA EN VIGENCIA | AK25: ACUMULACION SCGS DESPUES DE LA ENTRADA EN VIGENCIA | AV25: ACUMULACION DESDE EL INICIO DENTRO DEL SISTEMA DE CAPITALIZACION CON GARANTIA SOLIDARIA
B26: AÑO | C26: EDAD INI AÑO | D26: CREC. SALARIO | E26: SALARIO MENSUAL | F26: CUOTAS APORTADAS | G26: SALARIO ANUAL | I26: AÑO | J26: EDAD | K26: CUOTAS APORTADAS | L26: SALARIO COTIZADO 1er PILAR SISTEMA MIXTO ANUAL | M26: SALARIO COTIZADO SEGUNDO PILAR ANUAL | N26: SALARIO COTIZADO PARA PROMEDIO ANUAL | O26: SALARIO COTIZADO PARA PROMEDIO MENSUAL | Q26: AÑO | R26: EDAD FIN AÑO | S26: INDICADOR | T26: TASA O-P SALARIO | U26: SALARIO SEGUNDO PILAR | V26: AHORRO PENSIONAL INICIAL | W26: APORTES | X26: INTERESES | Y26: AHORRO PENSIONAL FINAL | AA26: AÑO | AB26: EDAD FIN AÑO | AC26: INDICADOR | AD26: TASA O-P SALARIO | AE26: SALARIO ANUAL CON MAX 2500 MENSUAL | AF26: AHORRO PENSIONAL INICIAL | AG26: APORTES | AH26: INTERESES | AI26: AHORRO PENSIONAL FINAL | AK26: AÑO | AL26: EDAD FIN AÑO | AM26: INDICADOR | AN26: TASA O-P SALARIO | AO26: TASA O-P XIII | AP26: SALARIO ANUAL SIN MAXIMO | AQ26: AHORRO PENSIONAL INICIAL | AR26: APORTES | AS26: INTERESES | AT26: AHORRO PENSIONAL INICIAL | AV26: AÑO | AW26: EDAD FIN AÑO | AX26: INDICADOR | AY26: TASA O-P SALARIO | AZ26: TASA O-P XIII | BA26: SALARIO ANUAL SIN MAXIMO | BB26: AHORRO PENSIONAL INICIAL | BC26: APORTES | BD26: INTERESES | BE26: AHORRO PENSIONAL INICIAL
B28: 1 | C28: =+F4 -> 22 | D28: 1 | E28: =+IF($C28>=$F$6,0,$F$19*D28) -> 700 | F28: =+IF($C28>=$F$6,0,$F$20) -> 6 | G28: =+E28*F28 -> 4200 | I28: =+B28 -> 1 | J28: =+C28 -> 22 | K28: =+IF(AL28<=$AF$11,1,0)*F28 -> 6 | L28: =+IF(AL28>$AF$11,0,IF(E28>500,500*F28,E28*F28)) -> 3000 | M28: =+IF(AL28>$AF$11,0,IF(G28-L28 <= 0,0,G28-L28)) -> 1200 | N28: =+IF($F$7<7,L28+M28,IF(AL28>$AF$11,0,IF($F$2=1,IF($J28<$F$5,IF(G28<=$F$16*12,G28,$F$16*12),G28),G28))) -> 4200 | O28: =+IFERROR(N28/K28,0) -> 700 | Q28: =+I28 -> 1 | R28: =+J28+1 -> 23 | S28: =+IF(R28<=$AF$11,1,0) -> 1 | T28: =+$F$9-$F$17 -> 0.1 | U28: =+M28 -> 1200 | V28: =+Y27 -> 0 | W28: =+T28*U28*S28 -> 120 | X28: =+$U$23*V28 -> 0 | Y28: =+(V28+W28+X28) -> 120 | AA28: =+B28 -> 1 | AB28: =+C28+1 -> 23 | AC28: =+IF(C28<$F$5,1,0) -> 0 | AD28: =F8 -> 0.15 | AE28: =+IF($F$2=1,IF(G28<=2500*12,G28,2500*12),G28) -> 4200 | AF28: =+AI27 -> 0 | AG28: =+AD28*AE28*$AC28 -> 0 | AH28: =+AF28*$F$11 -> 0 | AI28: =+(AF28+AG28+AH28) -> 0 | AK28: =+AA28 -> 1 | AL28: =+AB28 -> 23 | AM28: =+IF($C28>=$F$5,1,0) -> 1 | AN28: =+$F$9*AM28 -> 0.135 | AO28: =+AM28*$F$10 -> 0.18 | AP28: =+G28 -> 4200 | AQ28: =+AT27 -> 0 | AR28: =+(AN28*AP28+AO28*(AP28/12))*AM28 -> 630 | AS28: =+AQ28*$F$12 -> 0 | AT28: =+(AQ28+AR28+AS28) -> 630 | AV28: =+AK28 -> 1 | AW28: =+AL28 -> 23 | AX28: 1 | AY28: =+$F$9*AX28 -> 0.135 | AZ28: =+AX28*$F$10 -> 0.18 | BA28: =+G28 -> 4200 | BB28: =+BE27 -> 0 | BC28: =+(AY28*BA28+AZ28*(BA28/12))*AX28 -> 630 | BD28: =+BB28*$F$12 -> 0 | BE28: =+(BB28+BC28+BD28) -> 630
B29: =+B28+1 -> 2 | C29: =+C28+1 -> 23 | D29: =+D28*(1+$F$18) -> 1 | E29: =+IF($C29>=$F$6,0,$F$19*D29) -> 700 | F29: =+IF($C29>=$F$6,0,$F$20) -> 6 | G29: =+E29*F29 -> 4200 | I29: =+I28+1 -> 2 | J29: =+C29 -> 23 | K29: =+IF(AL29<=$AF$11,1,0)*F29 -> 6 | L29: =+IF(AL29>$AF$11,0,IF(E29>500,500*F29,E29*F29)) -> 3000 | M29: =+IF(AL29>$AF$11,0,IF(G29-L29 <= 0,0,G29-L29)) -> 1200 | N29: =+IF($F$7<7,L29+M29,IF(AL29>$AF$11,0,IF($F$2=1,IF($J29<$F$5,IF(G29<=$F$16*12,G29,$F$16*12),G29),G29))) -> 4200 | O29: =+IFERROR(N29/K29,0) -> 700 | Q29: =+I29 -> 2 | R29: =+J29+1 -> 24 | S29: =+IF(R29<=$AF$11,1,0) -> 1 | T29: =+T28 -> 0.1 | U29: =+M29 -> 1200 | V29: =+Y28 -> 120 | W29: =+T29*U29*S29 -> 120 | X29: =+$U$23*V29 -> 4.8 | Y29: =+(V29+W29+X29) -> 244.8 | AA29: =+B29 -> 2 | AB29: =+C29+1 -> 24 | AC29: =+IF(C29<$F$5,1,0) -> 0 | AD29: =+AD28 -> 0.15 | AE29: =+IF($F$2=1,IF(G29<=2500*12,G29,2500*12),G29) -> 4200 | AF29: =+AI28 -> 0 | AG29: =+AD29*AE29*$AC29 -> 0 | AH29: =+AF29*$F$11 -> 0 | AI29: =+(AF29+AG29+AH29) -> 0 | AK29: =+AA29 -> 2 | AL29: =+AB29 -> 24 | AM29: =+IF($C29>=$F$5,1,0) -> 1 | AN29: =+$F$9*AM29 -> 0.135 | AO29: =+AM29*$F$10 -> 0.18 | AP29: =+G29 -> 4200 | AQ29: =+AT28 -> 630 | AR29: =+(AN29*AP29+AO29*(AP29/12))*AM29 -> 630 | AS29: =+AQ29*$F$12 -> 25.2 | AT29: =+(AQ29+AR29+AS29) -> 1285.2 | AV29: =+AK29 -> 2 | AW29: =+AL29 -> 24 | AX29: 1 | AY29: =+$F$9*AX29 -> 0.135 | AZ29: =+AX29*$F$10 -> 0.18 | BA29: =+G29 -> 4200 | BB29: =+BE28 -> 630 | BC29: =+(AY29*BA29+AZ29*(BA29/12))*AX29 -> 630 | BD29: =+BB29*$F$12 -> 25.2 | BE29: =+(BB29+BC29+BD29) -> 1285.2
B30: =+B29+1 -> 3 | C30: =+C29+1 -> 24 | D30: =+D29*(1+$F$18) -> 1 | E30: =+IF($C30>=$F$6,0,$F$19*D30) -> 700 | F30: =+IF($C30>=$F$6,0,$F$20) -> 6 | G30: =+E30*F30 -> 4200 | I30: =+I29+1 -> 3 | J30: =+C30 -> 24 | K30: =+IF(AL30<=$AF$11,1,0)*F30 -> 6 | L30: =+IF(AL30>$AF$11,0,IF(E30>500,500*F30,E30*F30)) -> 3000 | M30: =+IF(AL30>$AF$11,0,IF(G30-L30 <= 0,0,G30-L30)) -> 1200 | N30: =+IF($F$7<7,L30+M30,IF(AL30>$AF$11,0,IF($F$2=1,IF($J30<$F$5,IF(G30<=$F$16*12,G30,$F$16*12),G30),G30))) -> 4200 | O30: =+IFERROR(N30/K30,0) -> 700 | Q30: =+I30 -> 3 | R30: =+J30+1 -> 25 | S30: =+IF(R30<=$AF$11,1,0) -> 1 | T30: =+T29 -> 0.1 | U30: =+M30 -> 1200 | V30: =+Y29 -> 244.8 | W30: =+T30*U30*S30 -> 120 | X30: =+$U$23*V30 -> 9.792 | Y30: =+(V30+W30+X30) -> 374.592 | AA30: =+B30 -> 3 | AB30: =+C30+1 -> 25 | AC30: =+IF(C30<$F$5,1,0) -> 0 | AD30: =+AD29 -> 0.15 | AE30: =+IF($F$2=1,IF(G30<=2500*12,G30,2500*12),G30) -> 4200 | AF30: =+AI29 -> 0 | AG30: =+AD30*AE30*$AC30 -> 0 | AH30: =+AF30*$F$11 -> 0 | AI30: =+(AF30+AG30+AH30) -> 0 | AK30: =+AA30 -> 3 | AL30: =+AB30 -> 25 | AM30: =+IF($C30>=$F$5,1,0) -> 1 | AN30: =+$F$9*AM30 -> 0.135 | AO30: =+AM30*$F$10 -> 0.18 | AP30: =+G30 -> 4200 | AQ30: =+AT29 -> 1285.2 | AR30: =+(AN30*AP30+AO30*(AP30/12))*AM30 -> 630 | AS30: =+AQ30*$F$12 -> 51.408 | AT30: =+(AQ30+AR30+AS30) -> 1966.608 | AV30: =+AK30 -> 3 | AW30: =+AL30 -> 25 | AX30: 1 | AY30: =+$F$9*AX30 -> 0.135 | AZ30: =+AX30*$F$10 -> 0.18 | BA30: =+G30 -> 4200 | BB30: =+BE29 -> 1285.2 | BC30: =+(AY30*BA30+AZ30*(BA30/12))*AX30 -> 630 | BD30: =+BB30*$F$12 -> 51.408 | BE30: =+(BB30+BC30+BD30) -> 1966.608
B31: =+B30+1 -> 4 | C31: =+C30+1 -> 25 | D31: =+D30*(1+$F$18) -> 1 | E31: =+IF($C31>=$F$6,0,$F$19*D31) -> 700 | F31: =+IF($C31>=$F$6,0,$F$20) -> 6 | G31: =+E31*F31 -> 4200 | I31: =+I30+1 -> 4 | J31: =+C31 -> 25 | K31: =+IF(AL31<=$AF$11,1,0)*F31 -> 6 | L31: =+IF(AL31>$AF$11,0,IF(E31>500,500*F31,E31*F31)) -> 3000 | M31: =+IF(AL31>$AF$11,0,IF(G31-L31 <= 0,0,G31-L31)) -> 1200 | N31: =+IF($F$7<7,L31+M31,IF(AL31>$AF$11,0,IF($F$2=1,IF($J31<$F$5,IF(G31<=$F$16*12,G31,$F$16*12),G31),G31))) -> 4200 | O31: =+IFERROR(N31/K31,0) -> 700 | Q31: =+I31 -> 4 | R31: =+J31+1 -> 26 | S31: =+IF(R31<=$AF$11,1,0) -> 1 | T31: =+T30 -> 0.1 | U31: =+M31 -> 1200 | V31: =+Y30 -> 374.592 | W31: =+T31*U31*S31 -> 120 | X31: =+$U$23*V31 -> 14.98368 | Y31: =+(V31+W31+X31) -> 509.57568 | AA31: =+B31 -> 4 | AB31: =+C31+1 -> 26 | AC31: =+IF(C31<$F$5,1,0) -> 0 | AD31: =+AD30 -> 0.15 | AE31: =+IF($F$2=1,IF(G31<=2500*12,G31,2500*12),G31) -> 4200 | AF31: =+AI30 -> 0 | AG31: =+AD31*AE31*$AC31 -> 0 | AH31: =+AF31*$F$11 -> 0 | AI31: =+(AF31+AG31+AH31) -> 0 | AK31: =+AA31 -> 4 | AL31: =+AB31 -> 26 | AM31: =+IF($C31>=$F$5,1,0) -> 1 | AN31: =+$F$9*AM31 -> 0.135 | AO31: =+AM31*$F$10 -> 0.18 | AP31: =+G31 -> 4200 | AQ31: =+AT30 -> 1966.608 | AR31: =+(AN31*AP31+AO31*(AP31/12))*AM31 -> 630 | AS31: =+AQ31*$F$12 -> 78.66432 | AT31: =+(AQ31+AR31+AS31) -> 2675.2723 | AV31: =+AK31 -> 4 | AW31: =+AL31 -> 26 | AX31: 1 | AY31: =+$F$9*AX31 -> 0.135 | AZ31: =+AX31*$F$10 -> 0.18 | BA31: =+G31 -> 4200 | BB31: =+BE30 -> 1966.608 | BC31: =+(AY31*BA31+AZ31*(BA31/12))*AX31 -> 630 | BD31: =+BB31*$F$12 -> 78.66432 | BE31: =+(BB31+BC31+BD31) -> 2675.2723
B32: =+B31+1 -> 5 | C32: =+C31+1 -> 26 | D32: =+D31*(1+$F$18) -> 1 | E32: =+IF($C32>=$F$6,0,$F$19*D32) -> 700 | F32: =+IF($C32>=$F$6,0,$F$20) -> 6 | G32: =+E32*F32 -> 4200 | I32: =+I31+1 -> 5 | J32: =+C32 -> 26 | K32: =+IF(AL32<=$AF$11,1,0)*F32 -> 6 | L32: =+IF(AL32>$AF$11,0,IF(E32>500,500*F32,E32*F32)) -> 3000 | M32: =+IF(AL32>$AF$11,0,IF(G32-L32 <= 0,0,G32-L32)) -> 1200 | N32: =+IF($F$7<7,L32+M32,IF(AL32>$AF$11,0,IF($F$2=1,IF($J32<$F$5,IF(G32<=$F$16*12,G32,$F$16*12),G32),G32))) -> 4200 | O32: =+IFERROR(N32/K32,0) -> 700 | Q32: =+I32 -> 5 | R32: =+J32+1 -> 27 | S32: =+IF(R32<=$AF$11,1,0) -> 1 | T32: =+T31 -> 0.1 | U32: =+M32 -> 1200 | V32: =+Y31 -> 509.57568 | W32: =+T32*U32*S32 -> 120 | X32: =+$U$23*V32 -> 20.383027 | Y32: =+(V32+W32+X32) -> 649.95871 | AA32: =+B32 -> 5 | AB32: =+C32+1 -> 27 | AC32: =+IF(C32<$F$5,1,0) -> 0 | AD32: =+AD31 -> 0.15 | AE32: =+IF($F$2=1,IF(G32<=2500*12,G32,2500*12),G32) -> 4200 | AF32: =+AI31 -> 0 | AG32: =+AD32*AE32*$AC32 -> 0 | AH32: =+AF32*$F$11 -> 0 | AI32: =+(AF32+AG32+AH32) -> 0 | AK32: =+AA32 -> 5 | AL32: =+AB32 -> 27 | AM32: =+IF($C32>=$F$5,1,0) -> 1 | AN32: =+$F$9*AM32 -> 0.135 | AO32: =+AM32*$F$10 -> 0.18 | AP32: =+G32 -> 4200 | AQ32: =+AT31 -> 2675.2723 | AR32: =+(AN32*AP32+AO32*(AP32/12))*AM32 -> 630 | AS32: =+AQ32*$F$12 -> 107.01089 | AT32: =+(AQ32+AR32+AS32) -> 3412.2832 | AV32: =+AK32 -> 5 | AW32: =+AL32 -> 27 | AX32: 1 | AY32: =+$F$9*AX32 -> 0.135 | AZ32: =+AX32*$F$10 -> 0.18 | BA32: =+G32 -> 4200 | BB32: =+BE31 -> 2675.2723 | BC32: =+(AY32*BA32+AZ32*(BA32/12))*AX32 -> 630 | BD32: =+BB32*$F$12 -> 107.01089 | BE32: =+(BB32+BC32+BD32) -> 3412.2832
B33: =+B32+1 -> 6 | C33: =+C32+1 -> 27 | D33: =+D32*(1+$F$18) -> 1 | E33: =+IF($C33>=$F$6,0,$F$19*D33) -> 700 | F33: =+IF($C33>=$F$6,0,$F$20) -> 6 | G33: =+E33*F33 -> 4200 | I33: =+I32+1 -> 6 | J33: =+C33 -> 27 | K33: =+IF(AL33<=$AF$11,1,0)*F33 -> 6 | L33: =+IF(AL33>$AF$11,0,IF(E33>500,500*F33,E33*F33)) -> 3000 | M33: =+IF(AL33>$AF$11,0,IF(G33-L33 <= 0,0,G33-L33)) -> 1200 | N33: =+IF($F$7<7,L33+M33,IF(AL33>$AF$11,0,IF($F$2=1,IF($J33<$F$5,IF(G33<=$F$16*12,G33,$F$16*12),G33),G33))) -> 4200 | O33: =+IFERROR(N33/K33,0) -> 700 | Q33: =+I33 -> 6 | R33: =+J33+1 -> 28 | S33: =+IF(R33<=$AF$11,1,0) -> 1 | T33: =+T32 -> 0.1 | U33: =+M33 -> 1200 | V33: =+Y32 -> 649.95871 | W33: =+T33*U33*S33 -> 120 | X33: =+$U$23*V33 -> 25.998348 | Y33: =+(V33+W33+X33) -> 795.95706 | AA33: =+B33 -> 6 | AB33: =+C33+1 -> 28 | AC33: =+IF(C33<$F$5,1,0) -> 0 | AD33: =+AD32 -> 0.15 | AE33: =+IF($F$2=1,IF(G33<=2500*12,G33,2500*12),G33) -> 4200 | AF33: =+AI32 -> 0 | AG33: =+AD33*AE33*$AC33 -> 0 | AH33: =+AF33*$F$11 -> 0 | AI33: =+(AF33+AG33+AH33) -> 0 | AK33: =+AA33 -> 6 | AL33: =+AB33 -> 28 | AM33: =+IF($C33>=$F$5,1,0) -> 1 | AN33: =+$F$9*AM33 -> 0.135 | AO33: =+AM33*$F$10 -> 0.18 | AP33: =+G33 -> 4200 | AQ33: =+AT32 -> 3412.2832 | AR33: =+(AN33*AP33+AO33*(AP33/12))*AM33 -> 630 | AS33: =+AQ33*$F$12 -> 136.49133 | AT33: =+(AQ33+AR33+AS33) -> 4178.7745 | AV33: =+AK33 -> 6 | AW33: =+AL33 -> 28 | AX33: 1 | AY33: =+$F$9*AX33 -> 0.135 | AZ33: =+AX33*$F$10 -> 0.18 | BA33: =+G33 -> 4200 | BB33: =+BE32 -> 3412.2832 | BC33: =+(AY33*BA33+AZ33*(BA33/12))*AX33 -> 630 | BD33: =+BB33*$F$12 -> 136.49133 | BE33: =+(BB33+BC33+BD33) -> 4178.7745
B34: =+B33+1 -> 7 | C34: =+C33+1 -> 28 | D34: =+D33*(1+$F$18) -> 1 | E34: =+IF($C34>=$F$6,0,$F$19*D34) -> 700 | F34: =+IF($C34>=$F$6,0,$F$20) -> 6 | G34: =+E34*F34 -> 4200 | I34: =+I33+1 -> 7 | J34: =+C34 -> 28 | K34: =+IF(AL34<=$AF$11,1,0)*F34 -> 6 | L34: =+IF(AL34>$AF$11,0,IF(E34>500,500*F34,E34*F34)) -> 3000 | M34: =+IF(AL34>$AF$11,0,IF(G34-L34 <= 0,0,G34-L34)) -> 1200 | N34: =+IF($F$7<7,L34+M34,IF(AL34>$AF$11,0,IF($F$2=1,IF($J34<$F$5,IF(G34<=$F$16*12,G34,$F$16*12),G34),G34))) -> 4200 | O34: =+IFERROR(N34/K34,0) -> 700 | Q34: =+I34 -> 7 | R34: =+J34+1 -> 29 | S34: =+IF(R34<=$AF$11,1,0) -> 1 | T34: =+T33 -> 0.1 | U34: =+M34 -> 1200 | V34: =+Y33 -> 795.95706 | W34: =+T34*U34*S34 -> 120 | X34: =+$U$23*V34 -> 31.838282 | Y34: =+(V34+W34+X34) -> 947.79534 | AA34: =+B34 -> 7 | AB34: =+C34+1 -> 29 | AC34: =+IF(C34<$F$5,1,0) -> 0 | AD34: =+AD33 -> 0.15 | AE34: =+IF($F$2=1,IF(G34<=2500*12,G34,2500*12),G34) -> 4200 | AF34: =+AI33 -> 0 | AG34: =+AD34*AE34*$AC34 -> 0 | AH34: =+AF34*$F$11 -> 0 | AI34: =+(AF34+AG34+AH34) -> 0 | AK34: =+AA34 -> 7 | AL34: =+AB34 -> 29 | AM34: =+IF($C34>=$F$5,1,0) -> 1 | AN34: =+$F$9*AM34 -> 0.135 | AO34: =+AM34*$F$10 -> 0.18 | AP34: =+G34 -> 4200 | AQ34: =+AT33 -> 4178.7745 | AR34: =+(AN34*AP34+AO34*(AP34/12))*AM34 -> 630 | AS34: =+AQ34*$F$12 -> 167.15098 | AT34: =+(AQ34+AR34+AS34) -> 4975.9255 | AV34: =+AK34 -> 7 | AW34: =+AL34 -> 29 | AX34: 1 | AY34: =+$F$9*AX34 -> 0.135 | AZ34: =+AX34*$F$10 -> 0.18 | BA34: =+G34 -> 4200 | BB34: =+BE33 -> 4178.7745 | BC34: =+(AY34*BA34+AZ34*(BA34/12))*AX34 -> 630 | BD34: =+BB34*$F$12 -> 167.15098 | BE34: =+(BB34+BC34+BD34) -> 4975.9255
B35: =+B34+1 -> 8 | C35: =+C34+1 -> 29 | D35: =+D34*(1+$F$18) -> 1 | E35: =+IF($C35>=$F$6,0,$F$19*D35) -> 700 | F35: =+IF($C35>=$F$6,0,$F$20) -> 6 | G35: =+E35*F35 -> 4200 | I35: =+I34+1 -> 8 | J35: =+C35 -> 29 | K35: =+IF(AL35<=$AF$11,1,0)*F35 -> 6 | L35: =+IF(AL35>$AF$11,0,IF(E35>500,500*F35,E35*F35)) -> 3000 | M35: =+IF(AL35>$AF$11,0,IF(G35-L35 <= 0,0,G35-L35)) -> 1200 | N35: =+IF($F$7<7,L35+M35,IF(AL35>$AF$11,0,IF($F$2=1,IF($J35<$F$5,IF(G35<=$F$16*12,G35,$F$16*12),G35),G35))) -> 4200 | O35: =+IFERROR(N35/K35,0) -> 700 | Q35: =+I35 -> 8 | R35: =+J35+1 -> 30 | S35: =+IF(R35<=$AF$11,1,0) -> 1 | T35: =+T34 -> 0.1 | U35: =+M35 -> 1200 | V35: =+Y34 -> 947.79534 | W35: =+T35*U35*S35 -> 120 | X35: =+$U$23*V35 -> 37.911814 | Y35: =+(V35+W35+X35) -> 1105.7072 | AA35: =+B35 -> 8 | AB35: =+C35+1 -> 30 | AC35: =+IF(C35<$F$5,1,0) -> 0 | AD35: =+AD34 -> 0.15 | AE35: =+IF($F$2=1,IF(G35<=2500*12,G35,2500*12),G35) -> 4200 | AF35: =+AI34 -> 0 | AG35: =+AD35*AE35*$AC35 -> 0 | AH35: =+AF35*$F$11 -> 0 | AI35: =+(AF35+AG35+AH35) -> 0 | AK35: =+AA35 -> 8 | AL35: =+AB35 -> 30 | AM35: =+IF($C35>=$F$5,1,0) -> 1 | AN35: =+$F$9*AM35 -> 0.135 | AO35: =+AM35*$F$10 -> 0.18 | AP35: =+G35 -> 4200 | AQ35: =+AT34 -> 4975.9255 | AR35: =+(AN35*AP35+AO35*(AP35/12))*AM35 -> 630 | AS35: =+AQ35*$F$12 -> 199.03702 | AT35: =+(AQ35+AR35+AS35) -> 5804.9625 | AV35: =+AK35 -> 8 | AW35: =+AL35 -> 30 | AX35: 1 | AY35: =+$F$9*AX35 -> 0.135 | AZ35: =+AX35*$F$10 -> 0.18 | BA35: =+G35 -> 4200 | BB35: =+BE34 -> 4975.9255 | BC35: =+(AY35*BA35+AZ35*(BA35/12))*AX35 -> 630 | BD35: =+BB35*$F$12 -> 199.03702 | BE35: =+(BB35+BC35+BD35) -> 5804.9625
B36: =+B35+1 -> 9 | C36: =+C35+1 -> 30 | D36: =+D35*(1+$F$18) -> 1 | E36: =+IF($C36>=$F$6,0,$F$19*D36) -> 700 | F36: =+IF($C36>=$F$6,0,$F$20) -> 6 | G36: =+E36*F36 -> 4200 | I36: =+I35+1 -> 9 | J36: =+C36 -> 30 | K36: =+IF(AL36<=$AF$11,1,0)*F36 -> 6 | L36: =+IF(AL36>$AF$11,0,IF(E36>500,500*F36,E36*F36)) -> 3000 | M36: =+IF(AL36>$AF$11,0,IF(G36-L36 <= 0,0,G36-L36)) -> 1200 | N36: =+IF($F$7<7,L36+M36,IF(AL36>$AF$11,0,IF($F$2=1,IF($J36<$F$5,IF(G36<=$F$16*12,G36,$F$16*12),G36),G36))) -> 4200 | O36: =+IFERROR(N36/K36,0) -> 700 | Q36: =+I36 -> 9 | R36: =+J36+1 -> 31 | S36: =+IF(R36<=$AF$11,1,0) -> 1 | T36: =+T35 -> 0.1 | U36: =+M36 -> 1200 | V36: =+Y35 -> 1105.7072 | W36: =+T36*U36*S36 -> 120 | X36: =+$U$23*V36 -> 44.228286 | Y36: =+(V36+W36+X36) -> 1269.9354 | AA36: =+B36 -> 9 | AB36: =+C36+1 -> 31 | AC36: =+IF(C36<$F$5,1,0) -> 0 | AD36: =+AD35 -> 0.15 | AE36: =+IF($F$2=1,IF(G36<=2500*12,G36,2500*12),G36) -> 4200 | AF36: =+AI35 -> 0 | AG36: =+AD36*AE36*$AC36 -> 0 | AH36: =+AF36*$F$11 -> 0 | AI36: =+(AF36+AG36+AH36) -> 0 | AK36: =+AA36 -> 9 | AL36: =+AB36 -> 31 | AM36: =+IF($C36>=$F$5,1,0) -> 1 | AN36: =+$F$9*AM36 -> 0.135 | AO36: =+AM36*$F$10 -> 0.18 | AP36: =+G36 -> 4200 | AQ36: =+AT35 -> 5804.9625 | AR36: =+(AN36*AP36+AO36*(AP36/12))*AM36 -> 630 | AS36: =+AQ36*$F$12 -> 232.1985 | AT36: =+(AQ36+AR36+AS36) -> 6667.161 | AV36: =+AK36 -> 9 | AW36: =+AL36 -> 31 | AX36: 1 | AY36: =+$F$9*AX36 -> 0.135 | AZ36: =+AX36*$F$10 -> 0.18 | BA36: =+G36 -> 4200 | BB36: =+BE35 -> 5804.9625 | BC36: =+(AY36*BA36+AZ36*(BA36/12))*AX36 -> 630 | BD36: =+BB36*$F$12 -> 232.1985 | BE36: =+(BB36+BC36+BD36) -> 6667.161
B37: =+B36+1 -> 10 | C37: =+C36+1 -> 31 | D37: =+D36*(1+$F$18) -> 1 | E37: =+IF($C37>=$F$6,0,$F$19*D37) -> 700 | F37: =+IF($C37>=$F$6,0,$F$20) -> 6 | G37: =+E37*F37 -> 4200 | I37: =+I36+1 -> 10 | J37: =+C37 -> 31 | K37: =+IF(AL37<=$AF$11,1,0)*F37 -> 6 | L37: =+IF(AL37>$AF$11,0,IF(E37>500,500*F37,E37*F37)) -> 3000 | M37: =+IF(AL37>$AF$11,0,IF(G37-L37 <= 0,0,G37-L37)) -> 1200 | N37: =+IF($F$7<7,L37+M37,IF(AL37>$AF$11,0,IF($F$2=1,IF($J37<$F$5,IF(G37<=$F$16*12,G37,$F$16*12),G37),G37))) -> 4200 | O37: =+IFERROR(N37/K37,0) -> 700 | Q37: =+I37 -> 10 | R37: =+J37+1 -> 32 | S37: =+IF(R37<=$AF$11,1,0) -> 1 | T37: =+T36 -> 0.1 | U37: =+M37 -> 1200 | V37: =+Y36 -> 1269.9354 | W37: =+T37*U37*S37 -> 120 | X37: =+$U$23*V37 -> 50.797417 | Y37: =+(V37+W37+X37) -> 1440.7329 | AA37: =+B37 -> 10 | AB37: =+C37+1 -> 32 | AC37: =+IF(C37<$F$5,1,0) -> 0 | AD37: =+AD36 -> 0.15 | AE37: =+IF($F$2=1,IF(G37<=2500*12,G37,2500*12),G37) -> 4200 | AF37: =+AI36 -> 0 | AG37: =+AD37*AE37*$AC37 -> 0 | AH37: =+AF37*$F$11 -> 0 | AI37: =+(AF37+AG37+AH37) -> 0 | AK37: =+AA37 -> 10 | AL37: =+AB37 -> 32 | AM37: =+IF($C37>=$F$5,1,0) -> 1 | AN37: =+$F$9*AM37 -> 0.135 | AO37: =+AM37*$F$10 -> 0.18 | AP37: =+G37 -> 4200 | AQ37: =+AT36 -> 6667.161 | AR37: =+(AN37*AP37+AO37*(AP37/12))*AM37 -> 630 | AS37: =+AQ37*$F$12 -> 266.68644 | AT37: =+(AQ37+AR37+AS37) -> 7563.8475 | AV37: =+AK37 -> 10 | AW37: =+AL37 -> 32 | AX37: 1 | AY37: =+$F$9*AX37 -> 0.135 | AZ37: =+AX37*$F$10 -> 0.18 | BA37: =+G37 -> 4200 | BB37: =+BE36 -> 6667.161 | BC37: =+(AY37*BA37+AZ37*(BA37/12))*AX37 -> 630 | BD37: =+BB37*$F$12 -> 266.68644 | BE37: =+(BB37+BC37+BD37) -> 7563.8475
B38: =+B37+1 -> 11 | C38: =+C37+1 -> 32 | D38: =+D37*(1+$F$18) -> 1 | E38: =+IF($C38>=$F$6,0,$F$19*D38) -> 700 | F38: =+IF($C38>=$F$6,0,$F$20) -> 6 | G38: =+E38*F38 -> 4200 | I38: =+I37+1 -> 11 | J38: =+C38 -> 32 | K38: =+IF(AL38<=$AF$11,1,0)*F38 -> 6 | L38: =+IF(AL38>$AF$11,0,IF(E38>500,500*F38,E38*F38)) -> 3000 | M38: =+IF(AL38>$AF$11,0,IF(G38-L38 <= 0,0,G38-L38)) -> 1200 | N38: =+IF($F$7<7,L38+M38,IF(AL38>$AF$11,0,IF($F$2=1,IF($J38<$F$5,IF(G38<=$F$16*12,G38,$F$16*12),G38),G38))) -> 4200 | O38: =+IFERROR(N38/K38,0) -> 700 | Q38: =+I38 -> 11 | R38: =+J38+1 -> 33 | S38: =+IF(R38<=$AF$11,1,0) -> 1 | T38: =+T37 -> 0.1 | U38: =+M38 -> 1200 | V38: =+Y37 -> 1440.7329 | W38: =+T38*U38*S38 -> 120 | X38: =+$U$23*V38 -> 57.629314 | Y38: =+(V38+W38+X38) -> 1618.3622 | AA38: =+B38 -> 11 | AB38: =+C38+1 -> 33 | AC38: =+IF(C38<$F$5,1,0) -> 0 | AD38: =+AD37 -> 0.15 | AE38: =+IF($F$2=1,IF(G38<=2500*12,G38,2500*12),G38) -> 4200 | AF38: =+AI37 -> 0 | AG38: =+AD38*AE38*$AC38 -> 0 | AH38: =+AF38*$F$11 -> 0 | AI38: =+(AF38+AG38+AH38) -> 0 | AK38: =+AA38 -> 11 | AL38: =+AB38 -> 33 | AM38: =+IF($C38>=$F$5,1,0) -> 1 | AN38: =+$F$9*AM38 -> 0.135 | AO38: =+AM38*$F$10 -> 0.18 | AP38: =+G38 -> 4200 | AQ38: =+AT37 -> 7563.8475 | AR38: =+(AN38*AP38+AO38*(AP38/12))*AM38 -> 630 | AS38: =+AQ38*$F$12 -> 302.5539 | AT38: =+(AQ38+AR38+AS38) -> 8496.4014 | AV38: =+AK38 -> 11 | AW38: =+AL38 -> 33 | AX38: 1 | AY38: =+$F$9*AX38 -> 0.135 | AZ38: =+AX38*$F$10 -> 0.18 | BA38: =+G38 -> 4200 | BB38: =+BE37 -> 7563.8475 | BC38: =+(AY38*BA38+AZ38*(BA38/12))*AX38 -> 630 | BD38: =+BB38*$F$12 -> 302.5539 | BE38: =+(BB38+BC38+BD38) -> 8496.4014
B39: =+B38+1 -> 12 | C39: =+C38+1 -> 33 | D39: =+D38*(1+$F$18) -> 1 | E39: =+IF($C39>=$F$6,0,$F$19*D39) -> 700 | F39: =+IF($C39>=$F$6,0,$F$20) -> 6 | G39: =+E39*F39 -> 4200 | I39: =+I38+1 -> 12 | J39: =+C39 -> 33 | K39: =+IF(AL39<=$AF$11,1,0)*F39 -> 6 | L39: =+IF(AL39>$AF$11,0,IF(E39>500,500*F39,E39*F39)) -> 3000 | M39: =+IF(AL39>$AF$11,0,IF(G39-L39 <= 0,0,G39-L39)) -> 1200 | N39: =+IF($F$7<7,L39+M39,IF(AL39>$AF$11,0,IF($F$2=1,IF($J39<$F$5,IF(G39<=$F$16*12,G39,$F$16*12),G39),G39))) -> 4200 | O39: =+IFERROR(N39/K39,0) -> 700 | Q39: =+I39 -> 12 | R39: =+J39+1 -> 34 | S39: =+IF(R39<=$AF$11,1,0) -> 1 | T39: =+T38 -> 0.1 | U39: =+M39 -> 1200 | V39: =+Y38 -> 1618.3622 | W39: =+T39*U39*S39 -> 120 | X39: =+$U$23*V39 -> 64.734487 | Y39: =+(V39+W39+X39) -> 1803.0967 | AA39: =+B39 -> 12 | AB39: =+C39+1 -> 34 | AC39: =+IF(C39<$F$5,1,0) -> 0 | AD39: =+AD38 -> 0.15 | AE39: =+IF($F$2=1,IF(G39<=2500*12,G39,2500*12),G39) -> 4200 | AF39: =+AI38 -> 0 | AG39: =+AD39*AE39*$AC39 -> 0 | AH39: =+AF39*$F$11 -> 0 | AI39: =+(AF39+AG39+AH39) -> 0 | AK39: =+AA39 -> 12 | AL39: =+AB39 -> 34 | AM39: =+IF($C39>=$F$5,1,0) -> 1 | AN39: =+$F$9*AM39 -> 0.135 | AO39: =+AM39*$F$10 -> 0.18 | AP39: =+G39 -> 4200 | AQ39: =+AT38 -> 8496.4014 | AR39: =+(AN39*AP39+AO39*(AP39/12))*AM39 -> 630 | AS39: =+AQ39*$F$12 -> 339.85606 | AT39: =+(AQ39+AR39+AS39) -> 9466.2574 | AV39: =+AK39 -> 12 | AW39: =+AL39 -> 34 | AX39: 1 | AY39: =+$F$9*AX39 -> 0.135 | AZ39: =+AX39*$F$10 -> 0.18 | BA39: =+G39 -> 4200 | BB39: =+BE38 -> 8496.4014 | BC39: =+(AY39*BA39+AZ39*(BA39/12))*AX39 -> 630 | BD39: =+BB39*$F$12 -> 339.85606 | BE39: =+(BB39+BC39+BD39) -> 9466.2574
B40: =+B39+1 -> 13 | C40: =+C39+1 -> 34 | D40: =+D39*(1+$F$18) -> 1 | E40: =+IF($C40>=$F$6,0,$F$19*D40) -> 700 | F40: =+IF($C40>=$F$6,0,$F$20) -> 6 | G40: =+E40*F40 -> 4200 | I40: =+I39+1 -> 13 | J40: =+C40 -> 34 | K40: =+IF(AL40<=$AF$11,1,0)*F40 -> 6 | L40: =+IF(AL40>$AF$11,0,IF(E40>500,500*F40,E40*F40)) -> 3000 | M40: =+IF(AL40>$AF$11,0,IF(G40-L40 <= 0,0,G40-L40)) -> 1200 | N40: =+IF($F$7<7,L40+M40,IF(AL40>$AF$11,0,IF($F$2=1,IF($J40<$F$5,IF(G40<=$F$16*12,G40,$F$16*12),G40),G40))) -> 4200 | O40: =+IFERROR(N40/K40,0) -> 700 | Q40: =+I40 -> 13 | R40: =+J40+1 -> 35 | S40: =+IF(R40<=$AF$11,1,0) -> 1 | T40: =+T39 -> 0.1 | U40: =+M40 -> 1200 | V40: =+Y39 -> 1803.0967 | W40: =+T40*U40*S40 -> 120 | X40: =+$U$23*V40 -> 72.123866 | Y40: =+(V40+W40+X40) -> 1995.2205 | AA40: =+B40 -> 13 | AB40: =+C40+1 -> 35 | AC40: =+IF(C40<$F$5,1,0) -> 0 | AD40: =+AD39 -> 0.15 | AE40: =+IF($F$2=1,IF(G40<=2500*12,G40,2500*12),G40) -> 4200 | AF40: =+AI39 -> 0 | AG40: =+AD40*AE40*$AC40 -> 0 | AH40: =+AF40*$F$11 -> 0 | AI40: =+(AF40+AG40+AH40) -> 0 | AK40: =+AA40 -> 13 | AL40: =+AB40 -> 35 | AM40: =+IF($C40>=$F$5,1,0) -> 1 | AN40: =+$F$9*AM40 -> 0.135 | AO40: =+AM40*$F$10 -> 0.18 | AP40: =+G40 -> 4200 | AQ40: =+AT39 -> 9466.2574 | AR40: =+(AN40*AP40+AO40*(AP40/12))*AM40 -> 630 | AS40: =+AQ40*$F$12 -> 378.6503 | AT40: =+(AQ40+AR40+AS40) -> 10474.908 | AV40: =+AK40 -> 13 | AW40: =+AL40 -> 35 | AX40: 1 | AY40: =+$F$9*AX40 -> 0.135 | AZ40: =+AX40*$F$10 -> 0.18 | BA40: =+G40 -> 4200 | BB40: =+BE39 -> 9466.2574 | BC40: =+(AY40*BA40+AZ40*(BA40/12))*AX40 -> 630 | BD40: =+BB40*$F$12 -> 378.6503 | BE40: =+(BB40+BC40+BD40) -> 10474.908
... B65: =+B64+1 -> 38 | C65: =+C64+1 -> 59 | D65: =+D64*(1+$F$18) -> 1 | E65: =+IF($C65>=$F$6,0,$F$19*D65) -> 700 | F65: =+IF($C65>=$F$6,0,$F$20) -> 6 | G65: =+E65*F65 -> 4200 | I65: =+I64+1 -> 38 | J65: =+C65 -> 59 | K65: =+IF(AL65<=$AF$11,1,0)*F65 -> 6 | L65: =+IF(AL65>$AF$11,0,IF(E65>500,500*F65,E65*F65)) -> 3000 | M65: =+IF(AL65>$AF$11,0,IF(G65-L65 <= 0,0,G65-L65)) -> 1200 | N65: =+IF($F$7<7,L65+M65,IF(AL65>$AF$11,0,IF($F$2=1,IF($J65<$F$5,IF(G65<=$F$16*12,G65,$F$16*12),G65),G65))) -> 4200 | O65: =+IFERROR(N65/K65,0) -> 700 | Q65: =+I65 -> 38 | R65: =+J65+1 -> 60 | S65: =+IF(R65<=$AF$11,1,0) -> 1 | T65: =+T64 -> 0.1 | U65: =+M65 -> 1200 | V65: =+Y64 -> 9804.2696 | W65: =+T65*U65*S65 -> 120 | X65: =+$U$23*V65 -> 392.17078 | Y65: =+(V65+W65+X65) -> 10316.44 | AA65: =+B65 -> 38 | AB65: =+C65+1 -> 60 | AC65: =+IF(C65<$F$5,1,0) -> 0 | AD65: =+AD64 -> 0.15 | AE65: =+IF($F$2=1,IF(G65<=2500*12,G65,2500*12),G65) -> 4200 | AF65: =+AI64 -> 0 | AG65: =+AD65*AE65*$AC65 -> 0 | AH65: =+AF65*$F$11 -> 0 | AI65: =+(AF65+AG65+AH65) -> 0 | AK65: =+AA65 -> 38 | AL65: =+AB65 -> 60 | AM65: =+IF($C65>=$F$5,1,0) -> 1 | AN65: =+$F$9*AM65 -> 0.135 | AO65: =+AM65*$F$10 -> 0.18 | AP65: =+G65 -> 4200 | AQ65: =+AT64 -> 51472.415 | AR65: =+(AN65*AP65+AO65*(AP65/12))*AM65 -> 630 | AS65: =+AQ65*$F$12 -> 2058.8966 | AT65: =+(AQ65+AR65+AS65) -> 54161.312 | AV65: =+AK65 -> 38 | AW65: =+AL65 -> 60 | AX65: 1 | AY65: =+$F$9*AX65 -> 0.135 | AZ65: =+AX65*$F$10 -> 0.18 | BA65: =+G65 -> 4200 | BB65: =+BE64 -> 51472.415 | BC65: =+(AY65*BA65+AZ65*(BA65/12))*AX65 -> 630 | BD65: =+BB65*$F$12 -> 2058.8966 | BE65: =+(BB65+BC65+BD65) -> 54161.312
B66: =+B65+1 -> 39 | C66: =+C65+1 -> 60 | D66: =+D65*(1+$F$18) -> 1 | E66: =+IF($C66>=$F$6,0,$F$19*D66) -> 700 | F66: =+IF($C66>=$F$6,0,$F$20) -> 6 | G66: =+E66*F66 -> 4200 | I66: =+I65+1 -> 39 | J66: =+C66 -> 60 | K66: =+IF(AL66<=$AF$11,1,0)*F66 -> 6 | L66: =+IF(AL66>$AF$11,0,IF(E66>500,500*F66,E66*F66)) -> 3000 | M66: =+IF(AL66>$AF$11,0,IF(G66-L66 <= 0,0,G66-L66)) -> 1200 | N66: =+IF($F$7<7,L66+M66,IF(AL66>$AF$11,0,IF($F$2=1,IF($J66<$F$5,IF(G66<=$F$16*12,G66,$F$16*12),G66),G66))) -> 4200 | O66: =+IFERROR(N66/K66,0) -> 700 | Q66: =+I66 -> 39 | R66: =+J66+1 -> 61 | S66: =+IF(R66<=$AF$11,1,0) -> 1 | T66: =+T65 -> 0.1 | U66: =+M66 -> 1200 | V66: =+Y65 -> 10316.44 | W66: =+T66*U66*S66 -> 120 | X66: =+$U$23*V66 -> 412.65761 | Y66: =+(V66+W66+X66) -> 10849.098 | AA66: =+B66 -> 39 | AB66: =+C66+1 -> 61 | AC66: =+IF(C66<$F$5,1,0) -> 0 | AD66: =+AD65 -> 0.15 | AE66: =+IF($F$2=1,IF(G66<=2500*12,G66,2500*12),G66) -> 4200 | AF66: =+AI65 -> 0 | AG66: =+AD66*AE66*$AC66 -> 0 | AH66: =+AF66*$F$11 -> 0 | AI66: =+(AF66+AG66+AH66) -> 0 | AK66: =+AA66 -> 39 | AL66: =+AB66 -> 61 | AM66: 1 | AN66: =+$F$9*AM66 -> 0.135 | AO66: =+AM66*$F$10 -> 0.18 | AP66: =+G66 -> 4200 | AQ66: =+AT65 -> 54161.312 | AR66: =+(AN66*AP66+AO66*(AP66/12))*AM66 -> 630 | AS66: =+AQ66*$F$12 -> 2166.4525 | AT66: =+(AQ66+AR66+AS66) -> 56957.764 | AV66: =+AK66 -> 39 | AW66: =+AL66 -> 61 | AX66: 1 | AY66: =+$F$9*AX66 -> 0.135 | AZ66: =+AX66*$F$10 -> 0.18 | BA66: =+G66 -> 4200 | BB66: =+BE65 -> 54161.312 | BC66: =+(AY66*BA66+AZ66*(BA66/12))*AX66 -> 630 | BD66: =+BB66*$F$12 -> 2166.4525 | BE66: =+(BB66+BC66+BD66) -> 56957.764
B67: =+B66+1 -> 40 | C67: =+C66+1 -> 61 | D67: =+D66*(1+$F$18) -> 1 | E67: =+IF($C67>=$F$6,0,$F$19*D67) -> 700 | F67: =+IF($C67>=$F$6,0,$F$20) -> 6 | G67: =+E67*F67 -> 4200 | I67: =+I66+1 -> 40 | J67: =+C67 -> 61 | K67: =+IF(AL67<=$AF$11,1,0)*F67 -> 6 | L67: =+IF(AL67>$AF$11,0,IF(E67>500,500*F67,E67*F67)) -> 3000 | M67: =+IF(AL67>$AF$11,0,IF(G67-L67 <= 0,0,G67-L67)) -> 1200 | N67: =+IF($F$7<7,L67+M67,IF(AL67>$AF$11,0,IF($F$2=1,IF($J67<$F$5,IF(G67<=$F$16*12,G67,$F$16*12),G67),G67))) -> 4200 | O67: =+IFERROR(N67/K67,0) -> 700 | Q67: =+I67 -> 40 | R67: =+J67+1 -> 62 | S67: 1 | T67: =+T66 -> 0.1 | U67: =+M67 -> 1200 | V67: =+Y66 -> 10849.098 | W67: =+T67*U67*S67 -> 120 | X67: =+$U$23*V67 -> 433.96392 | Y67: =+(V67+W67+X67) -> 11403.062 | AA67: =+B67 -> 40 | AB67: =+C67+1 -> 62 | AC67: =+IF(C67<$F$5,1,0) -> 0 | AD67: =+AD66 -> 0.15 | AE67: =+IF($F$2=1,IF(G67<=2500*12,G67,2500*12),G67) -> 4200 | AF67: =+AI66 -> 0 | AG67: =+AD67*AE67*$AC67 -> 0 | AH67: =+AF67*$F$11 -> 0 | AI67: =+(AF67+AG67+AH67) -> 0 | AK67: =+AA67 -> 40 | AL67: =+AB67 -> 62 | AM67: 1 | AN67: =+$F$9*AM67 -> 0.135 | AO67: =+AM67*$F$10 -> 0.18 | AP67: =+G67 -> 4200 | AQ67: =+AT66 -> 56957.764 | AR67: =+(AN67*AP67+AO67*(AP67/12))*AM67 -> 630 | AS67: =+AQ67*$F$12 -> 2278.3106 | AT67: =+(AQ67+AR67+AS67) -> 59866.075 | AV67: =+AK67 -> 40 | AW67: =+AL67 -> 62 | AX67: 1 | AY67: =+$F$9*AX67 -> 0.135 | AZ67: =+AX67*$F$10 -> 0.18 | BA67: =+G67 -> 4200 | BB67: =+BE66 -> 56957.764 | BC67: =+(AY67*BA67+AZ67*(BA67/12))*AX67 -> 630 | BD67: =+BB67*$F$12 -> 2278.3106 | BE67: =+(BB67+BC67+BD67) -> 59866.075
B68: =+B67+1 -> 41 | C68: =+C67+1 -> 62 | D68: =+D67*(1+$F$18) -> 1 | E68: =+IF($C68>=$F$6,0,$F$19*D68) -> 0 | F68: =+IF($C68>=$F$6,0,$F$20) -> 0 | G68: =+E68*F68 -> 0 | I68: =+I67+1 -> 41 | J68: =+C68 -> 62 | K68: =+IF(AL68<=$AF$11,1,0)*F68 -> 0 | L68: =+IF(AL68>$AF$11,0,IF(E68>500,500*F68,E68*F68)) -> 0 | M68: =+IF(AL68>$AF$11,0,IF(G68-L68 <= 0,0,G68-L68)) -> 0 | N68: =+IF($F$7<7,L68+M68,IF(AL68>$AF$11,0,IF($F$2=1,IF($J68<$F$5,IF(G68<=$F$16*12,G68,$F$16*12),G68),G68))) -> 0 | O68: =+IFERROR(N68/K68,0) -> 0 | Q68: =+I68 -> 41 | R68: =+J68+1 -> 63 | S68: =+IF(R68<=$AF$11,1,0) -> 0 | T68: =+T67 -> 0.1 | U68: =+M68 -> 0 | V68: =+Y67 -> 11403.062 | W68: =+T68*U68*S68 -> 0 | X68: =+$U$23*V68 -> 456.12248 | Y68: =+(V68+W68+X68) -> 11859.184 | AA68: =+B68 -> 41 | AB68: =+C68+1 -> 63 | AC68: =+IF(C68<$F$5,1,0) -> 0 | AD68: =+AD67 -> 0.15 | AE68: =+IF($F$2=1,IF(G68<=2500*12,G68,2500*12),G68) -> 0 | AF68: =+AI67 -> 0 | AG68: =+AD68*AE68*$AC68 -> 0 | AH68: =+AF68*$F$11 -> 0 | AI68: =+(AF68+AG68+AH68) -> 0 | AK68: =+AA68 -> 41 | AL68: =+AB68 -> 63 | AM68: 0 | AN68: =+$F$9*AM68 -> 0 | AO68: =+AM68*$F$10 -> 0 | AP68: =+G68 -> 0 | AQ68: =+AT67 -> 59866.075 | AR68: =+(AN68*AP68+AO68*(AP68/12))*AM68 -> 0 | AS68: =+AQ68*$F$12 -> 2394.643 | AT68: =+(AQ68+AR68+AS68) -> 62260.718 | AV68: =+AK68 -> 41 | AW68: =+AL68 -> 63 | AX68: 0 | AY68: =+$F$9*AX68 -> 0 | AZ68: =+AX68*$F$10 -> 0 | BA68: =+G68 -> 0 | BB68: =+BE67 -> 59866.075 | BC68: =+(AY68*BA68+AZ68*(BA68/12))*AX68 -> 0 | BD68: =+BB68*$F$12 -> 2394.643 | BE68: =+(BB68+BC68+BD68) -> 62260.718
B69: =+B68+1 -> 42 | C69: =+C68+1 -> 63 | D69: =+D68*(1+$F$18) -> 1 | E69: =+IF($C69>=$F$6,0,$F$19*D69) -> 0 | F69: =+IF($C69>=$F$6,0,$F$20) -> 0 | G69: =+E69*F69 -> 0 | I69: =+I68+1 -> 42 | J69: =+C69 -> 63 | K69: =+IF(AL69<=$AF$11,1,0)*F69 -> 0 | L69: =+IF(AL69>$AF$11,0,IF(E69>500,500*F69,E69*F69)) -> 0 | M69: =+IF(AL69>$AF$11,0,IF(G69-L69 <= 0,0,G69-L69)) -> 0 | N69: =+IF($F$7<7,L69+M69,IF(AL69>$AF$11,0,IF($F$2=1,IF($J69<$F$5,IF(G69<=$F$16*12,G69,$F$16*12),G69),G69))) -> 0 | O69: =+IFERROR(N69/K69,0) -> 0 | Q69: =+I69 -> 42 | R69: =+J69+1 -> 64 | S69: =+IF(R69<=$AF$11,1,0) -> 0 | T69: =+T68 -> 0.1 | U69: =+M69 -> 0 | V69: =+Y68 -> 11859.184 | W69: =+T69*U69*S69 -> 0 | X69: =+$U$23*V69 -> 474.36737 | Y69: =+(V69+W69+X69) -> 12333.552 | AA69: =+B69 -> 42 | AB69: =+C69+1 -> 64 | AC69: =+IF(C69<$F$5,1,0) -> 0 | AD69: =+AD68 -> 0.15 | AE69: =+IF($F$2=1,IF(G69<=2500*12,G69,2500*12),G69) -> 0 | AF69: =+AI68 -> 0 | AG69: =+AD69*AE69*$AC69 -> 0 | AH69: =+AF69*$F$11 -> 0 | AI69: =+(AF69+AG69+AH69) -> 0 | AK69: =+AA69 -> 42 | AL69: =+AB69 -> 64 | AM69: 0 | AN69: =+$F$9*AM69 -> 0 | AO69: =+AM69*$F$10 -> 0 | AP69: =+G69 -> 0 | AQ69: =+AT68 -> 62260.718 | AR69: =+(AN69*AP69+AO69*(AP69/12))*AM69 -> 0 | AS69: =+AQ69*$F$12 -> 2490.4287 | AT69: =+(AQ69+AR69+AS69) -> 64751.147 | AV69: =+AK69 -> 42 | AW69: =+AL69 -> 64 | AX69: 0 | AY69: =+$F$9*AX69 -> 0 | AZ69: =+AX69*$F$10 -> 0 | BA69: =+G69 -> 0 | BB69: =+BE68 -> 62260.718 | BC69: =+(AY69*BA69+AZ69*(BA69/12))*AX69 -> 0 | BD69: =+BB69*$F$12 -> 2490.4287 | BE69: =+(BB69+BC69+BD69) -> 64751.147
B70: =+B69+1 -> 43 | C70: =+C69+1 -> 64 | D70: =+D69*(1+$F$18) -> 1 | E70: =+IF($C70>=$F$6,0,$F$19*D70) -> 0 | F70: =+IF($C70>=$F$6,0,$F$20) -> 0 | G70: =+E70*F70 -> 0 | I70: =+I69+1 -> 43 | J70: =+C70 -> 64 | K70: =+IF(AL70<=$AF$11,1,0)*F70 -> 0 | L70: =+IF(AL70>$AF$11,0,IF(E70>500,500*F70,E70*F70)) -> 0 | M70: =+IF(AL70>$AF$11,0,IF(G70-L70 <= 0,0,G70-L70)) -> 0 | N70: =+IF($F$7<7,L70+M70,IF(AL70>$AF$11,0,IF($F$2=1,IF($J70<$F$5,IF(G70<=$F$16*12,G70,$F$16*12),G70),G70))) -> 0 | O70: =+IFERROR(N70/K70,0) -> 0 | Q70: =+I70 -> 43 | R70: =+J70+1 -> 65 | S70: =+IF(R70<=$AF$11,1,0) -> 0 | T70: =+T69 -> 0.1 | U70: =+M70 -> 0 | V70: =+Y69 -> 12333.552 | W70: =+T70*U70*S70 -> 0 | X70: =+$U$23*V70 -> 493.34207 | Y70: =+(V70+W70+X70) -> 12826.894 | AA70: =+B70 -> 43 | AB70: =+C70+1 -> 65 | AC70: =+IF(C70<$F$5,1,0) -> 0 | AD70: =+AD69 -> 0.15 | AE70: =+IF($F$2=1,IF(G70<=2500*12,G70,2500*12),G70) -> 0 | AF70: =+AI69 -> 0 | AG70: =+AD70*AE70*$AC70 -> 0 | AH70: =+AF70*$F$11 -> 0 | AI70: =+(AF70+AG70+AH70) -> 0 | AK70: =+AA70 -> 43 | AL70: =+AB70 -> 65 | AM70: 0 | AN70: =+$F$9*AM70 -> 0 | AO70: =+AM70*$F$10 -> 0 | AP70: =+G70 -> 0 | AQ70: =+AT69 -> 64751.147 | AR70: =+(AN70*AP70+AO70*(AP70/12))*AM70 -> 0 | AS70: =+AQ70*$F$12 -> 2590.0459 | AT70: =+(AQ70+AR70+AS70) -> 67341.192 | AV70: =+AK70 -> 43 | AW70: =+AL70 -> 65 | AX70: 0 | AY70: =+$F$9*AX70 -> 0 | AZ70: =+AX70*$F$10 -> 0 | BA70: =+G70 -> 0 | BB70: =+BE69 -> 64751.147 | BC70: =+(AY70*BA70+AZ70*(BA70/12))*AX70 -> 0 | BD70: =+BB70*$F$12 -> 2590.0459 | BE70: =+(BB70+BC70+BD70) -> 67341.192
B71: =+B70+1 -> 44 | C71: =+C70+1 -> 65 | D71: =+D70*(1+$F$18) -> 1 | E71: =+IF($C71>=$F$6,0,$F$19*D71) -> 0 | F71: =+IF($C71>=$F$6,0,$F$20) -> 0 | G71: =+E71*F71 -> 0 | I71: =+I70+1 -> 44 | J71: =+C71 -> 65 | K71: =+IF(AL71<=$AF$11,1,0)*F71 -> 0 | L71: =+IF(AL71>$AF$11,0,IF(E71>500,500*F71,E71*F71)) -> 0 | M71: =+IF(AL71>$AF$11,0,IF(G71-L71 <= 0,0,G71-L71)) -> 0 | N71: =+IF($F$7<7,L71+M71,IF(AL71>$AF$11,0,IF($F$2=1,IF($J71<$F$5,IF(G71<=$F$16*12,G71,$F$16*12),G71),G71))) -> 0 | O71: =+IFERROR(N71/K71,0) -> 0 | Q71: =+I71 -> 44 | R71: =+J71+1 -> 66 | S71: =+IF(R71<=$AF$11,1,0) -> 0 | T71: =+T70 -> 0.1 | U71: =+M71 -> 0 | V71: =+Y70 -> 12826.894 | W71: =+T71*U71*S71 -> 0 | X71: =+$U$23*V71 -> 513.07575 | Y71: =+(V71+W71+X71) -> 13339.97 | AA71: =+B71 -> 44 | AB71: =+C71+1 -> 66 | AC71: =+IF(C71<$F$5,1,0) -> 0 | AD71: =+AD70 -> 0.15 | AE71: =+IF($F$2=1,IF(G71<=2500*12,G71,2500*12),G71) -> 0 | AF71: =+AI70 -> 0 | AG71: =+AD71*AE71*$AC71 -> 0 | AH71: =+AF71*$F$11 -> 0 | AI71: =+(AF71+AG71+AH71) -> 0 | AK71: =+AA71 -> 44 | AL71: =+AB71 -> 66 | AM71: 0 | AN71: =+$F$9*AM71 -> 0 | AO71: =+AM71*$F$10 -> 0 | AP71: =+G71 -> 0 | AQ71: =+AT70 -> 67341.192 | AR71: =+(AN71*AP71+AO71*(AP71/12))*AM71 -> 0 | AS71: =+AQ71*$F$12 -> 2693.6477 | AT71: =+(AQ71+AR71+AS71) -> 70034.84 | AV71: =+AK71 -> 44 | AW71: =+AL71 -> 66 | AX71: 0 | AY71: =+$F$9*AX71 -> 0 | AZ71: =+AX71*$F$10 -> 0 | BA71: =+G71 -> 0 | BB71: =+BE70 -> 67341.192 | BC71: =+(AY71*BA71+AZ71*(BA71/12))*AX71 -> 0 | BD71: =+BB71*$F$12 -> 2693.6477 | BE71: =+(BB71+BC71+BD71) -> 70034.84
B72: =+B71+1 -> 45 | C72: =+C71+1 -> 66 | D72: =+D71*(1+$F$18) -> 1 | E72: =+IF($C72>=$F$6,0,$F$19*D72) -> 0 | F72: =+IF($C72>=$F$6,0,$F$20) -> 0 | G72: =+E72*F72 -> 0 | I72: =+I71+1 -> 45 | J72: =+C72 -> 66 | K72: =+IF(AL72<=$AF$11,1,0)*F72 -> 0 | L72: =+IF(AL72>$AF$11,0,IF(E72>500,500*F72,E72*F72)) -> 0 | M72: =+IF(AL72>$AF$11,0,IF(G72-L72 <= 0,0,G72-L72)) -> 0 | N72: =+IF($F$7<7,L72+M72,IF(AL72>$AF$11,0,IF($F$2=1,IF($J72<$F$5,IF(G72<=$F$16*12,G72,$F$16*12),G72),G72))) -> 0 | O72: =+IFERROR(N72/K72,0) -> 0 | Q72: =+I72 -> 45 | R72: =+J72+1 -> 67 | S72: =+IF(R72<=$AF$11,1,0) -> 0 | T72: =+T71 -> 0.1 | U72: =+M72 -> 0 | V72: =+Y71 -> 13339.97 | W72: =+T72*U72*S72 -> 0 | X72: =+$U$23*V72 -> 533.59878 | Y72: =+(V72+W72+X72) -> 13873.568 | AA72: =+B72 -> 45 | AB72: =+C72+1 -> 67 | AC72: =+IF(C72<$F$5,1,0) -> 0 | AD72: =+AD71 -> 0.15 | AE72: =+IF($F$2=1,IF(G72<=2500*12,G72,2500*12),G72) -> 0 | AF72: =+AI71 -> 0 | AG72: =+AD72*AE72*$AC72 -> 0 | AH72: =+AF72*$F$11 -> 0 | AI72: =+(AF72+AG72+AH72) -> 0 | AK72: =+AA72 -> 45 | AL72: =+AB72 -> 67 | AM72: 0 | AN72: =+$F$9*AM72 -> 0 | AO72: =+AM72*$F$10 -> 0 | AP72: =+G72 -> 0 | AQ72: =+AT71 -> 70034.84 | AR72: =+(AN72*AP72+AO72*(AP72/12))*AM72 -> 0 | AS72: =+AQ72*$F$12 -> 2801.3936 | AT72: =+(AQ72+AR72+AS72) -> 72836.234 | AV72: =+AK72 -> 45 | AW72: =+AL72 -> 67 | AX72: 0 | AY72: =+$F$9*AX72 -> 0 | AZ72: =+AX72*$F$10 -> 0 | BA72: =+G72 -> 0 | BB72: =+BE71 -> 70034.84 | BC72: =+(AY72*BA72+AZ72*(BA72/12))*AX72 -> 0 | BD72: =+BB72*$F$12 -> 2801.3936 | BE72: =+(BB72+BC72+BD72) -> 72836.234
B73: =+B72+1 -> 46 | C73: =+C72+1 -> 67 | D73: =+D72*(1+$F$18) -> 1 | E73: =+IF($C73>=$F$6,0,$F$19*D73) -> 0 | F73: =+IF($C73>=$F$6,0,$F$20) -> 0 | G73: =+E73*F73 -> 0 | I73: =+I72+1 -> 46 | J73: =+C73 -> 67 | K73: =+IF(AL73<=$AF$11,1,0)*F73 -> 0 | L73: =+IF(AL73>$AF$11,0,IF(E73>500,500*F73,E73*F73)) -> 0 | M73: =+IF(AL73>$AF$11,0,IF(G73-L73 <= 0,0,G73-L73)) -> 0 | N73: =+IF($F$7<7,L73+M73,IF(AL73>$AF$11,0,IF($F$2=1,IF($J73<$F$5,IF(G73<=$F$16*12,G73,$F$16*12),G73),G73))) -> 0 | O73: =+IFERROR(N73/K73,0) -> 0 | Q73: =+I73 -> 46 | R73: =+J73+1 -> 68 | S73: =+IF(R73<=$AF$11,1,0) -> 0 | T73: =+T72 -> 0.1 | U73: =+M73 -> 0 | V73: =+Y72 -> 13873.568 | W73: =+T73*U73*S73 -> 0 | X73: =+$U$23*V73 -> 554.94273 | Y73: =+(V73+W73+X73) -> 14428.511 | AA73: =+B73 -> 46 | AB73: =+C73+1 -> 68 | AC73: =+IF(C73<$F$5,1,0) -> 0 | AD73: =+AD72 -> 0.15 | AE73: =+IF($F$2=1,IF(G73<=2500*12,G73,2500*12),G73) -> 0 | AF73: =+AI72 -> 0 | AG73: =+AD73*AE73*$AC73 -> 0 | AH73: =+AF73*$F$11 -> 0 | AI73: =+(AF73+AG73+AH73) -> 0 | AK73: =+AA73 -> 46 | AL73: =+AB73 -> 68 | AM73: 0 | AN73: =+$F$9*AM73 -> 0 | AO73: =+AM73*$F$10 -> 0 | AP73: =+G73 -> 0 | AQ73: =+AT72 -> 72836.234 | AR73: =+(AN73*AP73+AO73*(AP73/12))*AM73 -> 0 | AS73: =+AQ73*$F$12 -> 2913.4494 | AT73: =+(AQ73+AR73+AS73) -> 75749.683 | AV73: =+AK73 -> 46 | AW73: =+AL73 -> 68 | AX73: 0 | AY73: =+$F$9*AX73 -> 0 | AZ73: =+AX73*$F$10 -> 0 | BA73: =+G73 -> 0 | BB73: =+BE72 -> 72836.234 | BC73: =+(AY73*BA73+AZ73*(BA73/12))*AX73 -> 0 | BD73: =+BB73*$F$12 -> 2913.4494 | BE73: =+(BB73+BC73+BD73) -> 75749.683
B74: =+B73+1 -> 47 | C74: =+C73+1 -> 68 | D74: =+D73*(1+$F$18) -> 1 | E74: =+IF($C74>=$F$6,0,$F$19*D74) -> 0 | F74: =+IF($C74>=$F$6,0,$F$20) -> 0 | G74: =+E74*F74 -> 0 | I74: =+I73+1 -> 47 | J74: =+C74 -> 68 | K74: =+IF(AL74<=$AF$11,1,0)*F74 -> 0 | L74: =+IF(AL74>$AF$11,0,IF(E74>500,500*F74,E74*F74)) -> 0 | M74: =+IF(AL74>$AF$11,0,IF(G74-L74 <= 0,0,G74-L74)) -> 0 | N74: =+IF($F$7<7,L74+M74,IF(AL74>$AF$11,0,IF($F$2=1,IF($J74<$F$5,IF(G74<=$F$16*12,G74,$F$16*12),G74),G74))) -> 0 | O74: =+IFERROR(N74/K74,0) -> 0 | Q74: =+I74 -> 47 | R74: =+J74+1 -> 69 | S74: =+IF(R74<=$AF$11,1,0) -> 0 | T74: =+T73 -> 0.1 | U74: =+M74 -> 0 | V74: =+Y73 -> 14428.511 | W74: =+T74*U74*S74 -> 0 | X74: =+$U$23*V74 -> 577.14044 | Y74: =+(V74+W74+X74) -> 15005.652 | AA74: =+B74 -> 47 | AB74: =+C74+1 -> 69 | AC74: =+IF(C74<$F$5,1,0) -> 0 | AD74: =+AD73 -> 0.15 | AE74: =+IF($F$2=1,IF(G74<=2500*12,G74,2500*12),G74) -> 0 | AF74: =+AI73 -> 0 | AG74: =+AD74*AE74*$AC74 -> 0 | AH74: =+AF74*$F$11 -> 0 | AI74: =+(AF74+AG74+AH74) -> 0 | AK74: =+AA74 -> 47 | AL74: =+AB74 -> 69 | AM74: 0 | AN74: =+$F$9*AM74 -> 0 | AO74: =+AM74*$F$10 -> 0 | AP74: =+G74 -> 0 | AQ74: =+AT73 -> 75749.683 | AR74: =+(AN74*AP74+AO74*(AP74/12))*AM74 -> 0 | AS74: =+AQ74*$F$12 -> 3029.9873 | AT74: =+(AQ74+AR74+AS74) -> 78779.67 | AV74: =+AK74 -> 47 | AW74: =+AL74 -> 69 | AX74: 0 | AY74: =+$F$9*AX74 -> 0 | AZ74: =+AX74*$F$10 -> 0 | BA74: =+G74 -> 0 | BB74: =+BE73 -> 75749.683 | BC74: =+(AY74*BA74+AZ74*(BA74/12))*AX74 -> 0 | BD74: =+BB74*$F$12 -> 3029.9873 | BE74: =+(BB74+BC74+BD74) -> 78779.67
B75: =+B74+1 -> 48 | C75: =+C74+1 -> 69 | D75: =+D74*(1+$F$18) -> 1 | E75: =+IF($C75>=$F$6,0,$F$19*D75) -> 0 | F75: =+IF($C75>=$F$6,0,$F$20) -> 0 | G75: =+E75*F75 -> 0 | I75: =+I74+1 -> 48 | J75: =+C75 -> 69 | K75: =+IF(AL75<=$AF$11,1,0)*F75 -> 0 | L75: =+IF(AL75>$AF$11,0,IF(E75>500,500*F75,E75*F75)) -> 0 | M75: =+IF(AL75>$AF$11,0,IF(G75-L75 <= 0,0,G75-L75)) -> 0 | N75: =+IF($F$7<7,L75+M75,IF(AL75>$AF$11,0,IF($F$2=1,IF($J75<$F$5,IF(G75<=$F$16*12,G75,$F$16*12),G75),G75))) -> 0 | O75: =+IFERROR(N75/K75,0) -> 0 | Q75: =+I75 -> 48 | R75: =+J75+1 -> 70 | S75: =+IF(R75<=$AF$11,1,0) -> 0 | T75: =+T74 -> 0.1 | U75: =+M75 -> 0 | V75: =+Y74 -> 15005.652 | W75: =+T75*U75*S75 -> 0 | X75: =+$U$23*V75 -> 600.22606 | Y75: =+(V75+W75+X75) -> 15605.878 | AA75: =+B75 -> 48 | AB75: =+C75+1 -> 70 | AC75: =+IF(C75<$F$5,1,0) -> 0 | AD75: =+AD74 -> 0.15 | AE75: =+IF($F$2=1,IF(G75<=2500*12,G75,2500*12),G75) -> 0 | AF75: =+AI74 -> 0 | AG75: =+AD75*AE75*$AC75 -> 0 | AH75: =+AF75*$F$11 -> 0 | AI75: =+(AF75+AG75+AH75) -> 0 | AK75: =+AA75 -> 48 | AL75: =+AB75 -> 70 | AM75: 0 | AN75: =+$F$9*AM75 -> 0 | AO75: =+AM75*$F$10 -> 0 | AP75: =+G75 -> 0 | AQ75: =+AT74 -> 78779.67 | AR75: =+(AN75*AP75+AO75*(AP75/12))*AM75 -> 0 | AS75: =+AQ75*$F$12 -> 3151.1868 | AT75: =+(AQ75+AR75+AS75) -> 81930.857 | AV75: =+AK75 -> 48 | AW75: =+AL75 -> 70 | AX75: 0 | AY75: =+$F$9*AX75 -> 0 | AZ75: =+AX75*$F$10 -> 0 | BA75: =+G75 -> 0 | BB75: =+BE74 -> 78779.67 | BC75: =+(AY75*BA75+AZ75*(BA75/12))*AX75 -> 0 | BD75: =+BB75*$F$12 -> 3151.1868 | BE75: =+(BB75+BC75+BD75) -> 81930.857
B76: =+B75+1 -> 49 | C76: =+C75+1 -> 70 | D76: =+D75*(1+$F$18) -> 1 | E76: =+IF($C76>=$F$6,0,$F$19*D76) -> 0 | F76: =+IF($C76>=$F$6,0,$F$20) -> 0 | G76: =+E76*F76 -> 0 | I76: =+I75+1 -> 49 | J76: =+C76 -> 70 | K76: =+IF(AL76<=$AF$11,1,0)*F76 -> 0 | L76: =+IF(AL76>$AF$11,0,IF(E76>500,500*F76,E76*F76)) -> 0 | M76: =+IF(AL76>$AF$11,0,IF(G76-L76 <= 0,0,G76-L76)) -> 0 | N76: =+IF($F$7<7,L76+M76,IF(AL76>$AF$11,0,IF($F$2=1,IF($J76<$F$5,IF(G76<=$F$16*12,G76,$F$16*12),G76),G76))) -> 0 | O76: =+IFERROR(N76/K76,0) -> 0 | Q76: =+I76 -> 49 | R76: =+J76+1 -> 71 | S76: =+IF(R76<=$AF$11,1,0) -> 0 | T76: =+T75 -> 0.1 | U76: =+M76 -> 0 | V76: =+Y75 -> 15605.878 | W76: =+T76*U76*S76 -> 0 | X76: =+$U$23*V76 -> 624.2351 | Y76: =+(V76+W76+X76) -> 16230.113 | AA76: =+B76 -> 49 | AB76: =+C76+1 -> 71 | AC76: =+IF(C76<$F$5,1,0) -> 0 | AD76: =+AD75 -> 0.15 | AE76: =+IF($F$2=1,IF(G76<=2500*12,G76,2500*12),G76) -> 0 | AF76: =+AI75 -> 0 | AG76: =+AD76*AE76*$AC76 -> 0 | AH76: =+AF76*$F$11 -> 0 | AI76: =+(AF76+AG76+AH76) -> 0 | AK76: =+AA76 -> 49 | AL76: =+AB76 -> 71 | AM76: 0 | AN76: =+$F$9*AM76 -> 0 | AO76: =+AM76*$F$10 -> 0 | AP76: =+G76 -> 0 | AQ76: =+AT75 -> 81930.857 | AR76: =+(AN76*AP76+AO76*(AP76/12))*AM76 -> 0 | AS76: =+AQ76*$F$12 -> 3277.2343 | AT76: =+(AQ76+AR76+AS76) -> 85208.092 | AV76: =+AK76 -> 49 | AW76: =+AL76 -> 71 | AX76: 0 | AY76: =+$F$9*AX76 -> 0 | AZ76: =+AX76*$F$10 -> 0 | BA76: =+G76 -> 0 | BB76: =+BE75 -> 81930.857 | BC76: =+(AY76*BA76+AZ76*(BA76/12))*AX76 -> 0 | BD76: =+BB76*$F$12 -> 3277.2343 | BE76: =+(BB76+BC76+BD76) -> 85208.092
B93: =+B92/12 -> 0
B95: =+B93-BM8 -> -4200

Sheet calculo 25
B1: DATOS BASICOS | BH1: BENEFICIO DE JUBILACION CSS SEBD
B2: SISTEMA | F2: 1 | BH2: CUOTAS APORTADAS | BM2: =+SUM(K28:K76) -> 300
B3: SEXO | F3: =+salidaformulas!B2 -> M | Q3: MIXTO | AA3: CAPITALIZACIÓN SOLIDARIA | BH3: CUOTAS EN EXCESO A DENSIDAD MIN | BM3: =+IF(BM2>240,BM2-F13,0) -> 60
B4: EDAD ENTRADA | F4: =+salidaformulas!B3 -> 22 | I4: SOLIDARIO | BH4: TASA DE REEMPLAZO AJUSTADA SEBD LEY 51 | BM4: =IF(F7<=7,BN4,BN4*AF13) -> 0.6625 | BN4: =IF(AND(BM2>=180,BM2<240),($F$14+INT(BM3/12)*$F$15)*BM2/240,IF(BM2<180,0,($F$14+INT(BM3/12)*$F$15))) -> 0.6625
B5: EDAD ACTUAL DIA DE REFORMA | F5: =+F4 -> 22 | J5: Mej. Salario Anual | K5: Mej Salario Anual | S5: Mej. Salario Anual | T5: Mej Salario Anual | BH5: PENSION ANNUAL A RECIBIR | BM5: =+BM6*12 -> 3478.125
B6: EDAD DE JUBILACION | F6: =+salidaformulas!B4 -> 62 | I6: Mejores Años | J6: TOTAL | K6: Primer Pilar | R6: Mejores Años | S6: TOTAL | T6: Primer Pilar | BH6: PENSION MENSUAL A RECIBIR | BM6: =IF(BM2>=240,MAX(MAX(BL8:BL10),265),MAX(BL8:BL10)) -> 289.84375
B7: AÑOS PARA JUBILARSE | F7: =+F6-F5 -> 40 | I7: 1 | J7: =LARGE($G$28:$G$65,I7) -> 5250 | K7: =LARGE($L$28:$L$65,I7) -> 3750 | R7: 1 | S7: =+J7 -> 5250 | T7: =+K7 -> 3750 | BL7: PENSION | BM7: PROM. ANUAL | BN7: PROM.MENSUAL
B8: % CUOTA APLICADO ANTES VIGENCIA NVA LEY | F8: 0.15 | I8: 2 | J8: =LARGE($G$28:$G$65,I8) -> 5250 | K8: =LARGE($L$28:$L$65,I8) -> 3750 | R8: 2 | S8: =+J8 -> 5250 | T8: =+K8 -> 3750 | BH8: CALCULO DE LOS MEJORES 10 AÑOS | BL8: =+IF($BM$4*BM8/12>1500,1500,$BM$4*BM8/12) -> 289.84375 | BM8: {=+AVERAGE(LARGE($G$28:$G$76,ROW(INDIRECT("1:10"))))} -> 5250
B9: % CUOTA EMPLEADO EMPLEADOR NUEVA LEY | F9: 0.135 | I9: 3 | J9: =LARGE($G$28:$G$65,I9) -> 5250 | K9: =LARGE($L$28:$L$65,I9) -> 3750 | R9: 3 | S9: =+J9 -> 5250 | T9: =+K9 -> 3750 | BH9: CALCULO DE LOS MEJORES 15 AÑOS (300 CUOTAS Y PROM>=$2,000) | BL9: =+IF($BM$4*BM9/12>2000,2000,$BM$4*BM9/12) -> 0 | BM9: {=IF(AND(BM2>300,AVERAGE(LARGE($G$28:$G$76,ROW(INDIRECT("1:15"))))>=24000),AVERAGE(LARGE($G$28:$G$76,ROW(INDIRECT("1:15")))),0)} -> 0
B10: % XIII EMPLEADO EMPLEADOR NUEVA LEY | F10: 0.18 | I10: 4 | J10: =LARGE($G$28:$G$65,I10) -> 5250 | K10: =LARGE($L$28:$L$65,I10) -> 3750 | R10: 4 | S10: =+J10 -> 5250 | T10: =+K10 -> 3750 | AA10: SCGS-CUANDO VIENE DEL SEBD o SM | BH10: CALCULO DE LOS MEJORES 20 AÑOS (360 cuotas y prom>=$2,500) | BL10: =+IF($BM$4*BM10/12>2500,2500,$BM$4*BM10/12) -> 0 | BM10: {=IF(AND(BM2>360,AVERAGE(LARGE($G$28:$G$76,ROW(INDIRECT("1:20"))))>=30000),AVERAGE(LARGE($G$28:$G$76,ROW(INDIRECT("1:20")))),0)} -> 0
B11: TASA DE RETORNO INVERSIONES ANTES VIG LEY | F11: 0.04 | I11: 5 | J11: =LARGE($G$28:$G$65,I11) -> 5250 | K11: =LARGE($L$28:$L$65,I11) -> 3750 | R11: 5 | S11: =+J11 -> 5250 | T11: =+K11 -> 3750 | AA11: EDAD JUBILACION | AF11: =+F6 -> 62 | AK11: RESULTADO COMPARATIVO | AO11: MONTO | AP11: REEMPLAZO MEJ.AÑOS | BH11: TASA DE REEMPLAZO FINAL DE ESTE CALCULO | BM11: =+BM5/VLOOKUP(MAX(BL8:BL10),BL8:BM10,2,0) -> 0.6625
B12: TASA RETORNO INVERSIONES PROMEDIO | F12: 0.04 | I12: 6 | J12: =LARGE($G$28:$G$65,I12) -> 5250 | K12: =LARGE($L$28:$L$65,I12) -> 3750 | R12: 6 | S12: =+J12 -> 5250 | T12: =+K12 -> 3750 | AA12: FONDO AHORRADO COP ANTES VIGENCIA NVA LEY | AF12: =+VLOOKUP(AF11,$AB$28:$AI$76,8,FALSE) -> 0 | AG12: R | AK12: PENSION A RECIBIR DEL SEBD | AO12: =+L18 -> 289.84375 | AP12: =+AO12/(J16/12) -> 0.6625
A13: A | B13: DENSIDAD MINIMA DE CUOTAS LEY 51 | F13: 240 | I13: 7 | J13: =LARGE($G$28:$G$65,I13) -> 5250 | K13: =LARGE($L$28:$L$65,I13) -> 3750 | R13: 7 | S13: =+J13 -> 5250 | T13: =+K13 -> 3750 | W13: VP | X13: RA*ax | AA13: FACTOR DESCUENTO | AF13: =+IF(AND($B$20=1,$F$2<>1),100%,IF($F$3="M",VLOOKUP(AF11,descuento!$A$6:$B$32,2,FALSE),VLOOKUP(AF11,descuento!$C$6:$D$32,2,FALSE))) -> 1 | AK13: PENSION A RECIBIR SISTEMA MIXTO | AO13: =+U22 -> 280.5002 | AP13: =+AO13/(S17/12) -> 0.64114331 | AV13: FONDO TOTAL APLICABLE | BB13: =+VLOOKUP(AF11,$AW$28:$BE$76,9,FALSE) -> 74832.594 | BH13: BENEFICIO DEL SISTEMA MIXTO
A14: B | B14: TASA DE REEMPLAZO INICIAL LEY 51 | F14: 0.6 | I14: 8 | J14: =LARGE($G$28:$G$65,I14) -> 5250 | K14: =LARGE($L$28:$L$65,I14) -> 3750 | R14: 8 | S14: =+J14 -> 5250 | T14: =+K14 -> 3750 | W14: VP/ax | X14: 12*RM | AA14: FONDO AHORRADO COP DESPUES VIGENCIA NVA LEY | AF14: =+VLOOKUP(AF11,$AL$28:$AT$76,9,FALSE) -> 74832.594 | AG14: S | AK14: PENSION A RECIBIR DEL SCGS | AO14: =+AF17 -> 385.71197 | AP14: =+AO14/(S16/12) -> 0.88162736 | AV14: FACTOR PENSION X MIL | BB14: =+AF16 -> 5.1543312
A15: C | B15: TASA DE REEMPLAZO ADICIONAL LEY 51 | F15: 0.0125 | I15: 9 | J15: =LARGE($G$28:$G$65,I15) -> 5250 | K15: =LARGE($L$28:$L$65,I15) -> 3750 | R15: 9 | S15: =+J15 -> 5250 | T15: =+K15 -> 3750 | W15: vp * (1/ax) | AA15: FONDO TOTAL APLICABLE | AF15: =+AF14+AF12*AF13 -> 74832.594 | AG15: T=R+S | AK15: PENSION A RECIBIR SI ENTRA NUEVO | AO15: =+BB15 -> 385.71197 | AP15: =+AO15/(S17/12) -> 0.88162736 | AV15: PENSION SCGS MENSUAL | BB15: =+BB13*0.001*BB14 -> 385.71197 | BH15: PROMEDIO ANUAL MEJORES 10 AÑOS PRIMER PILAR | BM15: {=+AVERAGE(LARGE($L$28:$L$76,ROW(INDIRECT("1:10"))))} -> 3750
B16: SALMAX MENSUAL COTIZADO ANTES VIG NVA LEY | F16: 2500 | I16: 10 | J16: =LARGE($G$28:$G$65,I16) -> 5250 | K16: =LARGE($L$28:$L$65,I16) -> 3750 | R16: 10 | S16: =+J16 -> 5250 | T16: =+K16 -> 3750 | AA16: FACTOR PENSION X MIL | AF16: =+VLOOKUP(AF11,'bases renta'!$K$20:$L$65,2,FALSE) -> 5.1543312 | AG16: U | AV16: REEMPLAZO MEJ.AÑOS | BB16: =+BB15/(J17/12) -> 0.88162736 | BH16: PENSION MENSUAL A RECIBIR PRIMER PILAR | BM16: =+BM15*BM4/12 -> 207.03125
B17: PORCENTAJE DE CUOTA OP DESCONTADA SMP | F17: 0.035 | H17: F | I17: PROMEDIO ANUAL | J17: =+AVERAGE(J7:J16) -> 5250 | K17: =+AVERAGE(K7:K16) -> 3750 | Q17: F | R17: PROMEDIO ANUAL | S17: =+J17 -> 5250 | T17: =+K17 -> 3750 | U17: J | AA17: PENSION SCGS MENSUAL | AF17: =+AF15*0.001*AF16 -> 385.71197 | AG17: V=(T/1000)*U | BH17: AHORRO PENSIONAL EDAD JUBILACION | BM17: =+VLOOKUP(AF11,$R$28:$Y$76,8,FALSE) -> 14253.827
B18: CRECIMIENTO SALARIAL CADA DOS AÑOS | F18: 0 | I18: CUOTAS | J18: =+BM2 -> 300 | K18: PENSION MENSUAL SEBD | L18: =+MIN(J17*J20/12,F16) -> 289.84375 | M18: G=(F*E)/12 | R18: CUOTAS | S18: =+J18 -> 300 | T18: PENSION MENSUAL 1er pilarBD | U18: =+(K17*S20)/12 -> 207.03125 | V18: K=(E*J)/12 | W18: REEMPLAZO MEJ.AÑOS | X18: =+U22/(J17/12) -> 0.64114331 | Y18: P=O/(E/12) | AA18: REEMPLAZO MEJ.AÑOS | AF18: =+AF17/(J17/12) -> 0.88162736 | AG18: W=V/(E/12) | BH18: FACTOR DE PENSIONAMIENTO XMIL | BM18: =+AF16 -> 5.1543312
B19: SALARIO INICIAL | F19: =+salidaformulas!A10 -> 700 | H19: D | I19: EXCESO DENSIDAD | J19: =+BM3 -> 60 | K19: SALARIO PROMEDIO TOTAL MENSUAL COTIZADO | L19: =+F23 -> 437.5 | M19: H | R19: EXCESO DENSIDAD | S19: =+J19 -> 60 | T19: AHORRO PERSONAL | U19: =+BM17 -> 14253.827 | V19: L | W19: SALARIO PROMEDIO TOTAL MENSUAL COTIZADO | X19: =+L19 -> 437.5 | Y19: =+M19 -> H | AA19: SALARIO PROMEDIO TOTAL MENSUAL COTIZADO | AF19: =+X19 -> 437.5 | AG19: H | BH19: PENSION MENSUAL 2do PILAR | BM19: =+(BM17/1000)*BM18 -> 73.468947
B20: cuotas pagadas por año | F20: 7.5 | H20: E=B+C*D | I20: REEMPLAZO MEJ.AÑOS | J20: =+BM4 -> 0.6625 | K20: TASA BRUTA REEMPLAZO | L20: =+L18/L19 -> 0.6625 | M20: I=G/H | Q20: E | R20: REEMPLAZO MEJ.AÑOS | S20: =+J20 -> 0.6625 | T20: FACTOR PENSIONAMIENTO VITALICIO | U20: =+BM18 -> 5.1543312 | V20: M | W20: TASA BRUTA REEMPLAZO | X20: =+U22/L19 -> 0.64114331 | Y20: Q=O/H | AA20: TASA BRUTA REEMPLAZO | AF20: =+AF17/L19 -> 0.88162736 | AG20: X=V/H | BH20: PENSION FINAL SISTEMA MIXTO | BM20: =IF(BM2>=240,MAX(BM16+BM19,265),BM16+BM19) -> 280.5002
C21: TOTAL CUOTAS MENSUALES | F21: =+SUMIF(F28:F76,">0") -> 300 | G21: =+F21/12 -> 25 | T21: PENSION MENSUAL 2do PILAR | U21: =+U19*0.001*U20 -> 73.468947 | V21: N=(L/1000)*M | BH21: TASA DE REEMPLAZO FINAL DE ESTE CALCULO | BM21: =+BM20*12/VLOOKUP(MAX($BL$8:$BL$10),$BL$8:$BN$10,2,0) -> 0.64114331
C22: SALARIO PROMEDIO ANNUAL | F22: =+AVERAGEIF(G28:G76,">0") -> 5250 | T22: PENSION TOTAL A RECIBIR | U22: =+U21+U18 -> 280.5002 | V22: O=N+K
C23: PROMEDIO MENSUALIZADO | F23: =+F22/12 -> 437.5 | T23: tasa capitalizacion mixto | U23: 0.04
B24: Tabla 1 | I24: Tabla 2 | Q24: Tabla 3 | AA24: Tabla 4 | AK24: Tabla 5 | AV24: Tabla 6
B25: Datos Básicos | I25: SALARIOS PARA CALCULO PROMEDIO MEJORES | Q25: SISTEMA DE ACUMULACION DEL SISTEMA MIXTO | AA25: ACUMULACION SCGS ANTES DE LA ENTRADA EN VIGENCIA | AK25: ACUMULACION SCGS DESPUES DE LA ENTRADA EN VIGENCIA | AV25: ACUMULACION DESDE EL INICIO DENTRO DEL SISTEMA DE CAPITALIZACION CON GARANTIA SOLIDARIA
B26: AÑO | C26: EDAD INI AÑO | D26: CREC. SALARIO | E26: SALARIO MENSUAL | F26: CUOTAS APORTADAS | G26: SALARIO ANUAL | I26: AÑO | J26: EDAD | K26: CUOTAS APORTADAS | L26: SALARIO COTIZADO 1er PILAR SISTEMA MIXTO ANUAL | M26: SALARIO COTIZADO SEGUNDO PILAR ANUAL | N26: SALARIO COTIZADO PARA PROMEDIO ANUAL | O26: SALARIO COTIZADO PARA PROMEDIO MENSUAL | Q26: AÑO | R26: EDAD FIN AÑO | S26: INDICADOR | T26: TASA O-P SALARIO | U26: SALARIO SEGUNDO PILAR | V26: AHORRO PENSIONAL INICIAL | W26: APORTES | X26: INTERESES | Y26: AHORRO PENSIONAL FINAL | AA26: AÑO | AB26: EDAD FIN AÑO | AC26: INDICADOR | AD26: TASA O-P SALARIO | AE26: SALARIO ANUAL CON MAX 2500 MENSUAL | AF26: AHORRO PENSIONAL INICIAL | AG26: APORTES | AH26: INTERESES | AI26: AHORRO PENSIONAL FINAL | AK26: AÑO | AL26: EDAD FIN AÑO | AM26: INDICADOR | AN26: TASA O-P SALARIO | AO26: TASA O-P XIII | AP26: SALARIO ANUAL SIN MAXIMO | AQ26: AHORRO PENSIONAL INICIAL | AR26: APORTES | AS26: INTERESES | AT26: AHORRO PENSIONAL INICIAL | AV26: AÑO | AW26: EDAD FIN AÑO | AX26: INDICADOR | AY26: TASA O-P SALARIO | AZ26: TASA O-P XIII | BA26: SALARIO ANUAL SIN MAXIMO | BB26: AHORRO PENSIONAL INICIAL | BC26: APORTES | BD26: INTERESES | BE26: AHORRO PENSIONAL INICIAL
B28: 1 | C28: =+F4 -> 22 | D28: 1 | E28: =+IF($C28>=$F$6,0,$F$19*D28) -> 700 | F28: =+IF($C28>=$F$6,0,$F$20) -> 7.5 | G28: =+E28*F28 -> 5250 | I28: =+B28 -> 1 | J28: =+C28 -> 22 | K28: =+IF(AL28<=$AF$11,1,0)*F28 -> 7.5 | L28: =+IF(AL28>$AF$11,0,IF(E28>500,500*F28,E28*F28)) -> 3750 | M28: =+IF(AL28>$AF$11,0,IF(G28-L28 <= 0,0,G28-L28)) -> 1500 | N28: =+IF($F$7<7,L28+M28,IF(AL28>$AF$11,0,IF($F$2=1,IF($J28<$F$5,IF(G28<=$F$16*12,G28,$F$16*12),G28),G28))) -> 5250 | O28: =+IFERROR(N28/K28,0) -> 700 | Q28: =+I28 -> 1 | R28: =+J28+1 -> 23 | S28: =+IF(R28<=$AF$11,1,0) -> 1 | T28: =+$F$9-$F$17 -> 0.1 | U28: =+M28 -> 1500 | V28: =+Y27 -> 0 | W28: =+T28*U28*S28 -> 150 | X28: =+$U$23*V28 -> 0 | Y28: =+(V28+W28+X28) -> 150 | AA28: =+B28 -> 1 | AB28: =+C28+1 -> 23 | AC28: =+IF(C28<$F$5,1,0) -> 0 | AD28: =F8 -> 0.15 | AE28: =+IF($F$2=1,IF(G28<=2500*12,G28,2500*12),G28) -> 5250 | AF28: =+AI27 -> 0 | AG28: =+AD28*AE28*$AC28 -> 0 | AH28: =+AF28*$F$11 -> 0 | AI28: =+(AF28+AG28+AH28) -> 0 | AK28: =+AA28 -> 1 | AL28: =+AB28 -> 23 | AM28: =+IF($C28>=$F$5,1,0) -> 1 | AN28: =+$F$9*AM28 -> 0.135 | AO28: =+AM28*$F$10 -> 0.18 | AP28: =+G28 -> 5250 | AQ28: =+AT27 -> 0 | AR28: =+(AN28*AP28+AO28*(AP28/12))*AM28 -> 787.5 | AS28: =+AQ28*$F$12 -> 0 | AT28: =+(AQ28+AR28+AS28) -> 787.5 | AV28: =+AK28 -> 1 | AW28: =+AL28 -> 23 | AX28: 1 | AY28: =+$F$9*AX28 -> 0.135 | AZ28: =+AX28*$F$10 -> 0.18 | BA28: =+G28 -> 5250 | BB28: =+BE27 -> 0 | BC28: =+(AY28*BA28+AZ28*(BA28/12))*AX28 -> 787.5 | BD28: =+BB28*$F$12 -> 0 | BE28: =+(BB28+BC28+BD28) -> 787.5
B29: =+B28+1 -> 2 | C29: =+C28+1 -> 23 | D29: =+D28*(1+$F$18) -> 1 | E29: =+IF($C29>=$F$6,0,$F$19*D29) -> 700 | F29: =+IF($C29>=$F$6,0,$F$20) -> 7.5 | G29: =+E29*F29 -> 5250 | I29: =+I28+1 -> 2 | J29: =+C29 -> 23 | K29: =+IF(AL29<=$AF$11,1,0)*F29 -> 7.5 | L29: =+IF(AL29>$AF$11,0,IF(E29>500,500*F29,E29*F29)) -> 3750 | M29: =+IF(AL29>$AF$11,0,IF(G29-L29 <= 0,0,G29-L29)) -> 1500 | N29: =+IF($F$7<7,L29+M29,IF(AL29>$AF$11,0,IF($F$2=1,IF($J29<$F$5,IF(G29<=$F$16*12,G29,$F$16*12),G29),G29))) -> 5250 | O29: =+IFERROR(N29/K29,0) -> 700 | Q29: =+I29 -> 2 | R29: =+J29+1 -> 24 | S29: =+IF(R29<=$AF$11,1,0) -> 1 | T29: =+T28 -> 0.1 | U29: =+M29 -> 1500 | V29: =+Y28 -> 150 | W29: =+T29*U29*S29 -> 150 | X29: =+$U$23*V29 -> 6 | Y29: =+(V29+W29+X29) -> 306 | AA29: =+B29 -> 2 | AB29: =+C29+1 -> 24 | AC29: =+IF(C29<$F$5,1,0) -> 0 | AD29: =+AD28 -> 0.15 | AE29: =+IF($F$2=1,IF(G29<=2500*12,G29,2500*12),G29) -> 5250 | AF29: =+AI28 -> 0 | AG29: =+AD29*AE29*$AC29 -> 0 | AH29: =+AF29*$F$11 -> 0 | AI29: =+(AF29+AG29+AH29) -> 0 | AK29: =+AA29 -> 2 | AL29: =+AB29 -> 24 | AM29: =+IF($C29>=$F$5,1,0) -> 1 | AN29: =+$F$9*AM29 -> 0.135 | AO29: =+AM29*$F$10 -> 0.18 | AP29: =+G29 -> 5250 | AQ29: =+AT28 -> 787.5 | AR29: =+(AN29*AP29+AO29*(AP29/12))*AM29 -> 787.5 | AS29: =+AQ29*$F$12 -> 31.5 | AT29: =+(AQ29+AR29+AS29) -> 1606.5 | AV29: =+AK29 -> 2 | AW29: =+AL29 -> 24 | AX29: 1 | AY29: =+$F$9*AX29 -> 0.135 | AZ29: =+AX29*$F$10 -> 0.18 | BA29: =+G29 -> 5250 | BB29: =+BE28 -> 787.5 | BC29: =+(AY29*BA29+AZ29*(BA29/12))*AX29 -> 787.5 | BD29: =+BB29*$F$12 -> 31.5 | BE29: =+(BB29+BC29+BD29) -> 1606.5
B30: =+B29+1 -> 3 | C30: =+C29+1 -> 24 | D30: =+D29*(1+$F$18) -> 1 | E30: =+IF($C30>=$F$6,0,$F$19*D30) -> 700 | F30: =+IF($C30>=$F$6,0,$F$20) -> 7.5 | G30: =+E30*F30 -> 5250 | I30: =+I29+1 -> 3 | J30: =+C30 -> 24 | K30: =+IF(AL30<=$AF$11,1,0)*F30 -> 7.5 | L30: =+IF(AL30>$AF$11,0,IF(E30>500,500*F30,E30*F30)) -> 3750 | M30: =+IF(AL30>$AF$11,0,IF(G30-L30 <= 0,0,G30-L30)) -> 1500 | N30: =+IF($F$7<7,L30+M30,IF(AL30>$AF$11,0,IF($F$2=1,IF($J30<$F$5,IF(G30<=$F$16*12,G30,$F$16*12),G30),G30))) -> 5250 | O30: =+IFERROR(N30/K30,0) -> 700 | Q30: =+I30 -> 3 | R30: =+J30+1 -> 25 | S30: =+IF(R30<=$AF$11,1,0) -> 1 | T30: =+T29 -> 0.1 | U30: =+M30 -> 1500 | V30: =+Y29 -> 306 | W30: =+T30*U30*S30 -> 150 | X30: =+$U$23*V30 -> 12.24 | Y30: =+(V30+W30+X30) -> 468.24 | AA30: =+B30 -> 3 | AB30: =+C30+1 -> 25 | AC30: =+IF(C30<$F$5,1,0) -> 0 | AD30: =+AD29 -> 0.15 | AE30: =+IF($F$2=1,IF(G30<=2500*12,G30,2500*12),G30) -> 5250 | AF30: =+AI29 -> 0 | AG30: =+AD30*AE30*$AC30 -> 0 | AH30: =+AF30*$F$11 -> 0 | AI30: =+(AF30+AG30+AH30) -> 0 | AK30: =+AA30 -> 3 | AL30: =+AB30 -> 25 | AM30: =+IF($C30>=$F$5,1,0) -> 1 | AN30: =+$F$9*AM30 -> 0.135 | AO30: =+AM30*$F$10 -> 0.18 | AP30: =+G30 -> 5250 | AQ30: =+AT29 -> 1606.5 | AR30: =+(AN30*AP30+AO30*(AP30/12))*AM30 -> 787.5 | AS30: =+AQ30*$F$12 -> 64.26 | AT30: =+(AQ30+AR30+AS30) -> 2458.26 | AV30: =+AK30 -> 3 | AW30: =+AL30 -> 25 | AX30: 1 | AY30: =+$F$9*AX30 -> 0.135 | AZ30: =+AX30*$F$10 -> 0.18 | BA30: =+G30 -> 5250 | BB30: =+BE29 -> 1606.5 | BC30: =+(AY30*BA30+AZ30*(BA30/12))*AX30 -> 787.5 | BD30: =+BB30*$F$12 -> 64.26 | BE30: =+(BB30+BC30+BD30) -> 2458.26
B31: =+B30+1 -> 4 | C31: =+C30+1 -> 25 | D31: =+D30*(1+$F$18) -> 1 | E31: =+IF($C31>=$F$6,0,$F$19*D31) -> 700 | F31: =+IF($C31>=$F$6,0,$F$20) -> 7.5 | G31: =+E31*F31 -> 5250 | I31: =+I30+1 -> 4 | J31: =+C31 -> 25 | K31: =+IF(AL31<=$AF$11,1,0)*F31 -> 7.5 | L31: =+IF(AL31>$AF$11,0,IF(E31>500,500*F31,E31*F31)) -> 3750 | M31: =+IF(AL31>$AF$11,0,IF(G31-L31 <= 0,0,G31-L31)) -> 1500 | N31: =+IF($F$7<7,L31+M31,IF(AL31>$AF$11,0,IF($F$2=1,IF($J31<$F$5,IF(G31<=$F$16*12,G31,$F$16*12),G31),G31))) -> 5250 | O31: =+IFERROR(N31/K31,0) -> 700 | Q31: =+I31 -> 4 | R31: =+J31+1 -> 26 | S31: =+IF(R31<=$AF$11,1,0) -> 1 | T31: =+T30 -> 0.1 | U31: =+M31 -> 1500 | V31: =+Y30 -> 468.24 | W31: =+T31*U31*S31 -> 150 | X31: =+$U$23*V31 -> 18.7296 | Y31: =+(V31+W31+X31) -> 636.9696 | AA31: =+B31 -> 4 | AB31: =+C31+1 -> 26 | AC31: =+IF(C31<$F$5,1,0) -> 0 | AD31: =+AD30 -> 0.15 | AE31: =+IF($F$2=1,IF(G31<=2500*12,G31,2500*12),G31) -> 5250 | AF31: =+AI30 -> 0 | AG31: =+AD31*AE31*$AC31 -> 0 | AH31: =+AF31*$F$11 -> 0 | AI31: =+(AF31+AG31+AH31) -> 0 | AK31: =+AA31 -> 4 | AL31: =+AB31 -> 26 | AM31: =+IF($C31>=$F$5,1,0) -> 1 | AN31: =+$F$9*AM31 -> 0.135 | AO31: =+AM31*$F$10 -> 0.18 | AP31: =+G31 -> 5250 | AQ31: =+AT30 -> 2458.26 | AR31: =+(AN31*AP31+AO31*(AP31/12))*AM31 -> 787.5 | AS31: =+AQ31*$F$12 -> 98.3304 | AT31: =+(AQ31+AR31+AS31) -> 3344.0904 | AV31: =+AK31 -> 4 | AW31: =+AL31 -> 26 | AX31: 1 | AY31: =+$F$9*AX31 -> 0.135 | AZ31: =+AX31*$F$10 -> 0.18 | BA31: =+G31 -> 5250 | BB31: =+BE30 -> 2458.26 | BC31: =+(AY31*BA31+AZ31*(BA31/12))*AX31 -> 787.5 | BD31: =+BB31*$F$12 -> 98.3304 | BE31: =+(BB31+BC31+BD31) -> 3344.0904
B32: =+B31+1 -> 5 | C32: =+C31+1 -> 26 | D32: =+D31*(1+$F$18) -> 1 | E32: =+IF($C32>=$F$6,0,$F$19*D32) -> 700 | F32: =+IF($C32>=$F$6,0,$F$20) -> 7.5 | G32: =+E32*F32 -> 5250 | I32: =+I31+1 -> 5 | J32: =+C32 -> 26 | K32: =+IF(AL32<=$AF$11,1,0)*F32 -> 7.5 | L32: =+IF(AL32>$AF$11,0,IF(E32>500,500*F32,E32*F32)) -> 3750 | M32: =+IF(AL32>$AF$11,0,IF(G32-L32 <= 0,0,G32-L32)) -> 1500 | N32: =+IF($F$7<7,L32+M32,IF(AL32>$AF$11,0,IF($F$2=1,IF($J32<$F$5,IF(G32<=$F$16*12,G32,$F$16*12),G32),G32))) -> 5250 | O32: =+IFERROR(N32/K32,0) -> 700 | Q32: =+I32 -> 5 | R32: =+J32+1 -> 27 | S32: =+IF(R32<=$AF$11,1,0) -> 1 | T32: =+T31 -> 0.1 | U32: =+M32 -> 1500 | V32: =+Y31 -> 636.9696 | W32: =+T32*U32*S32 -> 150 | X32: =+$U$23*V32 -> 25.478784 | Y32: =+(V32+W32+X32) -> 812.44838 | AA32: =+B32 -> 5 | AB32: =+C32+1 -> 27 | AC32: =+IF(C32<$F$5,1,0) -> 0 | AD32: =+AD31 -> 0.15 | AE32: =+IF($F$2=1,IF(G32<=2500*12,G32,2500*12),G32) -> 5250 | AF32: =+AI31 -> 0 | AG32: =+AD32*AE32*$AC32 -> 0 | AH32: =+AF32*$F$11 -> 0 | AI32: =+(AF32+AG32+AH32) -> 0 | AK32: =+AA32 -> 5 | AL32: =+AB32 -> 27 | AM32: =+IF($C32>=$F$5,1,0) -> 1 | AN32: =+$F$9*AM32 -> 0.135 | AO32: =+AM32*$F$10 -> 0.18 | AP32: =+G32 -> 5250 | AQ32: =+AT31 -> 3344.0904 | AR32: =+(AN32*AP32+AO32*(AP32/12))*AM32 -> 787.5 | AS32: =+AQ32*$F$12 -> 133.76362 | AT32: =+(AQ32+AR32+AS32) -> 4265.354 | AV32: =+AK32 -> 5 | AW32: =+AL32 -> 27 | AX32: 1 | AY32: =+$F$9*AX32 -> 0.135 | AZ32: =+AX32*$F$10 -> 0.18 | BA32: =+G32 -> 5250 | BB32: =+BE31 -> 3344.0904 | BC32: =+(AY32*BA32+AZ32*(BA32/12))*AX32 -> 787.5 | BD32: =+BB32*$F$12 -> 133.76362 | BE32: =+(BB32+BC32+BD32) -> 4265.354
B33: =+B32+1 -> 6 | C33: =+C32+1 -> 27 | D33: =+D32*(1+$F$18) -> 1 | E33: =+IF($C33>=$F$6,0,$F$19*D33) -> 700 | F33: =+IF($C33>=$F$6,0,$F$20) -> 7.5 | G33: =+E33*F33 -> 5250 | I33: =+I32+1 -> 6 | J33: =+C33 -> 27 | K33: =+IF(AL33<=$AF$11,1,0)*F33 -> 7.5 | L33: =+IF(AL33>$AF$11,0,IF(E33>500,500*F33,E33*F33)) -> 3750 | M33: =+IF(AL33>$AF$11,0,IF(G33-L33 <= 0,0,G33-L33)) -> 1500 | N33: =+IF($F$7<7,L33+M33,IF(AL33>$AF$11,0,IF($F$2=1,IF($J33<$F$5,IF(G33<=$F$16*12,G33,$F$16*12),G33),G33))) -> 5250 | O33: =+IFERROR(N33/K33,0) -> 700 | Q33: =+I33 -> 6 | R33: =+J33+1 -> 28 | S33: =+IF(R33<=$AF$11,1,0) -> 1 | T33: =+T32 -> 0.1 | U33: =+M33 -> 1500 | V33: =+Y32 -> 812.44838 | W33: =+T33*U33*S33 -> 150 | X33: =+$U$23*V33 -> 32.497935 | Y33: =+(V33+W33+X33) -> 994.94632 | AA33: =+B33 -> 6 | AB33: =+C33+1 -> 28 | AC33: =+IF(C33<$F$5,1,0) -> 0 | AD33: =+AD32 -> 0.15 | AE33: =+IF($F$2=1,IF(G33<=2500*12,G33,2500*12),G33) -> 5250 | AF33: =+AI32 -> 0 | AG33: =+AD33*AE33*$AC33 -> 0 | AH33: =+AF33*$F$11 -> 0 | AI33: =+(AF33+AG33+AH33) -> 0 | AK33: =+AA33 -> 6 | AL33: =+AB33 -> 28 | AM33: =+IF($C33>=$F$5,1,0) -> 1 | AN33: =+$F$9*AM33 -> 0.135 | AO33: =+AM33*$F$10 -> 0.18 | AP33: =+G33 -> 5250 | AQ33: =+AT32 -> 4265.354 | AR33: =+(AN33*AP33+AO33*(AP33/12))*AM33 -> 787.5 | AS33: =+AQ33*$F$12 -> 170.61416 | AT33: =+(AQ33+AR33+AS33) -> 5223.4682 | AV33: =+AK33 -> 6 | AW33: =+AL33 -> 28 | AX33: 1 | AY33: =+$F$9*AX33 -> 0.135 | AZ33: =+AX33*$F$10 -> 0.18 | BA33: =+G33 -> 5250 | BB33: =+BE32 -> 4265.354 | BC33: =+(AY33*BA33+AZ33*(BA33/12))*AX33 -> 787.5 | BD33: =+BB33*$F$12 -> 170.61416 | BE33: =+(BB33+BC33+BD33) -> 5223.4682
B34: =+B33+1 -> 7 | C34: =+C33+1 -> 28 | D34: =+D33*(1+$F$18) -> 1 | E34: =+IF($C34>=$F$6,0,$F$19*D34) -> 700 | F34: =+IF($C34>=$F$6,0,$F$20) -> 7.5 | G34: =+E34*F34 -> 5250 | I34: =+I33+1 -> 7 | J34: =+C34 -> 28 | K34: =+IF(AL34<=$AF$11,1,0)*F34 -> 7.5 | L34: =+IF(AL34>$AF$11,0,IF(E34>500,500*F34,E34*F34)) -> 3750 | M34: =+IF(AL34>$AF$11,0,IF(G34-L34 <= 0,0,G34-L34)) -> 1500 | N34: =+IF($F$7<7,L34+M34,IF(AL34>$AF$11,0,IF($F$2=1,IF($J34<$F$5,IF(G34<=$F$16*12,G34,$F$16*12),G34),G34))) -> 5250 | O34: =+IFERROR(N34/K34,0) -> 700 | Q34: =+I34 -> 7 | R34: =+J34+1 -> 29 | S34: =+IF(R34<=$AF$11,1,0) -> 1 | T34: =+T33 -> 0.1 | U34: =+M34 -> 1500 | V34: =+Y33 -> 994.94632 | W34: =+T34*U34*S34 -> 150 | X34: =+$U$23*V34 -> 39.797853 | Y34: =+(V34+W34+X34) -> 1184.7442 | AA34: =+B34 -> 7 | AB34: =+C34+1 -> 29 | AC34: =+IF(C34<$F$5,1,0) -> 0 | AD34: =+AD33 -> 0.15 | AE34: =+IF($F$2=1,IF(G34<=2500*12,G34,2500*12),G34) -> 5250 | AF34: =+AI33 -> 0 | AG34: =+AD34*AE34*$AC34 -> 0 | AH34: =+AF34*$F$11 -> 0 | AI34: =+(AF34+AG34+AH34) -> 0 | AK34: =+AA34 -> 7 | AL34: =+AB34 -> 29 | AM34: =+IF($C34>=$F$5,1,0) -> 1 | AN34: =+$F$9*AM34 -> 0.135 | AO34: =+AM34*$F$10 -> 0.18 | AP34: =+G34 -> 5250 | AQ34: =+AT33 -> 5223.4682 | AR34: =+(AN34*AP34+AO34*(AP34/12))*AM34 -> 787.5 | AS34: =+AQ34*$F$12 -> 208.93873 | AT34: =+(AQ34+AR34+AS34) -> 6219.9069 | AV34: =+AK34 -> 7 | AW34: =+AL34 -> 29 | AX34: 1 | AY34: =+$F$9*AX34 -> 0.135 | AZ34: =+AX34*$F$10 -> 0.18 | BA34: =+G34 -> 5250 | BB34: =+BE33 -> 5223.4682 | BC34: =+(AY34*BA34+AZ34*(BA34/12))*AX34 -> 787.5 | BD34: =+BB34*$F$12 -> 208.93873 | BE34: =+(BB34+BC34+BD34) -> 6219.9069
B35: =+B34+1 -> 8 | C35: =+C34+1 -> 29 | D35: =+D34*(1+$F$18) -> 1 | E35: =+IF($C35>=$F$6,0,$F$19*D35) -> 700 | F35: =+IF($C35>=$F$6,0,$F$20) -> 7.5 | G35: =+E35*F35 -> 5250 | I35: =+I34+1 -> 8 | J35: =+C35 -> 29 | K35: =+IF(AL35<=$AF$11,1,0)*F35 -> 7.5 | L35: =+IF(AL35>$AF$11,0,IF(E35>500,500*F35,E35*F35)) -> 3750 | M35: =+IF(AL35>$AF$11,0,IF(G35-L35 <= 0,0,G35-L35)) -> 1500 | N35: =+IF($F$7<7,L35+M35,IF(AL35>$AF$11,0,IF($F$2=1,IF($J35<$F$5,IF(G35<=$F$16*12,G35,$F$16*12),G35),G35))) -> 5250 | O35: =+IFERROR(N35/K35,0) -> 700 | Q35: =+I35 -> 8 | R35: =+J35+1 -> 30 | S35: =+IF(R35<=$AF$11,1,0) -> 1 | T35: =+T34 -> 0.1 | U35: =+M35 -> 1500 | V35: =+Y34 -> 1184.7442 | W35: =+T35*U35*S35 -> 150 | X35: =+$U$23*V35 -> 47.389767 | Y35: =+(V35+W35+X35) -> 1382.1339 | AA35: =+B35 -> 8 | AB35: =+C35+1 -> 30 | AC35: =+IF(C35<$F$5,1,0) -> 0 | AD35: =+AD34 -> 0.15 | AE35: =+IF($F$2=1,IF(G35<=2500*12,G35,2500*12),G35) -> 5250 | AF35: =+AI34 -> 0 | AG35: =+AD35*AE35*$AC35 -> 0 | AH35: =+AF35*$F$11 -> 0 | AI35: =+(AF35+AG35+AH35) -> 0 | AK35: =+AA35 -> 8 | AL35: =+AB35 -> 30 | AM35: =+IF($C35>=$F$5,1,0) -> 1 | AN35: =+$F$9*AM35 -> 0.135 | AO35: =+AM35*$F$10 -> 0.18 | AP35: =+G35 -> 5250 | AQ35: =+AT34 -> 6219.9069 | AR35: =+(AN35*AP35+AO35*(AP35/12))*AM35 -> 787.5 | AS35: =+AQ35*$F$12 -> 248.79628 | AT35: =+(AQ35+AR35+AS35) -> 7256.2032 | AV35: =+AK35 -> 8 | AW35: =+AL35 -> 30 | AX35: 1 | AY35: =+$F$9*AX35 -> 0.135 | AZ35: =+AX35*$F$10 -> 0.18 | BA35: =+G35 -> 5250 | BB35: =+BE34 -> 6219.9069 | BC35: =+(AY35*BA35+AZ35*(BA35/12))*AX35 -> 787.5 | BD35: =+BB35*$F$12 -> 248.79628 | BE35: =+(BB35+BC35+BD35) -> 7256.2032
B36: =+B35+1 -> 9 | C36: =+C35+1 -> 30 | D36: =+D35*(1+$F$18) -> 1 | E36: =+IF($C36>=$F$6,0,$F$19*D36) -> 700 | F36: =+IF($C36>=$F$6,0,$F$20) -> 7.5 | G36: =+E36*F36 -> 5250 | I36: =+I35+1 -> 9 | J36: =+C36 -> 30 | K36: =+IF(AL36<=$AF$11,1,0)*F36 -> 7.5 | L36: =+IF(AL36>$AF$11,0,IF(E36>500,500*F36,E36*F36)) -> 3750 | M36: =+IF(AL36>$AF$11,0,IF(G36-L36 <= 0,0,G36-L36)) -> 1500 | N36: =+IF($F$7<7,L36+M36,IF(AL36>$AF$11,0,IF($F$2=1,IF($J36<$F$5,IF(G36<=$F$16*12,G36,$F$16*12),G36),G36))) -> 5250 | O36: =+IFERROR(N36/K36,0) -> 700 | Q36: =+I36 -> 9 | R36: =+J36+1 -> 31 | S36: =+IF(R36<=$AF$11,1,0) -> 1 | T36: =+T35 -> 0.1 | U36: =+M36 -> 1500 | V36: =+Y35 -> 1382.1339 | W36: =+T36*U36*S36 -> 150 | X36: =+$U$23*V36 -> 55.285358 | Y36: =+(V36+W36+X36) -> 1587.4193 | AA36: =+B36 -> 9 | AB36: =+C36+1 -> 31 | AC36: =+IF(C36<$F$5,1,0) -> 0 | AD36: =+AD35 -> 0.15 | AE36: =+IF($F$2=1,IF(G36<=2500*12,G36,2500*12),G36) -> 5250 | AF36: =+AI35 -> 0 | AG36: =+AD36*AE36*$AC36 -> 0 | AH36: =+AF36*$F$11 -> 0 | AI36: =+(AF36+AG36+AH36) -> 0 | AK36: =+AA36 -> 9 | AL36: =+AB36 -> 31 | AM36: =+IF($C36>=$F$5,1,0) -> 1 | AN36: =+$F$9*AM36 -> 0.135 | AO36: =+AM36*$F$10 -> 0.18 | AP36: =+G36 -> 5250 | AQ36: =+AT35 -> 7256.2032 | AR36: =+(AN36*AP36+AO36*(AP36/12))*AM36 -> 787.5 | AS36: =+AQ36*$F$12 -> 290.24813 | AT36: =+(AQ36+AR36+AS36) -> 8333.9513 | AV36: =+AK36 -> 9 | AW36: =+AL36 -> 31 | AX36: 1 | AY36: =+$F$9*AX36 -> 0.135 | AZ36: =+AX36*$F$10 -> 0.18 | BA36: =+G36 -> 5250 | BB36: =+BE35 -> 7256.2032 | BC36: =+(AY36*BA36+AZ36*(BA36/12))*AX36 -> 787.5 | BD36: =+BB36*$F$12 -> 290.24813 | BE36: =+(BB36+BC36+BD36) -> 8333.9513
B37: =+B36+1 -> 10 | C37: =+C36+1 -> 31 | D37: =+D36*(1+$F$18) -> 1 | E37: =+IF($C37>=$F$6,0,$F$19*D37) -> 700 | F37: =+IF($C37>=$F$6,0,$F$20) -> 7.5 | G37: =+E37*F37 -> 5250 | I37: =+I36+1 -> 10 | J37: =+C37 -> 31 | K37: =+IF(AL37<=$AF$11,1,0)*F37 -> 7.5 | L37: =+IF(AL37>$AF$11,0,IF(E37>500,500*F37,E37*F37)) -> 3750 | M37: =+IF(AL37>$AF$11,0,IF(G37-L37 <= 0,0,G37-L37)) -> 1500 | N37: =+IF($F$7<7,L37+M37,IF(AL37>$AF$11,0,IF($F$2=1,IF($J37<$F$5,IF(G37<=$F$16*12,G37,$F$16*12),G37),G37))) -> 5250 | O37: =+IFERROR(N37/K37,0) -> 700 | Q37: =+I37 -> 10 | R37: =+J37+1 -> 32 | S37: =+IF(R37<=$AF$11,1,0) -> 1 | T37: =+T36 -> 0.1 | U37: =+M37 -> 1500 | V37: =+Y36 -> 1587.4193 | W37: =+T37*U37*S37 -> 150 | X37: =+$U$23*V37 -> 63.496772 | Y37: =+(V37+W37+X37) -> 1800.9161 | AA37: =+B37 -> 10 | AB37: =+C37+1 -> 32 | AC37: =+IF(C37<$F$5,1,0) -> 0 | AD37: =+AD36 -> 0.15 | AE37: =+IF($F$2=1,IF(G37<=2500*12,G37,2500*12),G37) -> 5250 | AF37: =+AI36 -> 0 | AG37: =+AD37*AE37*$AC37 -> 0 | AH37: =+AF37*$F$11 -> 0 | AI37: =+(AF37+AG37+AH37) -> 0 | AK37: =+AA37 -> 10 | AL37: =+AB37 -> 32 | AM37: =+IF($C37>=$F$5,1,0) -> 1 | AN37: =+$F$9*AM37 -> 0.135 | AO37: =+AM37*$F$10 -> 0.18 | AP37: =+G37 -> 5250 | AQ37: =+AT36 -> 8333.9513 | AR37: =+(AN37*AP37+AO37*(AP37/12))*AM37 -> 787.5 | AS37: =+AQ37*$F$12 -> 333.35805 | AT37: =+(AQ37+AR37+AS37) -> 9454.8094 | AV37: =+AK37 -> 10 | AW37: =+AL37 -> 32 | AX37: 1 | AY37: =+$F$9*AX37 -> 0.135 | AZ37: =+AX37*$F$10 -> 0.18 | BA37: =+G37 -> 5250 | BB37: =+BE36 -> 8333.9513 | BC37: =+(AY37*BA37+AZ37*(BA37/12))*AX37 -> 787.5 | BD37: =+BB37*$F$12 -> 333.35805 | BE37: =+(BB37+BC37+BD37) -> 9454.8094
B38: =+B37+1 -> 11 | C38: =+C37+1 -> 32 | D38: =+D37*(1+$F$18) -> 1 | E38: =+IF($C38>=$F$6,0,$F$19*D38) -> 700 | F38: =+IF($C38>=$F$6,0,$F$20) -> 7.5 | G38: =+E38*F38 -> 5250 | I38: =+I37+1 -> 11 | J38: =+C38 -> 32 | K38: =+IF(AL38<=$AF$11,1,0)*F38 -> 7.5 | L38: =+IF(AL38>$AF$11,0,IF(E38>500,500*F38,E38*F38)) -> 3750 | M38: =+IF(AL38>$AF$11,0,IF(G38-L38 <= 0,0,G38-L38)) -> 1500 | N38: =+IF($F$7<7,L38+M38,IF(AL38>$AF$11,0,IF($F$2=1,IF($J38<$F$5,IF(G38<=$F$16*12,G38,$F$16*12),G38),G38))) -> 5250 | O38: =+IFERROR(N38/K38,0) -> 700 | Q38: =+I38 -> 11 | R38: =+J38+1 -> 33 | S38: =+IF(R38<=$AF$11,1,0) -> 1 | T38: =+T37 -> 0.1 | U38: =+M38 -> 1500 | V38: =+Y37 -> 1800.9161 | W38: =+T38*U38*S38 -> 150 | X38: =+$U$23*V38 -> 72.036643 | Y38: =+(V38+W38+X38) -> 2022.9527 | AA38: =+B38 -> 11 | AB38: =+C38+1 -> 33 | AC38: =+IF(C38<$F$5,1,0) -> 0 | AD38: =+AD37 -> 0.15 | AE38: =+IF($F$2=1,IF(G38<=2500*12,G38,2500*12),G38) -> 5250 | AF38: =+AI37 -> 0 | AG38: =+AD38*AE38*$AC38 -> 0 | AH38: =+AF38*$F$11 -> 0 | AI38: =+(AF38+AG38+AH38) -> 0 | AK38: =+AA38 -> 11 | AL38: =+AB38 -> 33 | AM38: =+IF($C38>=$F$5,1,0) -> 1 | AN38: =+$F$9*AM38 -> 0.135 | AO38: =+AM38*$F$10 -> 0.18 | AP38: =+G38 -> 5250 | AQ38: =+AT37 -> 9454.8094 | AR38: =+(AN38*AP38+AO38*(AP38/12))*AM38 -> 787.5 | AS38: =+AQ38*$F$12 -> 378.19237 | AT38: =+(AQ38+AR38+AS38) -> 10620.502 | AV38: =+AK38 -> 11 | AW38: =+AL38 -> 33 | AX38: 1 | AY38: =+$F$9*AX38 -> 0.135 | AZ38: =+AX38*$F$10 -> 0.18 | BA38: =+G38 -> 5250 | BB38: =+BE37 -> 9454.8094 | BC38: =+(AY38*BA38+AZ38*(BA38/12))*AX38 -> 787.5 | BD38: =+BB38*$F$12 -> 378.19237 | BE38: =+(BB38+BC38+BD38) -> 10620.502
B39: =+B38+1 -> 12 | C39: =+C38+1 -> 33 | D39: =+D38*(1+$F$18) -> 1 | E39: =+IF($C39>=$F$6,0,$F$19*D39) -> 700 | F39: =+IF($C39>=$F$6,0,$F$20) -> 7.5 | G39: =+E39*F39 -> 5250 | I39: =+I38+1 -> 12 | J39: =+C39 -> 33 | K39: =+IF(AL39<=$AF$11,1,0)*F39 -> 7.5 | L39: =+IF(AL39>$AF$11,0,IF(E39>500,500*F39,E39*F39)) -> 3750 | M39: =+IF(AL39>$AF$11,0,IF(G39-L39 <= 0,0,G39-L39)) -> 1500 | N39: =+IF($F$7<7,L39+M39,IF(AL39>$AF$11,0,IF($F$2=1,IF($J39<$F$5,IF(G39<=$F$16*12,G39,$F$16*12),G39),G39))) -> 5250 | O39: =+IFERROR(N39/K39,0) -> 700 | Q39: =+I39 -> 12 | R39: =+J39+1 -> 34 | S39: =+IF(R39<=$AF$11,1,0) -> 1 | T39: =+T38 -> 0.1 | U39: =+M39 -> 1500 | V39: =+Y38 -> 2022.9527 | W39: =+T39*U39*S39 -> 150 | X39: =+$U$23*V39 -> 80.918108 | Y39: =+(V39+W39+X39) -> 2253.8708 | AA39: =+B39 -> 12 | AB39: =+C39+1 -> 34 | AC39: =+IF(C39<$F$5,1,0) -> 0 | AD39: =+AD38 -> 0.15 | AE39: =+IF($F$2=1,IF(G39<=2500*12,G39,2500*12),G39) -> 5250 | AF39: =+AI38 -> 0 | AG39: =+AD39*AE39*$AC39 -> 0 | AH39: =+AF39*$F$11 -> 0 | AI39: =+(AF39+AG39+AH39) -> 0 | AK39: =+AA39 -> 12 | AL39: =+AB39 -> 34 | AM39: =+IF($C39>=$F$5,1,0) -> 1 | AN39: =+$F$9*AM39 -> 0.135 | AO39: =+AM39*$F$10 -> 0.18 | AP39: =+G39 -> 5250 | AQ39: =+AT38 -> 10620.502 | AR39: =+(AN39*AP39+AO39*(AP39/12))*AM39 -> 787.5 | AS39: =+AQ39*$F$12 -> 424.82007 | AT39: =+(AQ39+AR39+AS39) -> 11832.822 | AV39: =+AK39 -> 12 | AW39: =+AL39 -> 34 | AX39: 1 | AY39: =+$F$9*AX39 -> 0.135 | AZ39: =+AX39*$F$10 -> 0.18 | BA39: =+G39 -> 5250 | BB39: =+BE38 -> 10620.502 | BC39: =+(AY39*BA39+AZ39*(BA39/12))*AX39 -> 787.5 | BD39: =+BB39*$F$12 -> 424.82007 | BE39: =+(BB39+BC39+BD39) -> 11832.822
B40: =+B39+1 -> 13 | C40: =+C39+1 -> 34 | D40: =+D39*(1+$F$18) -> 1 | E40: =+IF($C40>=$F$6,0,$F$19*D40) -> 700 | F40: =+IF($C40>=$F$6,0,$F$20) -> 7.5 | G40: =+E40*F40 -> 5250 | I40: =+I39+1 -> 13 | J40: =+C40 -> 34 | K40: =+IF(AL40<=$AF$11,1,0)*F40 -> 7.5 | L40: =+IF(AL40>$AF$11,0,IF(E40>500,500*F40,E40*F40)) -> 3750 | M40: =+IF(AL40>$AF$11,0,IF(G40-L40 <= 0,0,G40-L40)) -> 1500 | N40: =+IF($F$7<7,L40+M40,IF(AL40>$AF$11,0,IF($F$2=1,IF($J40<$F$5,IF(G40<=$F$16*12,G40,$F$16*12),G40),G40))) -> 5250 | O40: =+IFERROR(N40/K40,0) -> 700 | Q40: =+I40 -> 13 | R40: =+J40+1 -> 35 | S40: =+IF(R40<=$AF$11,1,0) -> 1 | T40: =+T39 -> 0.1 | U40: =+M40 -> 1500 | V40: =+Y39 -> 2253.8708 | W40: =+T40*U40*S40 -> 150 | X40: =+$U$23*V40 -> 90.154833 | Y40: =+(V40+W40+X40) -> 2494.0257 | AA40: =+B40 -> 13 | AB40: =+C40+1 -> 35 | AC40: =+IF(C40<$F$5,1,0) -> 0 | AD40: =+AD39 -> 0.15 | AE40: =+IF($F$2=1,IF(G40<=2500*12,G40,2500*12),G40) -> 5250 | AF40: =+AI39 -> 0 | AG40: =+AD40*AE40*$AC40 -> 0 | AH40: =+AF40*$F$11 -> 0 | AI40: =+(AF40+AG40+AH40) -> 0 | AK40: =+AA40 -> 13 | AL40: =+AB40 -> 35 | AM40: =+IF($C40>=$F$5,1,0) -> 1 | AN40: =+$F$9*AM40 -> 0.135 | AO40: =+AM40*$F$10 -> 0.18 | AP40: =+G40 -> 5250 | AQ40: =+AT39 -> 11832.822 | AR40: =+(AN40*AP40+AO40*(AP40/12))*AM40 -> 787.5 | AS40: =+AQ40*$F$12 -> 473.31287 | AT40: =+(AQ40+AR40+AS40) -> 13093.635 | AV40: =+AK40 -> 13 | AW40: =+AL40 -> 35 | AX40: 1 | AY40: =+$F$9*AX40 -> 0.135 | AZ40: =+AX40*$F$10 -> 0.18 | BA40: =+G40 -> 5250 | BB40: =+BE39 -> 11832.822 | BC40: =+(AY40*BA40+AZ40*(BA40/12))*AX40 -> 787.5 | BD40: =+BB40*$F$12 -> 473.31287 | BE40: =+(BB40+BC40+BD40) -> 13093.635
... B65: =+B64+1 -> 38 | C65: =+C64+1 -> 59 | D65: =+D64*(1+$F$18) -> 1 | E65: =+IF($C65>=$F$6,0,$F$19*D65) -> 700 | F65: =+IF($C65>=$F$6,0,$F$20) -> 7.5 | G65: =+E65*F65 -> 5250 | I65: =+I64+1 -> 38 | J65: =+C65 -> 59 | K65: =+IF(AL65<=$AF$11,1,0)*F65 -> 7.5 | L65: =+IF(AL65>$AF$11,0,IF(E65>500,500*F65,E65*F65)) -> 3750 | M65: =+IF(AL65>$AF$11,0,IF(G65-L65 <= 0,0,G65-L65)) -> 1500 | N65: =+IF($F$7<7,L65+M65,IF(AL65>$AF$11,0,IF($F$2=1,IF($J65<$F$5,IF(G65<=$F$16*12,G65,$F$16*12),G65),G65))) -> 5250 | O65: =+IFERROR(N65/K65,0) -> 700 | Q65: =+I65 -> 38 | R65: =+J65+1 -> 60 | S65: =+IF(R65<=$AF$11,1,0) -> 1 | T65: =+T64 -> 0.1 | U65: =+M65 -> 1500 | V65: =+Y64 -> 12255.337 | W65: =+T65*U65*S65 -> 150 | X65: =+$U$23*V65 -> 490.21348 | Y65: =+(V65+W65+X65) -> 12895.55 | AA65: =+B65 -> 38 | AB65: =+C65+1 -> 60 | AC65: =+IF(C65<$F$5,1,0) -> 0 | AD65: =+AD64 -> 0.15 | AE65: =+IF($F$2=1,IF(G65<=2500*12,G65,2500*12),G65) -> 5250 | AF65: =+AI64 -> 0 | AG65: =+AD65*AE65*$AC65 -> 0 | AH65: =+AF65*$F$11 -> 0 | AI65: =+(AF65+AG65+AH65) -> 0 | AK65: =+AA65 -> 38 | AL65: =+AB65 -> 60 | AM65: =+IF($C65>=$F$5,1,0) -> 1 | AN65: =+$F$9*AM65 -> 0.135 | AO65: =+AM65*$F$10 -> 0.18 | AP65: =+G65 -> 5250 | AQ65: =+AT64 -> 64340.519 | AR65: =+(AN65*AP65+AO65*(AP65/12))*AM65 -> 787.5 | AS65: =+AQ65*$F$12 -> 2573.6208 | AT65: =+(AQ65+AR65+AS65) -> 67701.64 | AV65: =+AK65 -> 38 | AW65: =+AL65 -> 60 | AX65: 1 | AY65: =+$F$9*AX65 -> 0.135 | AZ65: =+AX65*$F$10 -> 0.18 | BA65: =+G65 -> 5250 | BB65: =+BE64 -> 64340.519 | BC65: =+(AY65*BA65+AZ65*(BA65/12))*AX65 -> 787.5 | BD65: =+BB65*$F$12 -> 2573.6208 | BE65: =+(BB65+BC65+BD65) -> 67701.64
B66: =+B65+1 -> 39 | C66: =+C65+1 -> 60 | D66: =+D65*(1+$F$18) -> 1 | E66: =+IF($C66>=$F$6,0,$F$19*D66) -> 700 | F66: =+IF($C66>=$F$6,0,$F$20) -> 7.5 | G66: =+E66*F66 -> 5250 | I66: =+I65+1 -> 39 | J66: =+C66 -> 60 | K66: =+IF(AL66<=$AF$11,1,0)*F66 -> 7.5 | L66: =+IF(AL66>$AF$11,0,IF(E66>500,500*F66,E66*F66)) -> 3750 | M66: =+IF(AL66>$AF$11,0,IF(G66-L66 <= 0,0,G66-L66)) -> 1500 | N66: =+IF($F$7<7,L66+M66,IF(AL66>$AF$11,0,IF($F$2=1,IF($J66<$F$5,IF(G66<=$F$16*12,G66,$F$16*12),G66),G66))) -> 5250 | O66: =+IFERROR(N66/K66,0) -> 700 | Q66: =+I66 -> 39 | R66: =+J66+1 -> 61 | S66: =+IF(R66<=$AF$11,1,0) -> 1 | T66: =+T65 -> 0.1 | U66: =+M66 -> 1500 | V66: =+Y65 -> 12895.55 | W66: =+T66*U66*S66 -> 150 | X66: =+$U$23*V66 -> 515.82202 | Y66: =+(V66+W66+X66) -> 13561.372 | AA66: =+B66 -> 39 | AB66: =+C66+1 -> 61 | AC66: =+IF(C66<$F$5,1,0) -> 0 | AD66: =+AD65 -> 0.15 | AE66: =+IF($F$2=1,IF(G66<=2500*12,G66,2500*12),G66) -> 5250 | AF66: =+AI65 -> 0 | AG66: =+AD66*AE66*$AC66 -> 0 | AH66: =+AF66*$F$11 -> 0 | AI66: =+(AF66+AG66+AH66) -> 0 | AK66: =+AA66 -> 39 | AL66: =+AB66 -> 61 | AM66: 1 | AN66: =+$F$9*AM66 -> 0.135 | AO66: =+AM66*$F$10 -> 0.18 | AP66: =+G66 -> 5250 | AQ66: =+AT65 -> 67701.64 | AR66: =+(AN66*AP66+AO66*(AP66/12))*AM66 -> 787.5 | AS66: =+AQ66*$F$12 -> 2708.0656 | AT66: =+(AQ66+AR66+AS66) -> 71197.205 | AV66: =+AK66 -> 39 | AW66: =+AL66 -> 61 | AX66: 1 | AY66: =+$F$9*AX66 -> 0.135 | AZ66: =+AX66*$F$10 -> 0.18 | BA66: =+G66 -> 5250 | BB66: =+BE65 -> 67701.64 | BC66: =+(AY66*BA66+AZ66*(BA66/12))*AX66 -> 787.5 | BD66: =+BB66*$F$12 -> 2708.0656 | BE66: =+(BB66+BC66+BD66) -> 71197.205
B67: =+B66+1 -> 40 | C67: =+C66+1 -> 61 | D67: =+D66*(1+$F$18) -> 1 | E67: =+IF($C67>=$F$6,0,$F$19*D67) -> 700 | F67: =+IF($C67>=$F$6,0,$F$20) -> 7.5 | G67: =+E67*F67 -> 5250 | I67: =+I66+1 -> 40 | J67: =+C67 -> 61 | K67: =+IF(AL67<=$AF$11,1,0)*F67 -> 7.5 | L67: =+IF(AL67>$AF$11,0,IF(E67>500,500*F67,E67*F67)) -> 3750 | M67: =+IF(AL67>$AF$11,0,IF(G67-L67 <= 0,0,G67-L67)) -> 1500 | N67: =+IF($F$7<7,L67+M67,IF(AL67>$AF$11,0,IF($F$2=1,IF($J67<$F$5,IF(G67<=$F$16*12,G67,$F$16*12),G67),G67))) -> 5250 | O67: =+IFERROR(N67/K67,0) -> 700 | Q67: =+I67 -> 40 | R67: =+J67+1 -> 62 | S67: 1 | T67: =+T66 -> 0.1 | U67: =+M67 -> 1500 | V67: =+Y66 -> 13561.372 | W67: =+T67*U67*S67 -> 150 | X67: =+$U$23*V67 -> 542.4549 | Y67: =+(V67+W67+X67) -> 14253.827 | AA67: =+B67 -> 40 | AB67: =+C67+1 -> 62 | AC67: =+IF(C67<$F$5,1,0) -> 0 | AD67: =+AD66 -> 0.15 | AE67: =+IF($F$2=1,IF(G67<=2500*12,G67,2500*12),G67) -> 5250 | AF67: =+AI66 -> 0 | AG67: =+AD67*AE67*$AC67 -> 0 | AH67: =+AF67*$F$11 -> 0 | AI67: =+(AF67+AG67+AH67) -> 0 | AK67: =+AA67 -> 40 | AL67: =+AB67 -> 62 | AM67: 1 | AN67: =+$F$9*AM67 -> 0.135 | AO67: =+AM67*$F$10 -> 0.18 | AP67: =+G67 -> 5250 | AQ67: =+AT66 -> 71197.205 | AR67: =+(AN67*AP67+AO67*(AP67/12))*AM67 -> 787.5 | AS67: =+AQ67*$F$12 -> 2847.8882 | AT67: =+(AQ67+AR67+AS67) -> 74832.594 | AV67: =+AK67 -> 40 | AW67: =+AL67 -> 62 | AX67: 1 | AY67: =+$F$9*AX67 -> 0.135 | AZ67: =+AX67*$F$10 -> 0.18 | BA67: =+G67 -> 5250 | BB67: =+BE66 -> 71197.205 | BC67: =+(AY67*BA67+AZ67*(BA67/12))*AX67 -> 787.5 | BD67: =+BB67*$F$12 -> 2847.8882 | BE67: =+(BB67+BC67+BD67) -> 74832.594
B68: =+B67+1 -> 41 | C68: =+C67+1 -> 62 | D68: =+D67*(1+$F$18) -> 1 | E68: =+IF($C68>=$F$6,0,$F$19*D68) -> 0 | F68: =+IF($C68>=$F$6,0,$F$20) -> 0 | G68: =+E68*F68 -> 0 | I68: =+I67+1 -> 41 | J68: =+C68 -> 62 | K68: =+IF(AL68<=$AF$11,1,0)*F68 -> 0 | L68: =+IF(AL68>$AF$11,0,IF(E68>500,500*F68,E68*F68)) -> 0 | M68: =+IF(AL68>$AF$11,0,IF(G68-L68 <= 0,0,G68-L68)) -> 0 | N68: =+IF($F$7<7,L68+M68,IF(AL68>$AF$11,0,IF($F$2=1,IF($J68<$F$5,IF(G68<=$F$16*12,G68,$F$16*12),G68),G68))) -> 0 | O68: =+IFERROR(N68/K68,0) -> 0 | Q68: =+I68 -> 41 | R68: =+J68+1 -> 63 | S68: =+IF(R68<=$AF$11,1,0) -> 0 | T68: =+T67 -> 0.1 | U68: =+M68 -> 0 | V68: =+Y67 -> 14253.827 | W68: =+T68*U68*S68 -> 0 | X68: =+$U$23*V68 -> 570.15309 | Y68: =+(V68+W68+X68) -> 14823.98 | AA68: =+B68 -> 41 | AB68: =+C68+1 -> 63 | AC68: =+IF(C68<$F$5,1,0) -> 0 | AD68: =+AD67 -> 0.15 | AE68: =+IF($F$2=1,IF(G68<=2500*12,G68,2500*12),G68) -> 0 | AF68: =+AI67 -> 0 | AG68: =+AD68*AE68*$AC68 -> 0 | AH68: =+AF68*$F$11 -> 0 | AI68: =+(AF68+AG68+AH68) -> 0 | AK68: =+AA68 -> 41 | AL68: =+AB68 -> 63 | AM68: 0 | AN68: =+$F$9*AM68 -> 0 | AO68: =+AM68*$F$10 -> 0 | AP68: =+G68 -> 0 | AQ68: =+AT67 -> 74832.594 | AR68: =+(AN68*AP68+AO68*(AP68/12))*AM68 -> 0 | AS68: =+AQ68*$F$12 -> 2993.3037 | AT68: =+(AQ68+AR68+AS68) -> 77825.897 | AV68: =+AK68 -> 41 | AW68: =+AL68 -> 63 | AX68: 0 | AY68: =+$F$9*AX68 -> 0 | AZ68: =+AX68*$F$10 -> 0 | BA68: =+G68 -> 0 | BB68: =+BE67 -> 74832.594 | BC68: =+(AY68*BA68+AZ68*(BA68/12))*AX68 -> 0 | BD68: =+BB68*$F$12 -> 2993.3037 | BE68: =+(BB68+BC68+BD68) -> 77825.897
B69: =+B68+1 -> 42 | C69: =+C68+1 -> 63 | D69: =+D68*(1+$F$18) -> 1 | E69: =+IF($C69>=$F$6,0,$F$19*D69) -> 0 | F69: =+IF($C69>=$F$6,0,$F$20) -> 0 | G69: =+E69*F69 -> 0 | I69: =+I68+1 -> 42 | J69: =+C69 -> 63 | K69: =+IF(AL69<=$AF$11,1,0)*F69 -> 0 | L69: =+IF(AL69>$AF$11,0,IF(E69>500,500*F69,E69*F69)) -> 0 | M69: =+IF(AL69>$AF$11,0,IF(G69-L69 <= 0,0,G69-L69)) -> 0 | N69: =+IF($F$7<7,L69+M69,IF(AL69>$AF$11,0,IF($F$2=1,IF($J69<$F$5,IF(G69<=$F$16*12,G69,$F$16*12),G69),G69))) -> 0 | O69: =+IFERROR(N69/K69,0) -> 0 | Q69: =+I69 -> 42 | R69: =+J69+1 -> 64 | S69: =+IF(R69<=$AF$11,1,0) -> 0 | T69: =+T68 -> 0.1 | U69: =+M69 -> 0 | V69: =+Y68 -> 14823.98 | W69: =+T69*U69*S69 -> 0 | X69: =+$U$23*V69 -> 592.95922 | Y69: =+(V69+W69+X69) -> 15416.94 | AA69: =+B69 -> 42 | AB69: =+C69+1 -> 64 | AC69: =+IF(C69<$F$5,1,0) -> 0 | AD69: =+AD68 -> 0.15 | AE69: =+IF($F$2=1,IF(G69<=2500*12,G69,2500*12),G69) -> 0 | AF69: =+AI68 -> 0 | AG69: =+AD69*AE69*$AC69 -> 0 | AH69: =+AF69*$F$11 -> 0 | AI69: =+(AF69+AG69+AH69) -> 0 | AK69: =+AA69 -> 42 | AL69: =+AB69 -> 64 | AM69: 0 | AN69: =+$F$9*AM69 -> 0 | AO69: =+AM69*$F$10 -> 0 | AP69: =+G69 -> 0 | AQ69: =+AT68 -> 77825.897 | AR69: =+(AN69*AP69+AO69*(AP69/12))*AM69 -> 0 | AS69: =+AQ69*$F$12 -> 3113.0359 | AT69: =+(AQ69+AR69+AS69) -> 80938.933 | AV69: =+AK69 -> 42 | AW69: =+AL69 -> 64 | AX69: 0 | AY69: =+$F$9*AX69 -> 0 | AZ69: =+AX69*$F$10 -> 0 | BA69: =+G69 -> 0 | BB69: =+BE68 -> 77825.897 | BC69: =+(AY69*BA69+AZ69*(BA69/12))*AX69 -> 0 | BD69: =+BB69*$F$12 -> 3113.0359 | BE69: =+(BB69+BC69+BD69) -> 80938.933
B70: =+B69+1 -> 43 | C70: =+C69+1 -> 64 | D70: =+D69*(1+$F$18) -> 1 | E70: =+IF($C70>=$F$6,0,$F$19*D70) -> 0 | F70: =+IF($C70>=$F$6,0,$F$20) -> 0 | G70: =+E70*F70 -> 0 | I70: =+I69+1 -> 43 | J70: =+C70 -> 64 | K70: =+IF(AL70<=$AF$11,1,0)*F70 -> 0 | L70: =+IF(AL70>$AF$11,0,IF(E70>500,500*F70,E70*F70)) -> 0 | M70: =+IF(AL70>$AF$11,0,IF(G70-L70 <= 0,0,G70-L70)) -> 0 | N70: =+IF($F$7<7,L70+M70,IF(AL70>$AF$11,0,IF($F$2=1,IF($J70<$F$5,IF(G70<=$F$16*12,G70,$F$16*12),G70),G70))) -> 0 | O70: =+IFERROR(N70/K70,0) -> 0 | Q70: =+I70 -> 43 | R70: =+J70+1 -> 65 | S70: =+IF(R70<=$AF$11,1,0) -> 0 | T70: =+T69 -> 0.1 | U70: =+M70 -> 0 | V70: =+Y69 -> 15416.94 | W70: =+T70*U70*S70 -> 0 | X70: =+$U$23*V70 -> 616.67759 | Y70: =+(V70+W70+X70) -> 16033.617 | AA70: =+B70 -> 43 | AB70: =+C70+1 -> 65 | AC70: =+IF(C70<$F$5,1,0) -> 0 | AD70: =+AD69 -> 0.15 | AE70: =+IF($F$2=1,IF(G70<=2500*12,G70,2500*12),G70) -> 0 | AF70: =+AI69 -> 0 | AG70: =+AD70*AE70*$AC70 -> 0 | AH70: =+AF70*$F$11 -> 0 | AI70: =+(AF70+AG70+AH70) -> 0 | AK70: =+AA70 -> 43 | AL70: =+AB70 -> 65 | AM70: 0 | AN70: =+$F$9*AM70 -> 0 | AO70: =+AM70*$F$10 -> 0 | AP70: =+G70 -> 0 | AQ70: =+AT69 -> 80938.933 | AR70: =+(AN70*AP70+AO70*(AP70/12))*AM70 -> 0 | AS70: =+AQ70*$F$12 -> 3237.5573 | AT70: =+(AQ70+AR70+AS70) -> 84176.491 | AV70: =+AK70 -> 43 | AW70: =+AL70 -> 65 | AX70: 0 | AY70: =+$F$9*AX70 -> 0 | AZ70: =+AX70*$F$10 -> 0 | BA70: =+G70 -> 0 | BB70: =+BE69 -> 80938.933 | BC70: =+(AY70*BA70+AZ70*(BA70/12))*AX70 -> 0 | BD70: =+BB70*$F$12 -> 3237.5573 | BE70: =+(BB70+BC70+BD70) -> 84176.491
B71: =+B70+1 -> 44 | C71: =+C70+1 -> 65 | D71: =+D70*(1+$F$18) -> 1 | E71: =+IF($C71>=$F$6,0,$F$19*D71) -> 0 | F71: =+IF($C71>=$F$6,0,$F$20) -> 0 | G71: =+E71*F71 -> 0 | I71: =+I70+1 -> 44 | J71: =+C71 -> 65 | K71: =+IF(AL71<=$AF$11,1,0)*F71 -> 0 | L71: =+IF(AL71>$AF$11,0,IF(E71>500,500*F71,E71*F71)) -> 0 | M71: =+IF(AL71>$AF$11,0,IF(G71-L71 <= 0,0,G71-L71)) -> 0 | N71: =+IF($F$7<7,L71+M71,IF(AL71>$AF$11,0,IF($F$2=1,IF($J71<$F$5,IF(G71<=$F$16*12,G71,$F$16*12),G71),G71))) -> 0 | O71: =+IFERROR(N71/K71,0) -> 0 | Q71: =+I71 -> 44 | R71: =+J71+1 -> 66 | S71: =+IF(R71<=$AF$11,1,0) -> 0 | T71: =+T70 -> 0.1 | U71: =+M71 -> 0 | V71: =+Y70 -> 16033.617 | W71: =+T71*U71*S71 -> 0 | X71: =+$U$23*V71 -> 641.34469 | Y71: =+(V71+W71+X71) -> 16674.962 | AA71: =+B71 -> 44 | AB71: =+C71+1 -> 66 | AC71: =+IF(C71<$F$5,1,0) -> 0 | AD71: =+AD70 -> 0.15 | AE71: =+IF($F$2=1,IF(G71<=2500*12,G71,2500*12),G71) -> 0 | AF71: =+AI70 -> 0 | AG71: =+AD71*AE71*$AC71 -> 0 | AH71: =+AF71*$F$11 -> 0 | AI71: =+(AF71+AG71+AH71) -> 0 | AK71: =+AA71 -> 44 | AL71: =+AB71 -> 66 | AM71: 0 | AN71: =+$F$9*AM71 -> 0 | AO71: =+AM71*$F$10 -> 0 | AP71: =+G71 -> 0 | AQ71: =+AT70 -> 84176.491 | AR71: =+(AN71*AP71+AO71*(AP71/12))*AM71 -> 0 | AS71: =+AQ71*$F$12 -> 3367.0596 | AT71: =+(AQ71+AR71+AS71) -> 87543.55 | AV71: =+AK71 -> 44 | AW71: =+AL71 -> 66 | AX71: 0 | AY71: =+$F$9*AX71 -> 0 | AZ71: =+AX71*$F$10 -> 0 | BA71: =+G71 -> 0 | BB71: =+BE70 -> 84176.491 | BC71: =+(AY71*BA71+AZ71*(BA71/12))*AX71 -> 0 | BD71: =+BB71*$F$12 -> 3367.0596 | BE71: =+(BB71+BC71+BD71) -> 87543.55
B72: =+B71+1 -> 45 | C72: =+C71+1 -> 66 | D72: =+D71*(1+$F$18) -> 1 | E72: =+IF($C72>=$F$6,0,$F$19*D72) -> 0 | F72: =+IF($C72>=$F$6,0,$F$20) -> 0 | G72: =+E72*F72 -> 0 | I72: =+I71+1 -> 45 | J72: =+C72 -> 66 | K72: =+IF(AL72<=$AF$11,1,0)*F72 -> 0 | L72: =+IF(AL72>$AF$11,0,IF(E72>500,500*F72,E72*F72)) -> 0 | M72: =+IF(AL72>$AF$11,0,IF(G72-L72 <= 0,0,G72-L72)) -> 0 | N72: =+IF($F$7<7,L72+M72,IF(AL72>$AF$11,0,IF($F$2=1,IF($J72<$F$5,IF(G72<=$F$16*12,G72,$F$16*12),G72),G72))) -> 0 | O72: =+IFERROR(N72/K72,0) -> 0 | Q72: =+I72 -> 45 | R72: =+J72+1 -> 67 | S72: =+IF(R72<=$AF$11,1,0) -> 0 | T72: =+T71 -> 0.1 | U72: =+M72 -> 0 | V72: =+Y71 -> 16674.962 | W72: =+T72*U72*S72 -> 0 | X72: =+$U$23*V72 -> 666.99848 | Y72: =+(V72+W72+X72) -> 17341.96 | AA72: =+B72 -> 45 | AB72: =+C72+1 -> 67 | AC72: =+IF(C72<$F$5,1,0) -> 0 | AD72: =+AD71 -> 0.15 | AE72: =+IF($F$2=1,IF(G72<=2500*12,G72,2500*12),G72) -> 0 | AF72: =+AI71 -> 0 | AG72: =+AD72*AE72*$AC72 -> 0 | AH72: =+AF72*$F$11 -> 0 | AI72: =+(AF72+AG72+AH72) -> 0 | AK72: =+AA72 -> 45 | AL72: =+AB72 -> 67 | AM72: 0 | AN72: =+$F$9*AM72 -> 0 | AO72: =+AM72*$F$10 -> 0 | AP72: =+G72 -> 0 | AQ72: =+AT71 -> 87543.55 | AR72: =+(AN72*AP72+AO72*(AP72/12))*AM72 -> 0 | AS72: =+AQ72*$F$12 -> 3501.742 | AT72: =+(AQ72+AR72+AS72) -> 91045.292 | AV72: =+AK72 -> 45 | AW72: =+AL72 -> 67 | AX72: 0 | AY72: =+$F$9*AX72 -> 0 | AZ72: =+AX72*$F$10 -> 0 | BA72: =+G72 -> 0 | BB72: =+BE71 -> 87543.55 | BC72: =+(AY72*BA72+AZ72*(BA72/12))*AX72 -> 0 | BD72: =+BB72*$F$12 -> 3501.742 | BE72: =+(BB72+BC72+BD72) -> 91045.292
B73: =+B72+1 -> 46 | C73: =+C72+1 -> 67 | D73: =+D72*(1+$F$18) -> 1 | E73: =+IF($C73>=$F$6,0,$F$19*D73) -> 0 | F73: =+IF($C73>=$F$6,0,$F$20) -> 0 | G73: =+E73*F73 -> 0 | I73: =+I72+1 -> 46 | J73: =+C73 -> 67 | K73: =+IF(AL73<=$AF$11,1,0)*F73 -> 0 | L73: =+IF(AL73>$AF$11,0,IF(E73>500,500*F73,E73*F73)) -> 0 | M73: =+IF(AL73>$AF$11,0,IF(G73-L73 <= 0,0,G73-L73)) -> 0 | N73: =+IF($F$7<7,L73+M73,IF(AL73>$AF$11,0,IF($F$2=1,IF($J73<$F$5,IF(G73<=$F$16*12,G73,$F$16*12),G73),G73))) -> 0 | O73: =+IFERROR(N73/K73,0) -> 0 | Q73: =+I73 -> 46 | R73: =+J73+1 -> 68 | S73: =+IF(R73<=$AF$11,1,0) -> 0 | T73: =+T72 -> 0.1 | U73: =+M73 -> 0 | V73: =+Y72 -> 17341.96 | W73: =+T73*U73*S73 -> 0 | X73: =+$U$23*V73 -> 693.67842 | Y73: =+(V73+W73+X73) -> 18035.639 | AA73: =+B73 -> 46 | AB73: =+C73+1 -> 68 | AC73: =+IF(C73<$F$5,1,0) -> 0 | AD73: =+AD72 -> 0.15 | AE73: =+IF($F$2=1,IF(G73<=2500*12,G73,2500*12),G73) -> 0 | AF73: =+AI72 -> 0 | AG73: =+AD73*AE73*$AC73 -> 0 | AH73: =+AF73*$F$11 -> 0 | AI73: =+(AF73+AG73+AH73) -> 0 | AK73: =+AA73 -> 46 | AL73: =+AB73 -> 68 | AM73: 0 | AN73: =+$F$9*AM73 -> 0 | AO73: =+AM73*$F$10 -> 0 | AP73: =+G73 -> 0 | AQ73: =+AT72 -> 91045.292 | AR73: =+(AN73*AP73+AO73*(AP73/12))*AM73 -> 0 | AS73: =+AQ73*$F$12 -> 3641.8117 | AT73: =+(AQ73+AR73+AS73) -> 94687.104 | AV73: =+AK73 -> 46 | AW73: =+AL73 -> 68 | AX73: 0 | AY73: =+$F$9*AX73 -> 0 | AZ73: =+AX73*$F$10 -> 0 | BA73: =+G73 -> 0 | BB73: =+BE72 -> 91045.292 | BC73: =+(AY73*BA73+AZ73*(BA73/12))*AX73 -> 0 | BD73: =+BB73*$F$12 -> 3641.8117 | BE73: =+(BB73+BC73+BD73) -> 94687.104
B74: =+B73+1 -> 47 | C74: =+C73+1 -> 68 | D74: =+D73*(1+$F$18) -> 1 | E74: =+IF($C74>=$F$6,0,$F$19*D74) -> 0 | F74: =+IF($C74>=$F$6,0,$F$20) -> 0 | G74: =+E74*F74 -> 0 | I74: =+I73+1 -> 47 | J74: =+C74 -> 68 | K74: =+IF(AL74<=$AF$11,1,0)*F74 -> 0 | L74: =+IF(AL74>$AF$11,0,IF(E74>500,500*F74,E74*F74)) -> 0 | M74: =+IF(AL74>$AF$11,0,IF(G74-L74 <= 0,0,G74-L74)) -> 0 | N74: =+IF($F$7<7,L74+M74,IF(AL74>$AF$11,0,IF($F$2=1,IF($J74<$F$5,IF(G74<=$F$16*12,G74,$F$16*12),G74),G74))) -> 0 | O74: =+IFERROR(N74/K74,0) -> 0 | Q74: =+I74 -> 47 | R74: =+J74+1 -> 69 | S74: =+IF(R74<=$AF$11,1,0) -> 0 | T74: =+T73 -> 0.1 | U74: =+M74 -> 0 | V74: =+Y73 -> 18035.639 | W74: =+T74*U74*S74 -> 0 | X74: =+$U$23*V74 -> 721.42555 | Y74: =+(V74+W74+X74) -> 18757.064 | AA74: =+B74 -> 47 | AB74: =+C74+1 -> 69 | AC74: =+IF(C74<$F$5,1,0) -> 0 | AD74: =+AD73 -> 0.15 | AE74: =+IF($F$2=1,IF(G74<=2500*12,G74,2500*12),G74) -> 0 | AF74: =+AI73 -> 0 | AG74: =+AD74*AE74*$AC74 -> 0 | AH74: =+AF74*$F$11 -> 0 | AI74: =+(AF74+AG74+AH74) -> 0 | AK74: =+AA74 -> 47 | AL74: =+AB74 -> 69 | AM74: 0 | AN74: =+$F$9*AM74 -> 0 | AO74: =+AM74*$F$10 -> 0 | AP74: =+G74 -> 0 | AQ74: =+AT73 -> 94687.104 | AR74: =+(AN74*AP74+AO74*(AP74/12))*AM74 -> 0 | AS74: =+AQ74*$F$12 -> 3787.4842 | AT74: =+(AQ74+AR74+AS74) -> 98474.588 | AV74: =+AK74 -> 47 | AW74: =+AL74 -> 69 | AX74: 0 | AY74: =+$F$9*AX74 -> 0 | AZ74: =+AX74*$F$10 -> 0 | BA74: =+G74 -> 0 | BB74: =+BE73 -> 94687.104 | BC74: =+(AY74*BA74+AZ74*(BA74/12))*AX74 -> 0 | BD74: =+BB74*$F$12 -> 3787.4842 | BE74: =+(BB74+BC74+BD74) -> 98474.588
B75: =+B74+1 -> 48 | C75: =+C74+1 -> 69 | D75: =+D74*(1+$F$18) -> 1 | E75: =+IF($C75>=$F$6,0,$F$19*D75) -> 0 | F75: =+IF($C75>=$F$6,0,$F$20) -> 0 | G75: =+E75*F75 -> 0 | I75: =+I74+1 -> 48 | J75: =+C75 -> 69 | K75: =+IF(AL75<=$AF$11,1,0)*F75 -> 0 | L75: =+IF(AL75>$AF$11,0,IF(E75>500,500*F75,E75*F75)) -> 0 | M75: =+IF(AL75>$AF$11,0,IF(G75-L75 <= 0,0,G75-L75)) -> 0 | N75: =+IF($F$7<7,L75+M75,IF(AL75>$AF$11,0,IF($F$2=1,IF($J75<$F$5,IF(G75<=$F$16*12,G75,$F$16*12),G75),G75))) -> 0 | O75: =+IFERROR(N75/K75,0) -> 0 | Q75: =+I75 -> 48 | R75: =+J75+1 -> 70 | S75: =+IF(R75<=$AF$11,1,0) -> 0 | T75: =+T74 -> 0.1 | U75: =+M75 -> 0 | V75: =+Y74 -> 18757.064 | W75: =+T75*U75*S75 -> 0 | X75: =+$U$23*V75 -> 750.28258 | Y75: =+(V75+W75+X75) -> 19507.347 | AA75: =+B75 -> 48 | AB75: =+C75+1 -> 70 | AC75: =+IF(C75<$F$5,1,0) -> 0 | AD75: =+AD74 -> 0.15 | AE75: =+IF($F$2=1,IF(G75<=2500*12,G75,2500*12),G75) -> 0 | AF75: =+AI74 -> 0 | AG75: =+AD75*AE75*$AC75 -> 0 | AH75: =+AF75*$F$11 -> 0 | AI75: =+(AF75+AG75+AH75) -> 0 | AK75: =+AA75 -> 48 | AL75: =+AB75 -> 70 | AM75: 0 | AN75: =+$F$9*AM75 -> 0 | AO75: =+AM75*$F$10 -> 0 | AP75: =+G75 -> 0 | AQ75: =+AT74 -> 98474.588 | AR75: =+(AN75*AP75+AO75*(AP75/12))*AM75 -> 0 | AS75: =+AQ75*$F$12 -> 3938.9835 | AT75: =+(AQ75+AR75+AS75) -> 102413.57 | AV75: =+AK75 -> 48 | AW75: =+AL75 -> 70 | AX75: 0 | AY75: =+$F$9*AX75 -> 0 | AZ75: =+AX75*$F$10 -> 0 | BA75: =+G75 -> 0 | BB75: =+BE74 -> 98474.588 | BC75: =+(AY75*BA75+AZ75*(BA75/12))*AX75 -> 0 | BD75: =+BB75*$F$12 -> 3938.9835 | BE75: =+(BB75+BC75+BD75) -> 102413.57
B76: =+B75+1 -> 49 | C76: =+C75+1 -> 70 | D76: =+D75*(1+$F$18) -> 1 | E76: =+IF($C76>=$F$6,0,$F$19*D76) -> 0 | F76: =+IF($C76>=$F$6,0,$F$20) -> 0 | G76: =+E76*F76 -> 0 | I76: =+I75+1 -> 49 | J76: =+C76 -> 70 | K76: =+IF(AL76<=$AF$11,1,0)*F76 -> 0 | L76: =+IF(AL76>$AF$11,0,IF(E76>500,500*F76,E76*F76)) -> 0 | M76: =+IF(AL76>$AF$11,0,IF(G76-L76 <= 0,0,G76-L76)) -> 0 | N76: =+IF($F$7<7,L76+M76,IF(AL76>$AF$11,0,IF($F$2=1,IF($J76<$F$5,IF(G76<=$F$16*12,G76,$F$16*12),G76),G76))) -> 0 | O76: =+IFERROR(N76/K76,0) -> 0 | Q76: =+I76 -> 49 | R76: =+J76+1 -> 71 | S76: =+IF(R76<=$AF$11,1,0) -> 0 | T76: =+T75 -> 0.1 | U76: =+M76 -> 0 | V76: =+Y75 -> 19507.347 | W76: =+T76*U76*S76 -> 0 | X76: =+$U$23*V76 -> 780.29388 | Y76: =+(V76+W76+X76) -> 20287.641 | AA76: =+B76 -> 49 | AB76: =+C76+1 -> 71 | AC76: =+IF(C76<$F$5,1,0) -> 0 | AD76: =+AD75 -> 0.15 | AE76: =+IF($F$2=1,IF(G76<=2500*12,G76,2500*12),G76) -> 0 | AF76: =+AI75 -> 0 | AG76: =+AD76*AE76*$AC76 -> 0 | AH76: =+AF76*$F$11 -> 0 | AI76: =+(AF76+AG76+AH76) -> 0 | AK76: =+AA76 -> 49 | AL76: =+AB76 -> 71 | AM76: 0 | AN76: =+$F$9*AM76 -> 0 | AO76: =+AM76*$F$10 -> 0 | AP76: =+G76 -> 0 | AQ76: =+AT75 -> 102413.57 | AR76: =+(AN76*AP76+AO76*(AP76/12))*AM76 -> 0 | AS76: =+AQ76*$F$12 -> 4096.5429 | AT76: =+(AQ76+AR76+AS76) -> 106510.11 | AV76: =+AK76 -> 49 | AW76: =+AL76 -> 71 | AX76: 0 | AY76: =+$F$9*AX76 -> 0 | AZ76: =+AX76*$F$10 -> 0 | BA76: =+G76 -> 0 | BB76: =+BE75 -> 102413.57 | BC76: =+(AY76*BA76+AZ76*(BA76/12))*AX76 -> 0 | BD76: =+BB76*$F$12 -> 4096.5429 | BE76: =+(BB76+BC76+BD76) -> 106510.11
B93: =+B92/12 -> 0
B95: =+B93-BM8 -> -5250

Sheet calculo 30
B1: DATOS BASICOS | BH1: BENEFICIO DE JUBILACION CSS SEBD
B2: SISTEMA | F2: 1 | BH2: CUOTAS APORTADAS | BM2: =+SUM(K28:K76) -> 360
B3: SEXO | F3: =+salidaformulas!B2 -> M | Q3: MIXTO | AA3: CAPITALIZACIÓN SOLIDARIA | BH3: CUOTAS EN EXCESO A DENSIDAD MIN | BM3: =+IF(BM2>240,BM2-F13,0) -> 120
B4: EDAD ENTRADA | F4: =+salidaformulas!B3 -> 22 | I4: SOLIDARIO | BH4: TASA DE REEMPLAZO AJUSTADA SEBD LEY 51 | BM4: =IF(F7<=7,BN4,BN4*AF13) -> 0.725 | BN4: =IF(AND(BM2>=180,BM2<240),($F$14+INT(BM3/12)*$F$15)*BM2/240,IF(BM2<180,0,($F$14+INT(BM3/12)*$F$15))) -> 0.725
B5: EDAD ACTUAL DIA DE REFORMA | F5: =+F4 -> 22 | J5: Mej. Salario Anual | K5: Mej Salario Anual | S5: Mej. Salario Anual | T5: Mej Salario Anual | BH5: PENSION ANNUAL A RECIBIR | BM5: =+BM6*12 -> 4567.5
B6: EDAD DE JUBILACION | F6: =+salidaformulas!B4 -> 62 | I6: Mejores Años | J6: TOTAL | K6: Primer Pilar | R6: Mejores Años | S6: TOTAL | T6: Primer Pilar | BH6: PENSION MENSUAL A RECIBIR | BM6: =IF(BM2>=240,MAX(MAX(BL8:BL10),265),MAX(BL8:BL10)) -> 380.625
B7: AÑOS PARA JUBILARSE | F7: =+F6-F5 -> 40 | I7: 1 | J7: =LARGE($G$28:$G$65,I7) -> 6300 | K7: =LARGE($L$28:$L$65,I7) -> 4500 | R7: 1 | S7: =+J7 -> 6300 | T7: =+K7 -> 4500 | BL7: PENSION | BM7: PROM. ANUAL | BN7: PROM.MENSUAL
B8: % CUOTA APLICADO ANTES VIGENCIA NVA LEY | F8: 0.15 | I8: 2 | J8: =LARGE($G$28:$G$65,I8) -> 6300 | K8: =LARGE($L$28:$L$65,I8) -> 4500 | R8: 2 | S8: =+J8 -> 6300 | T8: =+K8 -> 4500 | BH8: CALCULO DE LOS MEJORES 10 AÑOS | BL8: =+IF($BM$4*BM8/12>1500,1500,$BM$4*BM8/12) -> 380.625 | BM8: {=+AVERAGE(LARGE($G$28:$G$76,ROW(INDIRECT("1:10"))))} -> 6300
B9: % CUOTA EMPLEADO EMPLEADOR NUEVA LEY | F9: 0.135 | I9: 3 | J9: =LARGE($G$28:$G$65,I9) -> 6300 | K9: =LARGE($L$28:$L$65,I9) -> 4500 | R9: 3 | S9: =+J9 -> 6300 | T9: =+K9 -> 4500 | BH9: CALCULO DE LOS MEJORES 15 AÑOS (300 CUOTAS Y PROM>=$2,000) | BL9: =+IF($BM$4*BM9/12>2000,2000,$BM$4*BM9/12) -> 0 | BM9: {=IF(AND(BM2>300,AVERAGE(LARGE($G$28:$G$76,ROW(INDIRECT("1:15"))))>=24000),AVERAGE(LARGE($G$28:$G$76,ROW(INDIRECT("1:15")))),0)} -> 0
B10: % XIII EMPLEADO EMPLEADOR NUEVA LEY | F10: 0.18 | I10: 4 | J10: =LARGE($G$28:$G$65,I10) -> 6300 | K10: =LARGE($L$28:$L$65,I10) -> 4500 | R10: 4 | S10: =+J10 -> 6300 | T10: =+K10 -> 4500 | AA10: SCGS-CUANDO VIENE DEL SEBD o SM | BH10: CALCULO DE LOS MEJORES 20 AÑOS (360 cuotas y prom>=$2,500) | BL10: =+IF($BM$4*BM10/12>2500,2500,$BM$4*BM10/12) -> 0 | BM10: {=IF(AND(BM2>360,AVERAGE(LARGE($G$28:$G$76,ROW(INDIRECT("1:20"))))>=30000),AVERAGE(LARGE($G$28:$G$76,ROW(INDIRECT("1:20")))),0)} -> 0
B11: TASA DE RETORNO INVERSIONES ANTES VIG LEY | F11: 0.04 | I11: 5 | J11: =LARGE($G$28:$G$65,I11) -> 6300 | K11: =LARGE($L$28:$L$65,I11) -> 4500 | R11: 5 | S11: =+J11 -> 6300 | T11: =+K11 -> 4500 | AA11: EDAD JUBILACION | AF11: =+F6 -> 62 | AK11: RESULTADO COMPARATIVO | AO11: MONTO | AP11: REEMPLAZO MEJ.AÑOS | BH11: TASA DE REEMPLAZO FINAL DE ESTE CALCULO | BM11: =+BM5/VLOOKUP(MAX(BL8:BL10),BL8:BM10,2,0) -> 0.725
B12: TASA RETORNO INVERSIONES PROMEDIO | F12: 0.04 | I12: 6 | J12: =LARGE($G$28:$G$65,I12) -> 6300 | K12: =LARGE($L$28:$L$65,I12) -> 4500 | R12: 6 | S12: =+J12 -> 6300 | T12: =+K12 -> 4500 | AA12: FONDO AHORRADO COP ANTES VIGENCIA NVA LEY | AF12: =+VLOOKUP(AF11,$AB$28:$AI$76,8,FALSE) -> 0 | AG12: R | AK12: PENSION A RECIBIR DEL SEBD | AO12: =+L18 -> 380.625 | AP12: =+AO12/(J16/12) -> 0.725
A13: A | B13: DENSIDAD MINIMA DE CUOTAS LEY 51 | F13: 240 | I13: 7 | J13: =LARGE($G$28:$G$65,I13) -> 6300 | K13: =LARGE($L$28:$L$65,I13) -> 4500 | R13: 7 | S13: =+J13 -> 6300 | T13: =+K13 -> 4500 | W13: VP | X13: RA*ax | AA13: FACTOR DESCUENTO | AF13: =+IF(AND($B$20=1,$F$2<>1),100%,IF($F$3="M",VLOOKUP(AF11,descuento!$A$6:$B$32,2,FALSE),VLOOKUP(AF11,descuento!$C$6:$D$32,2,FALSE))) -> 1 | AK13: PENSION A RECIBIR SISTEMA MIXTO | AO13: =+U22 -> 360.03774 | AP13: =+AO13/(S17/12) -> 0.68578616 | AV13: FONDO TOTAL APLICABLE | BB13: =+VLOOKUP(AF11,$AW$28:$BE$76,9,FALSE) -> 89799.112 | BH13: BENEFICIO DEL SISTEMA MIXTO
A14: B | B14: TASA DE REEMPLAZO INICIAL LEY 51 | F14: 0.6 | I14: 8 | J14: =LARGE($G$28:$G$65,I14) -> 6300 | K14: =LARGE($L$28:$L$65,I14) -> 4500 | R14: 8 | S14: =+J14 -> 6300 | T14: =+K14 -> 4500 | W14: VP/ax | X14: 12*RM | AA14: FONDO AHORRADO COP DESPUES VIGENCIA NVA LEY | AF14: =+VLOOKUP(AF11,$AL$28:$AT$76,9,FALSE) -> 89799.112 | AG14: S | AK14: PENSION A RECIBIR DEL SCGS | AO14: =+AF17 -> 462.85437 | AP14: =+AO14/(S16/12) -> 0.88162736 | AV14: FACTOR PENSION X MIL | BB14: =+AF16 -> 5.1543312
A15: C | B15: TASA DE REEMPLAZO ADICIONAL LEY 51 | F15: 0.0125 | I15: 9 | J15: =LARGE($G$28:$G$65,I15) -> 6300 | K15: =LARGE($L$28:$L$65,I15) -> 4500 | R15: 9 | S15: =+J15 -> 6300 | T15: =+K15 -> 4500 | W15: vp * (1/ax) | AA15: FONDO TOTAL APLICABLE | AF15: =+AF14+AF12*AF13 -> 89799.112 | AG15: T=R+S | AK15: PENSION A RECIBIR SI ENTRA NUEVO | AO15: =+BB15 -> 462.85437 | AP15: =+AO15/(S17/12) -> 0.88162736 | AV15: PENSION SCGS MENSUAL | BB15: =+BB13*0.001*BB14 -> 462.85437 | BH15: PROMEDIO ANUAL MEJORES 10 AÑOS PRIMER PILAR | BM15: {=+AVERAGE(LARGE($L$28:$L$76,ROW(INDIRECT("1:10"))))} -> 4500
B16: SALMAX MENSUAL COTIZADO ANTES VIG NVA LEY | F16: 2500 | I16: 10 | J16: =LARGE($G$28:$G$65,I16) -> 6300 | K16: =LARGE($L$28:$L$65,I16) -> 4500 | R16: 10 | S16: =+J16 -> 6300 | T16: =+K16 -> 4500 | AA16: FACTOR PENSION X MIL | AF16: =+VLOOKUP(AF11,'bases renta'!$K$20:$L$65,2,FALSE) -> 5.1543312 | AG16: U | AV16: REEMPLAZO MEJ.AÑOS | BB16: =+BB15/(J17/12) -> 0.88162736 | BH16: PENSION MENSUAL A RECIBIR PRIMER PILAR | BM16: =+BM15*BM4/12 -> 271.875
B17: PORCENTAJE DE CUOTA OP DESCONTADA SMP | F17: 0.035 | H17: F | I17: PROMEDIO ANUAL | J17: =+AVERAGE(J7:J16) -> 6300 | K17: =+AVERAGE(K7:K16) -> 4500 | Q17: F | R17: PROMEDIO ANUAL | S17: =+J17 -> 6300 | T17: =+K17 -> 4500 | U17: J | AA17: PENSION SCGS MENSUAL | AF17: =+AF15*0.001*AF16 -> 462.85437 | AG17: V=(T/1000)*U | BH17: AHORRO PENSIONAL EDAD JUBILACION | BM17: =+VLOOKUP(AF11,$R$28:$Y$76,8,FALSE) -> 17104.593
B18: CRECIMIENTO SALARIAL CADA DOS AÑOS | F18: 0 | I18: CUOTAS | J18: =+BM2 -> 360 | K18: PENSION MENSUAL SEBD | L18: =+MIN(J17*J20/12,F16) -> 380.625 | M18: G=(F*E)/12 | R18: CUOTAS | S18: =+J18 -> 360 | T18: PENSION MENSUAL 1er pilarBD | U18: =+(K17*S20)/12 -> 271.875 | V18: K=(E*J)/12 | W18: REEMPLAZO MEJ.AÑOS | X18: =+U22/(J17/12) -> 0.68578616 | Y18: P=O/(E/12) | AA18: REEMPLAZO MEJ.AÑOS | AF18: =+AF17/(J17/12) -> 0.88162736 | AG18: W=V/(E/12) | BH18: FACTOR DE PENSIONAMIENTO XMIL | BM18: =+AF16 -> 5.1543312
B19: SALARIO INICIAL | F19: =+salidaformulas!A10 -> 700 | H19: D | I19: EXCESO DENSIDAD | J19: =+BM3 -> 120 | K19: SALARIO PROMEDIO TOTAL MENSUAL COTIZADO | L19: =+F23 -> 525 | M19: H | R19: EXCESO DENSIDAD | S19: =+J19 -> 120 | T19: AHORRO PERSONAL | U19: =+BM17 -> 17104.593 | V19: L | W19: SALARIO PROMEDIO TOTAL MENSUAL COTIZADO | X19: =+L19 -> 525 | Y19: =+M19 -> H | AA19: SALARIO PROMEDIO TOTAL MENSUAL COTIZADO | AF19: =+X19 -> 525 | AG19: H | BH19: PENSION MENSUAL 2do PILAR | BM19: =+(BM17/1000)*BM18 -> 88.162736
B20: cuotas pagadas por año | F20: 9 | H20: E=B+C*D | I20: REEMPLAZO MEJ.AÑOS | J20: =+BM4 -> 0.725 | K20: TASA BRUTA REEMPLAZO | L20: =+L18/L19 -> 0.725 | M20: I=G/H | Q20: E | R20: REEMPLAZO MEJ.AÑOS | S20: =+J20 -> 0.725 | T20: FACTOR PENSIONAMIENTO VITALICIO | U20: =+BM18 -> 5.1543312 | V20: M | W20: TASA BRUTA REEMPLAZO | X20: =+U22/L19 -> 0.68578616 | Y20: Q=O/H | AA20: TASA BRUTA REEMPLAZO | AF20: =+AF17/L19 -> 0.88162736 | AG20: X=V/H | BH20: PENSION FINAL SISTEMA MIXTO | BM20: =IF(BM2>=240,MAX(BM16+BM19,265),BM16+BM19) -> 360.03774
C21: TOTAL CUOTAS MENSUALES | F21: =+SUMIF(F28:F76,">0") -> 360 | G21: =+F21/12 -> 30 | T21: PENSION MENSUAL 2do PILAR | U21: =+U19*0.001*U20 -> 88.162736 | V21: N=(L/1000)*M | BH21: TASA DE REEMPLAZO FINAL DE ESTE CALCULO | BM21: =+BM20*12/VLOOKUP(MAX($BL$8:$BL$10),$BL$8:$BN$10,2,0) -> 0.68578616
C22: SALARIO PROMEDIO ANNUAL | F22: =+AVERAGEIF(G28:G76,">0") -> 6300 | T22: PENSION TOTAL A RECIBIR | U22: =+U21+U18 -> 360.03774 | V22: O=N+K
C23: PROMEDIO MENSUALIZADO | F23: =+F22/12 -> 525 | T23: tasa capitalizacion mixto | U23: 0.04
B24: Tabla 1 | I24: Tabla 2 | Q24: Tabla 3 | AA24: Tabla 4 | AK24: Tabla 5 | AV24: Tabla 6
B25: Datos Básicos | I25: SALARIOS PARA CALCULO PROMEDIO MEJORES | Q25: SISTEMA DE ACUMULACION DEL SISTEMA MIXTO | AA25: ACUMULACION SCGS ANTES DE LA ENTRADA EN VIGENCIA | AK25: ACUMULACION SCGS DESPUES DE LA ENTRADA EN VIGENCIA | AV25: ACUMULACION DESDE EL INICIO DENTRO DEL SISTEMA DE CAPITALIZACION CON GARANTIA SOLIDARIA
B26: AÑO | C26: EDAD INI AÑO | D26: CREC. SALARIO | E26: SALARIO MENSUAL | F26: CUOTAS APORTADAS | G26: SALARIO ANUAL | I26: AÑO | J26: EDAD | K26: CUOTAS APORTADAS | L26: SALARIO COTIZADO 1er PILAR SISTEMA MIXTO ANUAL | M26: SALARIO COTIZADO SEGUNDO PILAR ANUAL | N26: SALARIO COTIZADO PARA PROMEDIO ANUAL | O26: SALARIO COTIZADO PARA PROMEDIO MENSUAL | Q26: AÑO | R26: EDAD FIN AÑO | S26: INDICADOR | T26: TASA O-P SALARIO | U26: SALARIO SEGUNDO PILAR | V26: AHORRO PENSIONAL INICIAL | W26: APORTES | X26: INTERESES | Y26: AHORRO PENSIONAL FINAL | AA26: AÑO | AB26: EDAD FIN AÑO | AC26: INDICADOR | AD26: TASA O-P SALARIO | AE26: SALARIO ANUAL CON MAX 2500 MENSUAL | AF26: AHORRO PENSIONAL INICIAL | AG26: APORTES | AH26: INTERESES | AI26: AHORRO PENSIONAL FINAL | AK26: AÑO | AL26: EDAD FIN AÑO | AM26: INDICADOR | AN26: TASA O-P SALARIO | AO26: TASA O-P XIII | AP26: SALARIO ANUAL SIN MAXIMO | AQ26: AHORRO PENSIONAL INICIAL | AR26: APORTES | AS26: INTERESES | AT26: AHORRO PENSIONAL INICIAL | AV26: AÑO | AW26: EDAD FIN AÑO | AX26: INDICADOR | AY26: TASA O-P SALARIO | AZ26: TASA O-P XIII | BA26: SALARIO ANUAL SIN MAXIMO | BB26: AHORRO PENSIONAL INICIAL | BC26: APORTES | BD26: INTERESES | BE26: AHORRO PENSIONAL INICIAL
B28: 1 | C28: =+F4 -> 22 | D28: 1 | E28: =+IF($C28>=$F$6,0,$F$19*D28) -> 700 | F28: =+IF($C28>=$F$6,0,$F$20) -> 9 | G28: =+E28*F28 -> 6300 | I28: =+B28 -> 1 | J28: =+C28 -> 22 | K28: =+IF(AL28<=$AF$11,1,0)*F28 -> 9 | L28: =+IF(AL28>$AF$11,0,IF(E28>500,500*F28,E28*F28)) -> 4500 | M28: =+IF(AL28>$AF$11,0,IF(G28-L28 <= 0,0,G28-L28)) -> 1800 | N28: =+IF($F$7<7,L28+M28,IF(AL28>$AF$11,0,IF($F$2=1,IF($J28<$F$5,IF(G28<=$F$16*12,G28,$F$16*12),G28),G28))) -> 6300 | O28: =+IFERROR(N28/K28,0) -> 700 | Q28: =+I28 -> 1 | R28: =+J28+1 -> 23 | S28: =+IF(R28<=$AF$11,1,0) -> 1 | T28: =+$F$9-$F$17 -> 0.1 | U28: =+M28 -> 1800 | V28: =+Y27 -> 0 | W28: =+T28*U28*S28 -> 180 | X28: =+$U$23*V28 -> 0 | Y28: =+(V28+W28+X28) -> 180 | AA28: =+B28 -> 1 | AB28: =+C28+1 -> 23 | AC28: =+IF(C28<$F$5,1,0) -> 0 | AD28: =F8 -> 0.15 | AE28: =+IF($F$2=1,IF(G28<=2500*12,G28,2500*12),G28) -> 6300 | AF28: =+AI27 -> 0 | AG28: =+AD28*AE28*$AC28 -> 0 | AH28: =+AF28*$F$11 -> 0 | AI28: =+(AF28+AG28+AH28) -> 0 | AK28: =+AA28 -> 1 | AL28: =+AB28 -> 23 | AM28: =+IF($C28>=$F$5,1,0) -> 1 | AN28: =+$F$9*AM28 -> 0.135 | AO28: =+AM28*$F$10 -> 0.18 | AP28: =+G28 -> 6300 | AQ28: =+AT27 -> 0 | AR28: =+(AN28*AP28+AO28*(AP28/12))*AM28 -> 945 | AS28: =+AQ28*$F$12 -> 0 | AT28: =+(AQ28+AR28+AS28) -> 945 | AV28: =+AK28 -> 1 | AW28: =+AL28 -> 23 | AX28: 1 | AY28: =+$F$9*AX28 -> 0.135 | AZ28: =+AX28*$F$10 -> 0.18 | BA28: =+G28 -> 6300 | BB28: =+BE27 -> 0 | BC28: =+(AY28*BA28+AZ28*(BA28/12))*AX28 -> 945 | BD28: =+BB28*$F$12 -> 0 | BE28: =+(BB28+BC28+BD28) -> 945
B29: =+B28+1 -> 2 | C29: =+C28+1 -> 23 | D29: =+D28*(1+$F$18) -> 1 | E29: =+IF($C29>=$F$6,0,$F$19*D29) -> 700 | F29: =+IF($C29>=$F$6,0,$F$20) -> 9 | G29: =+E29*F29 -> 6300 | I29: =+I28+1 -> 2 | J29: =+C29 -> 23 | K29: =+IF(AL29<=$AF$11,1,0)*F29 -> 9 | L29: =+IF(AL29>$AF$11,0,IF(E29>500,500*F29,E29*F29)) -> 4500 | M29: =+IF(AL29>$AF$11,0,IF(G29-L29 <= 0,0,G29-L29)) -> 1800 | N29: =+IF($F$7<7,L29+M29,IF(AL29>$AF$11,0,IF($F$2=1,IF($J29<$F$5,IF(G29<=$F$16*12,G29,$F$16*12),G29),G29))) -> 6300 | O29: =+IFERROR(N29/K29,0) -> 700 | Q29: =+I29 -> 2 | R29: =+J29+1 -> 24 | S29: =+IF(R29<=$AF$11,1,0) -> 1 | T29: =+T28 -> 0.1 | U29: =+M29 -> 1800 | V29: =+Y28 -> 180 | W29: =+T29*U29*S29 -> 180 | X29: =+$U$23*V29 -> 7.2 | Y29: =+(V29+W29+X29) -> 367.2 | AA29: =+B29 -> 2 | AB29: =+C29+1 -> 24 | AC29: =+IF(C29<$F$5,1,0) -> 0 | AD29: =+AD28 -> 0.15 | AE29: =+IF($F$2=1,IF(G29<=2500*12,G29,2500*12),G29) -> 6300 | AF29: =+AI28 -> 0 | AG29: =+AD29*AE29*$AC29 -> 0 | AH29: =+AF29*$F$11 -> 0 | AI29: =+(AF29+AG29+AH29) -> 0 | AK29: =+AA29 -> 2 | AL29: =+AB29 -> 24 | AM29: =+IF($C29>=$F$5,1,0) -> 1 | AN29: =+$F$9*AM29 -> 0.135 | AO29: =+AM29*$F$10 -> 0.18 | AP29: =+G29 -> 6300 | AQ29: =+AT28 -> 945 | AR29: =+(AN29*AP29+AO29*(AP29/12))*AM29 -> 945 | AS29: =+AQ29*$F$12 -> 37.8 | AT29: =+(AQ29+AR29+AS29) -> 1927.8 | AV29: =+AK29 -> 2 | AW29: =+AL29 -> 24 | AX29: 1 | AY29: =+$F$9*AX29 -> 0.135 | AZ29: =+AX29*$F$10 -> 0.18 | BA29: =+G29 -> 6300 | BB29: =+BE28 -> 945 | BC29: =+(AY29*BA29+AZ29*(BA29/12))*AX29 -> 945 | BD29: =+BB29*$F$12 -> 37.8 | BE29: =+(BB29+BC29+BD29) -> 1927.8
B30: =+B29+1 -> 3 | C30: =+C29+1 -> 24 | D30: =+D29*(1+$F$18) -> 1 | E30: =+IF($C30>=$F$6,0,$F$19*D30) -> 700 | F30: =+IF($C30>=$F$6,0,$F$20) -> 9 | G30: =+E30*F30 -> 6300 | I30: =+I29+1 -> 3 | J30: =+C30 -> 24 | K30: =+IF(AL30<=$AF$11,1,0)*F30 -> 9 | L30: =+IF(AL30>$AF$11,0,IF(E30>500,500*F30,E30*F30)) -> 4500 | M30: =+IF(AL30>$AF$11,0,IF(G30-L30 <= 0,0,G30-L30)) -> 1800 | N30: =+IF($F$7<7,L30+M30,IF(AL30>$AF$11,0,IF($F$2=1,IF($J30<$F$5,IF(G30<=$F$16*12,G30,$F$16*12),G30),G30))) -> 6300 | O30: =+IFERROR(N30/K30,0) -> 700 | Q30: =+I30 -> 3 | R30: =+J30+1 -> 25 | S30: =+IF(R30<=$AF$11,1,0) -> 1 | T30: =+T29 -> 0.1 | U30: =+M30 -> 1800 | V30: =+Y29 -> 367.2 | W30: =+T30*U30*S30 -> 180 | X30: =+$U$23*V30 -> 14.688 | Y30: =+(V30+W30+X30) -> 561.888 | AA30: =+B30 -> 3 | AB30: =+C30+1 -> 25 | AC30: =+IF(C30<$F$5,1,0) -> 0 | AD30: =+AD29 -> 0.15 | AE30: =+IF($F$2=1,IF(G30<=2500*12,G30,2500*12),G30) -> 6300 | AF30: =+AI29 -> 0 | AG30: =+AD30*AE30*$AC30 -> 0 | AH30: =+AF30*$F$11 -> 0 | AI30: =+(AF30+AG30+AH30) -> 0 | AK30: =+AA30 -> 3 | AL30: =+AB30 -> 25 | AM30: =+IF($C30>=$F$5,1,0) -> 1 | AN30: =+$F$9*AM30 -> 0.135 | AO30: =+AM30*$F$10 -> 0.18 | AP30: =+G30 -> 6300 | AQ30: =+AT29 -> 1927.8 | AR30: =+(AN30*AP30+AO30*(AP30/12))*AM30 -> 945 | AS30: =+AQ30*$F$12 -> 77.112 | AT30: =+(AQ30+AR30+AS30) -> 2949.912 | AV30: =+AK30 -> 3 | AW30: =+AL30 -> 25 | AX30: 1 | AY30: =+$F$9*AX30 -> 0.135 | AZ30: =+AX30*$F$10 -> 0.18 | BA30: =+G30 -> 6300 | BB30: =+BE29 -> 1927.8 | BC30: =+(AY30*BA30+AZ30*(BA30/12))*AX30 -> 945 | BD30: =+BB30*$F$12 -> 77.112 | BE30: =+(BB30+BC30+BD30) -> 2949.912
B31: =+B30+1 -> 4 | C31: =+C30+1 -> 25 | D31: =+D30*(1+$F$18) -> 1 | E31: =+IF($C31>=$F$6,0,$F$19*D31) -> 700 | F31: =+IF($C31>=$F$6,0,$F$20) -> 9 | G31: =+E31*F31 -> 6300 | I31: =+I30+1 -> 4 | J31: =+C31 -> 25 | K31: =+IF(AL31<=$AF$11,1,0)*F31 -> 9 | L31: =+IF(AL31>$AF$11,0,IF(E31>500,500*F31,E31*F31)) -> 4500 | M31: =+IF(AL31>$AF$11,0,IF(G31-L31 <= 0,0,G31-L31)) -> 1800 | N31: =+IF($F$7<7,L31+M31,IF(AL31>$AF$11,0,IF($F$2=1,IF($J31<$F$5,IF(G31<=$F$16*12,G31,$F$16*12),G31),G31))) -> 6300 | O31: =+IFERROR(N31/K31,0) -> 700 | Q31: =+I31 -> 4 | R31: =+J31+1 -> 26 | S31: =+IF(R31<=$AF$11,1,0) -> 1 | T31: =+T30 -> 0.1 | U31: =+M31 -> 1800 | V31: =+Y30 -> 561.888 | W31: =+T31*U31*S31 -> 180 | X31: =+$U$23*V31 -> 22.47552 | Y31: =+(V31+W31+X31) -> 764.36352 | AA31: =+B31 -> 4 | AB31: =+C31+1 -> 26 | AC31: =+IF(C31<$F$5,1,0) -> 0 | AD31: =+AD30 -> 0.15 | AE31: =+IF($F$2=1,IF(G31<=2500*12,G31,2500*12),G31) -> 6300 | AF31: =+AI30 -> 0 | AG31: =+AD31*AE31*$AC31 -> 0 | AH31: =+AF31*$F$11 -> 0 | AI31: =+(AF31+AG31+AH31) -> 0 | AK31: =+AA31 -> 4 | AL31: =+AB31 -> 26 | AM31: =+IF($C31>=$F$5,1,0) -> 1 | AN31: =+$F$9*AM31 -> 0.135 | AO31: =+AM31*$F$10 -> 0.18 | AP31: =+G31 -> 6300 | AQ31: =+AT30 -> 2949.912 | AR31: =+(AN31*AP31+AO31*(AP31/12))*AM31 -> 945 | AS31: =+AQ31*$F$12 -> 117.99648 | AT31: =+(AQ31+AR31+AS31) -> 4012.9085 | AV31: =+AK31 -> 4 | AW31: =+AL31 -> 26 | AX31: 1 | AY31: =+$F$9*AX31 -> 0.135 | AZ31: =+AX31*$F$10 -> 0.18 | BA31: =+G31 -> 6300 | BB31: =+BE30 -> 2949.912 | BC31: =+(AY31*BA31+AZ31*(BA31/12))*AX31 -> 945 | BD31: =+BB31*$F$12 -> 117.99648 | BE31: =+(BB31+BC31+BD31) -> 4012.9085
B32: =+B31+1 -> 5 | C32: =+C31+1 -> 26 | D32: =+D31*(1+$F$18) -> 1 | E32: =+IF($C32>=$F$6,0,$F$19*D32) -> 700 | F32: =+IF($C32>=$F$6,0,$F$20) -> 9 | G32: =+E32*F32 -> 6300 | I32: =+I31+1 -> 5 | J32: =+C32 -> 26 | K32: =+IF(AL32<=$AF$11,1,0)*F32 -> 9 | L32: =+IF(AL32>$AF$11,0,IF(E32>500,500*F32,E32*F32)) -> 4500 | M32: =+IF(AL32>$AF$11,0,IF(G32-L32 <= 0,0,G32-L32)) -> 1800 | N32: =+IF($F$7<7,L32+M32,IF(AL32>$AF$11,0,IF($F$2=1,IF($J32<$F$5,IF(G32<=$F$16*12,G32,$F$16*12),G32),G32))) -> 6300 | O32: =+IFERROR(N32/K32,0) -> 700 | Q32: =+I32 -> 5 | R32: =+J32+1 -> 27 | S32: =+IF(R32<=$AF$11,1,0) -> 1 | T32: =+T31 -> 0.1 | U32: =+M32 -> 1800 | V32: =+Y31 -> 764.36352 | W32: =+T32*U32*S32 -> 180 | X32: =+$U$23*V32 -> 30.574541 | Y32: =+(V32+W32+X32) -> 974.93806 | AA32: =+B32 -> 5 | AB32: =+C32+1 -> 27 | AC32: =+IF(C32<$F$5,1,0) -> 0 | AD32: =+AD31 -> 0.15 | AE32: =+IF($F$2=1,IF(G32<=2500*12,G32,2500*12),G32) -> 6300 | AF32: =+AI31 -> 0 | AG32: =+AD32*AE32*$AC32 -> 0 | AH32: =+AF32*$F$11 -> 0 | AI32: =+(AF32+AG32+AH32) -> 0 | AK32: =+AA32 -> 5 | AL32: =+AB32 -> 27 | AM32: =+IF($C32>=$F$5,1,0) -> 1 | AN32: =+$F$9*AM32 -> 0.135 | AO32: =+AM32*$F$10 -> 0.18 | AP32: =+G32 -> 6300 | AQ32: =+AT31 -> 4012.9085 | AR32: =+(AN32*AP32+AO32*(AP32/12))*AM32 -> 945 | AS32: =+AQ32*$F$12 -> 160.51634 | AT32: =+(AQ32+AR32+AS32) -> 5118.4248 | AV32: =+AK32 -> 5 | AW32: =+AL32 -> 27 | AX32: 1 | AY32: =+$F$9*AX32 -> 0.135 | AZ32: =+AX32*$F$10 -> 0.18 | BA32: =+G32 -> 6300 | BB32: =+BE31 -> 4012.9085 | BC32: =+(AY32*BA32+AZ32*(BA32/12))*AX32 -> 945 | BD32: =+BB32*$F$12 -> 160.51634 | BE32: =+(BB32+BC32+BD32) -> 5118.4248
B33: =+B32+1 -> 6 | C33: =+C32+1 -> 27 | D33: =+D32*(1+$F$18) -> 1 | E33: =+IF($C33>=$F$6,0,$F$19*D33) -> 700 | F33: =+IF($C33>=$F$6,0,$F$20) -> 9 | G33: =+E33*F33 -> 6300 | I33: =+I32+1 -> 6 | J33: =+C33 -> 27 | K33: =+IF(AL33<=$AF$11,1,0)*F33 -> 9 | L33: =+IF(AL33>$AF$11,0,IF(E33>500,500*F33,E33*F33)) -> 4500 | M33: =+IF(AL33>$AF$11,0,IF(G33-L33 <= 0,0,G33-L33)) -> 1800 | N33: =+IF($F$7<7,L33+M33,IF(AL33>$AF$11,0,IF($F$2=1,IF($J33<$F$5,IF(G33<=$F$16*12,G33,$F$16*12),G33),G33))) -> 6300 | O33: =+IFERROR(N33/K33,0) -> 700 | Q33: =+I33 -> 6 | R33: =+J33+1 -> 28 | S33: =+IF(R33<=$AF$11,1,0) -> 1 | T33: =+T32 -> 0.1 | U33: =+M33 -> 1800 | V33: =+Y32 -> 974.93806 | W33: =+T33*U33*S33 -> 180 | X33: =+$U$23*V33 -> 38.997522 | Y33: =+(V33+W33+X33) -> 1193.9356 | AA33: =+B33 -> 6 | AB33: =+C33+1 -> 28 | AC33: =+IF(C33<$F$5,1,0) -> 0 | AD33: =+AD32 -> 0.15 | AE33: =+IF($F$2=1,IF(G33<=2500*12,G33,2500*12),G33) -> 6300 | AF33: =+AI32 -> 0 | AG33: =+AD33*AE33*$AC33 -> 0 | AH33: =+AF33*$F$11 -> 0 | AI33: =+(AF33+AG33+AH33) -> 0 | AK33: =+AA33 -> 6 | AL33: =+AB33 -> 28 | AM33: =+IF($C33>=$F$5,1,0) -> 1 | AN33: =+$F$9*AM33 -> 0.135 | AO33: =+AM33*$F$10 -> 0.18 | AP33: =+G33 -> 6300 | AQ33: =+AT32 -> 5118.4248 | AR33: =+(AN33*AP33+AO33*(AP33/12))*AM33 -> 945 | AS33: =+AQ33*$F$12 -> 204.73699 | AT33: =+(AQ33+AR33+AS33) -> 6268.1618 | AV33: =+AK33 -> 6 | AW33: =+AL33 -> 28 | AX33: 1 | AY33: =+$F$9*AX33 -> 0.135 | AZ33: =+AX33*$F$10 -> 0.18 | BA33: =+G33 -> 6300 | BB33: =+BE32 -> 5118.4248 | BC33: =+(AY33*BA33+AZ33*(BA33/12))*AX33 -> 945 | BD33: =+BB33*$F$12 -> 204.73699 | BE33: =+(BB33+BC33+BD33) -> 6268.1618
B34: =+B33+1 -> 7 | C34: =+C33+1 -> 28 | D34: =+D33*(1+$F$18) -> 1 | E34: =+IF($C34>=$F$6,0,$F$19*D34) -> 700 | F34: =+IF($C34>=$F$6,0,$F$20) -> 9 | G34: =+E34*F34 -> 6300 | I34: =+I33+1 -> 7 | J34: =+C34 -> 28 | K34: =+IF(AL34<=$AF$11,1,0)*F34 -> 9 | L34: =+IF(AL34>$AF$11,0,IF(E34>500,500*F34,E34*F34)) -> 4500 | M34: =+IF(AL34>$AF$11,0,IF(G34-L34 <= 0,0,G34-L34)) -> 1800 | N34: =+IF($F$7<7,L34+M34,IF(AL34>$AF$11,0,IF($F$2=1,IF($J34<$F$5,IF(G34<=$F$16*12,G34,$F$16*12),G34),G34))) -> 6300 | O34: =+IFERROR(N34/K34,0) -> 700 | Q34: =+I34 -> 7 | R34: =+J34+1 -> 29 | S34: =+IF(R34<=$AF$11,1,0) -> 1 | T34: =+T33 -> 0.1 | U34: =+M34 -> 1800 | V34: =+Y33 -> 1193.9356 | W34: =+T34*U34*S34 -> 180 | X34: =+$U$23*V34 -> 47.757423 | Y34: =+(V34+W34+X34) -> 1421.693 | AA34: =+B34 -> 7 | AB34: =+C34+1 -> 29 | AC34: =+IF(C34<$F$5,1,0) -> 0 | AD34: =+AD33 -> 0.15 | AE34: =+IF($F$2=1,IF(G34<=2500*12,G34,2500*12),G34) -> 6300 | AF34: =+AI33 -> 0 | AG34: =+AD34*AE34*$AC34 -> 0 | AH34: =+AF34*$F$11 -> 0 | AI34: =+(AF34+AG34+AH34) -> 0 | AK34: =+AA34 -> 7 | AL34: =+AB34 -> 29 | AM34: =+IF($C34>=$F$5,1,0) -> 1 | AN34: =+$F$9*AM34 -> 0.135 | AO34: =+AM34*$F$10 -> 0.18 | AP34: =+G34 -> 6300 | AQ34: =+AT33 -> 6268.1618 | AR34: =+(AN34*AP34+AO34*(AP34/12))*AM34 -> 945 | AS34: =+AQ34*$F$12 -> 250.72647 | AT34: =+(AQ34+AR34+AS34) -> 7463.8883 | AV34: =+AK34 -> 7 | AW34: =+AL34 -> 29 | AX34: 1 | AY34: =+$F$9*AX34 -> 0.135 | AZ34: =+AX34*$F$10 -> 0.18 | BA34: =+G34 -> 6300 | BB34: =+BE33 -> 6268.1618 | BC34: =+(AY34*BA34+AZ34*(BA34/12))*AX34 -> 945 | BD34: =+BB34*$F$12 -> 250.72647 | BE34: =+(BB34+BC34+BD34) -> 7463.8883
B35: =+B34+1 -> 8 | C35: =+C34+1 -> 29 | D35: =+D34*(1+$F$18) -> 1 | E35: =+IF($C35>=$F$6,0,$F$19*D35) -> 700 | F35: =+IF($C35>=$F$6,0,$F$20) -> 9 | G35: =+E35*F35 -> 6300 | I35: =+I34+1 -> 8 | J35: =+C35 -> 29 | K35: =+IF(AL35<=$AF$11,1,0)*F35 -> 9 | L35: =+IF(AL35>$AF$11,0,IF(E35>500,500*F35,E35*F35)) -> 4500 | M35: =+IF(AL35>$AF$11,0,IF(G35-L35 <= 0,0,G35-L35)) -> 1800 | N35: =+IF($F$7<7,L35+M35,IF(AL35>$AF$11,0,IF($F$2=1,IF($J35<$F$5,IF(G35<=$F$16*12,G35,$F$16*12),G35),G35))) -> 6300 | O35: =+IFERROR(N35/K35,0) -> 700 | Q35: =+I35 -> 8 | R35: =+J35+1 -> 30 | S35: =+IF(R35<=$AF$11,1,0) -> 1 | T35: =+T34 -> 0.1 | U35: =+M35 -> 1800 | V35: =+Y34 -> 1421.693 | W35: =+T35*U35*S35 -> 180 | X35: =+$U$23*V35 -> 56.86772 | Y35: =+(V35+W35+X35) -> 1658.5607 | AA35: =+B35 -> 8 | AB35: =+C35+1 -> 30 | AC35: =+IF(C35<$F$5,1,0) -> 0 | AD35: =+AD34 -> 0.15 | AE35: =+IF($F$2=1,IF(G35<=2500*12,G35,2500*12),G35) -> 6300 | AF35: =+AI34 -> 0 | AG35: =+AD35*AE35*$AC35 -> 0 | AH35: =+AF35*$F$11 -> 0 | AI35: =+(AF35+AG35+AH35) -> 0 | AK35: =+AA35 -> 8 | AL35: =+AB35 -> 30 | AM35: =+IF($C35>=$F$5,1,0) -> 1 | AN35: =+$F$9*AM35 -> 0.135 | AO35: =+AM35*$F$10 -> 0.18 | AP35: =+G35 -> 6300 | AQ35: =+AT34 -> 7463.8883 | AR35: =+(AN35*AP35+AO35*(AP35/12))*AM35 -> 945 | AS35: =+AQ35*$F$12 -> 298.55553 | AT35: =+(AQ35+AR35+AS35) -> 8707.4438 | AV35: =+AK35 -> 8 | AW35: =+AL35 -> 30 | AX35: 1 | AY35: =+$F$9*AX35 -> 0.135 | AZ35: =+AX35*$F$10 -> 0.18 | BA35: =+G35 -> 6300 | BB35: =+BE34 -> 7463.8883 | BC35: =+(AY35*BA35+AZ35*(BA35/12))*AX35 -> 945 | BD35: =+BB35*$F$12 -> 298.55553 | BE35: =+(BB35+BC35+BD35) -> 8707.4438
B36: =+B35+1 -> 9 | C36: =+C35+1 -> 30 | D36: =+D35*(1+$F$18) -> 1 | E36: =+IF($C36>=$F$6,0,$F$19*D36) -> 700 | F36: =+IF($C36>=$F$6,0,$F$20) -> 9 | G36: =+E36*F36 -> 6300 | I36: =+I35+1 -> 9 | J36: =+C36 -> 30 | K36: =+IF(AL36<=$AF$11,1,0)*F36 -> 9 | L36: =+IF(AL36>$AF$11,0,IF(E36>500,500*F36,E36*F36)) -> 4500 | M36: =+IF(AL36>$AF$11,0,IF(G36-L36 <= 0,0,G36-L36)) -> 1800 | N36: =+IF($F$7<7,L36+M36,IF(AL36>$AF$11,0,IF($F$2=1,IF($J36<$F$5,IF(G36<=$F$16*12,G36,$F$16*12),G36),G36))) -> 6300 | O36: =+IFERROR(N36/K36,0) -> 700 | Q36: =+I36 -> 9 | R36: =+J36+1 -> 31 | S36: =+IF(R36<=$AF$11,1,0) -> 1 | T36: =+T35 -> 0.1 | U36: =+M36 -> 1800 | V36: =+Y35 -> 1658.5607 | W36: =+T36*U36*S36 -> 180 | X36: =+$U$23*V36 -> 66.342429 | Y36: =+(V36+W36+X36) -> 1904.9032 | AA36: =+B36 -> 9 | AB36: =+C36+1 -> 31 | AC36: =+IF(C36<$F$5,1,0) -> 0 | AD36: =+AD35 -> 0.15 | AE36: =+IF($F$2=1,IF(G36<=2500*12,G36,2500*12),G36) -> 6300 | AF36: =+AI35 -> 0 | AG36: =+AD36*AE36*$AC36 -> 0 | AH36: =+AF36*$F$11 -> 0 | AI36: =+(AF36+AG36+AH36) -> 0 | AK36: =+AA36 -> 9 | AL36: =+AB36 -> 31 | AM36: =+IF($C36>=$F$5,1,0) -> 1 | AN36: =+$F$9*AM36 -> 0.135 | AO36: =+AM36*$F$10 -> 0.18 | AP36: =+G36 -> 6300 | AQ36: =+AT35 -> 8707.4438 | AR36: =+(AN36*AP36+AO36*(AP36/12))*AM36 -> 945 | AS36: =+AQ36*$F$12 -> 348.29775 | AT36: =+(AQ36+AR36+AS36) -> 10000.742 | AV36: =+AK36 -> 9 | AW36: =+AL36 -> 31 | AX36: 1 | AY36: =+$F$9*AX36 -> 0.135 | AZ36: =+AX36*$F$10 -> 0.18 | BA36: =+G36 -> 6300 | BB36: =+BE35 -> 8707.4438 | BC36: =+(AY36*BA36+AZ36*(BA36/12))*AX36 -> 945 | BD36: =+BB36*$F$12 -> 348.29775 | BE36: =+(BB36+BC36+BD36) -> 10000.742
B37: =+B36+1 -> 10 | C37: =+C36+1 -> 31 | D37: =+D36*(1+$F$18) -> 1 | E37: =+IF($C37>=$F$6,0,$F$19*D37) -> 700 | F37: =+IF($C37>=$F$6,0,$F$20) -> 9 | G37: =+E37*F37 -> 6300 | I37: =+I36+1 -> 10 | J37: =+C37 -> 31 | K37: =+IF(AL37<=$AF$11,1,0)*F37 -> 9 | L37: =+IF(AL37>$AF$11,0,IF(E37>500,500*F37,E37*F37)) -> 4500 | M37: =+IF(AL37>$AF$11,0,IF(G37-L37 <= 0,0,G37-L37)) -> 1800 | N37: =+IF($F$7<7,L37+M37,IF(AL37>$AF$11,0,IF($F$2=1,IF($J37<$F$5,IF(G37<=$F$16*12,G37,$F$16*12),G37),G37))) -> 6300 | O37: =+IFERROR(N37/K37,0) -> 700 | Q37: =+I37 -> 10 | R37: =+J37+1 -> 32 | S37: =+IF(R37<=$AF$11,1,0) -> 1 | T37: =+T36 -> 0.1 | U37: =+M37 -> 1800 | V37: =+Y36 -> 1904.9032 | W37: =+T37*U37*S37 -> 180 | X37: =+$U$23*V37 -> 76.196126 | Y37: =+(V37+W37+X37) -> 2161.0993 | AA37: =+B37 -> 10 | AB37: =+C37+1 -> 32 | AC37: =+IF(C37<$F$5,1,0) -> 0 | AD37: =+AD36 -> 0.15 | AE37: =+IF($F$2=1,IF(G37<=2500*12,G37,2500*12),G37) -> 6300 | AF37: =+AI36 -> 0 | AG37: =+AD37*AE37*$AC37 -> 0 | AH37: =+AF37*$F$11 -> 0 | AI37: =+(AF37+AG37+AH37) -> 0 | AK37: =+AA37 -> 10 | AL37: =+AB37 -> 32 | AM37: =+IF($C37>=$F$5,1,0) -> 1 | AN37: =+$F$9*AM37 -> 0.135 | AO37: =+AM37*$F$10 -> 0.18 | AP37: =+G37 -> 6300 | AQ37: =+AT36 -> 10000.742 | AR37: =+(AN37*AP37+AO37*(AP37/12))*AM37 -> 945 | AS37: =+AQ37*$F$12 -> 400.02966 | AT37: =+(AQ37+AR37+AS37) -> 11345.771 | AV37: =+AK37 -> 10 | AW37: =+AL37 -> 32 | AX37: 1 | AY37: =+$F$9*AX37 -> 0.135 | AZ37: =+AX37*$F$10 -> 0.18 | BA37: =+G37 -> 6300 | BB37: =+BE36 -> 10000.742 | BC37: =+(AY37*BA37+AZ37*(BA37/12))*AX37 -> 945 | BD37: =+BB37*$F$12 -> 400.02966 | BE37: =+(BB37+BC37+BD37) -> 11345.771
B38: =+B37+1 -> 11 | C38: =+C37+1 -> 32 | D38: =+D37*(1+$F$18) -> 1 | E38: =+IF($C38>=$F$6,0,$F$19*D38) -> 700 | F38: =+IF($C38>=$F$6,0,$F$20) -> 9 | G38: =+E38*F38 -> 6300 | I38: =+I37+1 -> 11 | J38: =+C38 -> 32 | K38: =+IF(AL38<=$AF$11,1,0)*F38 -> 9 | L38: =+IF(AL38>$AF$11,0,IF(E38>500,500*F38,E38*F38)) -> 4500 | M38: =+IF(AL38>$AF$11,0,IF(G38-L38 <= 0,0,G38-L38)) -> 1800 | N38: =+IF($F$7<7,L38+M38,IF(AL38>$AF$11,0,IF($F$2=1,IF($J38<$F$5,IF(G38<=$F$16*12,G38,$F$16*12),G38),G38))) -> 6300 | O38: =+IFERROR(N38/K38,0) -> 700 | Q38: =+I38 -> 11 | R38: =+J38+1 -> 33 | S38: =+IF(R38<=$AF$11,1,0) -> 1 | T38: =+T37 -> 0.1 | U38: =+M38 -> 1800 | V38: =+Y37 -> 2161.0993 | W38: =+T38*U38*S38 -> 180 | X38: =+$U$23*V38 -> 86.443971 | Y38: =+(V38+W38+X38) -> 2427.5433 | AA38: =+B38 -> 11 | AB38: =+C38+1 -> 33 | AC38: =+IF(C38<$F$5,1,0) -> 0 | AD38: =+AD37 -> 0.15 | AE38: =+IF($F$2=1,IF(G38<=2500*12,G38,2500*12),G38) -> 6300 | AF38: =+AI37 -> 0 | AG38: =+AD38*AE38*$AC38 -> 0 | AH38: =+AF38*$F$11 -> 0 | AI38: =+(AF38+AG38+AH38) -> 0 | AK38: =+AA38 -> 11 | AL38: =+AB38 -> 33 | AM38: =+IF($C38>=$F$5,1,0) -> 1 | AN38: =+$F$9*AM38 -> 0.135 | AO38: =+AM38*$F$10 -> 0.18 | AP38: =+G38 -> 6300 | AQ38: =+AT37 -> 11345.771 | AR38: =+(AN38*AP38+AO38*(AP38/12))*AM38 -> 945 | AS38: =+AQ38*$F$12 -> 453.83085 | AT38: =+(AQ38+AR38+AS38) -> 12744.602 | AV38: =+AK38 -> 11 | AW38: =+AL38 -> 33 | AX38: 1 | AY38: =+$F$9*AX38 -> 0.135 | AZ38: =+AX38*$F$10 -> 0.18 | BA38: =+G38 -> 6300 | BB38: =+BE37 -> 11345.771 | BC38: =+(AY38*BA38+AZ38*(BA38/12))*AX38 -> 945 | BD38: =+BB38*$F$12 -> 453.83085 | BE38: =+(BB38+BC38+BD38) -> 12744.602
B39: =+B38+1 -> 12 | C39: =+C38+1 -> 33 | D39: =+D38*(1+$F$18) -> 1 | E39: =+IF($C39>=$F$6,0,$F$19*D39) -> 700 | F39: =+IF($C39>=$F$6,0,$F$20) -> 9 | G39: =+E39*F39 -> 6300 | I39: =+I38+1 -> 12 | J39: =+C39 -> 33 | K39: =+IF(AL39<=$AF$11,1,0)*F39 -> 9 | L39: =+IF(AL39>$AF$11,0,IF(E39>500,500*F39,E39*F39)) -> 4500 | M39: =+IF(AL39>$AF$11,0,IF(G39-L39 <= 0,0,G39-L39)) -> 1800 | N39: =+IF($F$7<7,L39+M39,IF(AL39>$AF$11,0,IF($F$2=1,IF($J39<$F$5,IF(G39<=$F$16*12,G39,$F$16*12),G39),G39))) -> 6300 | O39: =+IFERROR(N39/K39,0) -> 700 | Q39: =+I39 -> 12 | R39: =+J39+1 -> 34 | S39: =+IF(R39<=$AF$11,1,0) -> 1 | T39: =+T38 -> 0.1 | U39: =+M39 -> 1800 | V39: =+Y38 -> 2427.5433 | W39: =+T39*U39*S39 -> 180 | X39: =+$U$23*V39 -> 97.10173 | Y39: =+(V39+W39+X39) -> 2704.645 | AA39: =+B39 -> 12 | AB39: =+C39+1 -> 34 | AC39: =+IF(C39<$F$5,1,0) -> 0 | AD39: =+AD38 -> 0.15 | AE39: =+IF($F$2=1,IF(G39<=2500*12,G39,2500*12),G39) -> 6300 | AF39: =+AI38 -> 0 | AG39: =+AD39*AE39*$AC39 -> 0 | AH39: =+AF39*$F$11 -> 0 | AI39: =+(AF39+AG39+AH39) -> 0 | AK39: =+AA39 -> 12 | AL39: =+AB39 -> 34 | AM39: =+IF($C39>=$F$5,1,0) -> 1 | AN39: =+$F$9*AM39 -> 0.135 | AO39: =+AM39*$F$10 -> 0.18 | AP39: =+G39 -> 6300 | AQ39: =+AT38 -> 12744.602 | AR39: =+(AN39*AP39+AO39*(AP39/12))*AM39 -> 945 | AS39: =+AQ39*$F$12 -> 509.78408 | AT39: =+(AQ39+AR39+AS39) -> 14199.386 | AV39: =+AK39 -> 12 | AW39: =+AL39 -> 34 | AX39: 1 | AY39: =+$F$9*AX39 -> 0.135 | AZ39: =+AX39*$F$10 -> 0.18 | BA39: =+G39 -> 6300 | BB39: =+BE38 -> 12744.602 | BC39: =+(AY39*BA39+AZ39*(BA39/12))*AX39 -> 945 | BD39: =+BB39*$F$12 -> 509.78408 | BE39: =+(BB39+BC39+BD39) -> 14199.386
B40: =+B39+1 -> 13 | C40: =+C39+1 -> 34 | D40: =+D39*(1+$F$18) -> 1 | E40: =+IF($C40>=$F$6,0,$F$19*D40) -> 700 | F40: =+IF($C40>=$F$6,0,$F$20) -> 9 | G40: =+E40*F40 -> 6300 | I40: =+I39+1 -> 13 | J40: =+C40 -> 34 | K40: =+IF(AL40<=$AF$11,1,0)*F40 -> 9 | L40: =+IF(AL40>$AF$11,0,IF(E40>500,500*F40,E40*F40)) -> 4500 | M40: =+IF(AL40>$AF$11,0,IF(G40-L40 <= 0,0,G40-L40)) -> 1800 | N40: =+IF($F$7<7,L40+M40,IF(AL40>$AF$11,0,IF($F$2=1,IF($J40<$F$5,IF(G40<=$F$16*12,G40,$F$16*12),G40),G40))) -> 6300 | O40: =+IFERROR(N40/K40,0) -> 700 | Q40: =+I40 -> 13 | R40: =+J40+1 -> 35 | S40: =+IF(R40<=$AF$11,1,0) -> 1 | T40: =+T39 -> 0.1 | U40: =+M40 -> 1800 | V40: =+Y39 -> 2704.645 | W40: =+T40*U40*S40 -> 180 | X40: =+$U$23*V40 -> 108.1858 | Y40: =+(V40+W40+X40) -> 2992.8308 | AA40: =+B40 -> 13 | AB40: =+C40+1 -> 35 | AC40: =+IF(C40<$F$5,1,0) -> 0 | AD40: =+AD39 -> 0.15 | AE40: =+IF($F$2=1,IF(G40<=2500*12,G40,2500*12),G40) -> 6300 | AF40: =+AI39 -> 0 | AG40: =+AD40*AE40*$AC40 -> 0 | AH40: =+AF40*$F$11 -> 0 | AI40: =+(AF40+AG40+AH40) -> 0 | AK40: =+AA40 -> 13 | AL40: =+AB40 -> 35 | AM40: =+IF($C40>=$F$5,1,0) -> 1 | AN40: =+$F$9*AM40 -> 0.135 | AO40: =+AM40*$F$10 -> 0.18 | AP40: =+G40 -> 6300 | AQ40: =+AT39 -> 14199.386 | AR40: =+(AN40*AP40+AO40*(AP40/12))*AM40 -> 945 | AS40: =+AQ40*$F$12 -> 567.97545 | AT40: =+(AQ40+AR40+AS40) -> 15712.362 | AV40: =+AK40 -> 13 | AW40: =+AL40 -> 35 | AX40: 1 | AY40: =+$F$9*AX40 -> 0.135 | AZ40: =+AX40*$F$10 -> 0.18 | BA40: =+G40 -> 6300 | BB40: =+BE39 -> 14199.386 | BC40: =+(AY40*BA40+AZ40*(BA40/12))*AX40 -> 945 | BD40: =+BB40*$F$12 -> 567.97545 | BE40: =+(BB40+BC40+BD40) -> 15712.362
... B65: =+B64+1 -> 38 | C65: =+C64+1 -> 59 | D65: =+D64*(1+$F$18) -> 1 | E65: =+IF($C65>=$F$6,0,$F$19*D65) -> 700 | F65: =+IF($C65>=$F$6,0,$F$20) -> 9 | G65: =+E65*F65 -> 6300 | I65: =+I64+1 -> 38 | J65: =+C65 -> 59 | K65: =+IF(AL65<=$AF$11,1,0)*F65 -> 9 | L65: =+IF(AL65>$AF$11,0,IF(E65>500,500*F65,E65*F65)) -> 4500 | M65: =+IF(AL65>$AF$11,0,IF(G65-L65 <= 0,0,G65-L65)) -> 1800 | N65: =+IF($F$7<7,L65+M65,IF(AL65>$AF$11,0,IF($F$2=1,IF($J65<$F$5,IF(G65<=$F$16*12,G65,$F$16*12),G65),G65))) -> 6300 | O65: =+IFERROR(N65/K65,0) -> 700 | Q65: =+I65 -> 38 | R65: =+J65+1 -> 60 | S65: =+IF(R65<=$AF$11,1,0) -> 1 | T65: =+T64 -> 0.1 | U65: =+M65 -> 1800 | V65: =+Y64 -> 14706.404 | W65: =+T65*U65*S65 -> 180 | X65: =+$U$23*V65 -> 588.25617 | Y65: =+(V65+W65+X65) -> 15474.661 | AA65: =+B65 -> 38 | AB65: =+C65+1 -> 60 | AC65: =+IF(C65<$F$5,1,0) -> 0 | AD65: =+AD64 -> 0.15 | AE65: =+IF($F$2=1,IF(G65<=2500*12,G65,2500*12),G65) -> 6300 | AF65: =+AI64 -> 0 | AG65: =+AD65*AE65*$AC65 -> 0 | AH65: =+AF65*$F$11 -> 0 | AI65: =+(AF65+AG65+AH65) -> 0 | AK65: =+AA65 -> 38 | AL65: =+AB65 -> 60 | AM65: =+IF($C65>=$F$5,1,0) -> 1 | AN65: =+$F$9*AM65 -> 0.135 | AO65: =+AM65*$F$10 -> 0.18 | AP65: =+G65 -> 6300 | AQ65: =+AT64 -> 77208.623 | AR65: =+(AN65*AP65+AO65*(AP65/12))*AM65 -> 945 | AS65: =+AQ65*$F$12 -> 3088.3449 | AT65: =+(AQ65+AR65+AS65) -> 81241.968 | AV65: =+AK65 -> 38 | AW65: =+AL65 -> 60 | AX65: 1 | AY65: =+$F$9*AX65 -> 0.135 | AZ65: =+AX65*$F$10 -> 0.18 | BA65: =+G65 -> 6300 | BB65: =+BE64 -> 77208.623 | BC65: =+(AY65*BA65+AZ65*(BA65/12))*AX65 -> 945 | BD65: =+BB65*$F$12 -> 3088.3449 | BE65: =+(BB65+BC65+BD65) -> 81241.968
B66: =+B65+1 -> 39 | C66: =+C65+1 -> 60 | D66: =+D65*(1+$F$18) -> 1 | E66: =+IF($C66>=$F$6,0,$F$19*D66) -> 700 | F66: =+IF($C66>=$F$6,0,$F$20) -> 9 | G66: =+E66*F66 -> 6300 | I66: =+I65+1 -> 39 | J66: =+C66 -> 60 | K66: =+IF(AL66<=$AF$11,1,0)*F66 -> 9 | L66: =+IF(AL66>$AF$11,0,IF(E66>500,500*F66,E66*F66)) -> 4500 | M66: =+IF(AL66>$AF$11,0,IF(G66-L66 <= 0,0,G66-L66)) -> 1800 | N66: =+IF($F$7<7,L66+M66,IF(AL66>$AF$11,0,IF($F$2=1,IF($J66<$F$5,IF(G66<=$F$16*12,G66,$F$16*12),G66),G66))) -> 6300 | O66: =+IFERROR(N66/K66,0) -> 700 | Q66: =+I66 -> 39 | R66: =+J66+1 -> 61 | S66: =+IF(R66<=$AF$11,1,0) -> 1 | T66: =+T65 -> 0.1 | U66: =+M66 -> 1800 | V66: =+Y65 -> 15474.661 | W66: =+T66*U66*S66 -> 180 | X66: =+$U$23*V66 -> 618.98642 | Y66: =+(V66+W66+X66) -> 16273.647 | AA66: =+B66 -> 39 | AB66: =+C66+1 -> 61 | AC66: =+IF(C66<$F$5,1,0) -> 0 | AD66: =+AD65 -> 0.15 | AE66: =+IF($F$2=1,IF(G66<=2500*12,G66,2500*12),G66) -> 6300 | AF66: =+AI65 -> 0 | AG66: =+AD66*AE66*$AC66 -> 0 | AH66: =+AF66*$F$11 -> 0 | AI66: =+(AF66+AG66+AH66) -> 0 | AK66: =+AA66 -> 39 | AL66: =+AB66 -> 61 | AM66: 1 | AN66: =+$F$9*AM66 -> 0.135 | AO66: =+AM66*$F$10 -> 0.18 | AP66: =+G66 -> 6300 | AQ66: =+AT65 -> 81241.968 | AR66: =+(AN66*AP66+AO66*(AP66/12))*AM66 -> 945 | AS66: =+AQ66*$F$12 -> 3249.6787 | AT66: =+(AQ66+AR66+AS66) -> 85436.646 | AV66: =+AK66 -> 39 | AW66: =+AL66 -> 61 | AX66: 1 | AY66: =+$F$9*AX66 -> 0.135 | AZ66: =+AX66*$F$10 -> 0.18 | BA66: =+G66 -> 6300 | BB66: =+BE65 -> 81241.968 | BC66: =+(AY66*BA66+AZ66*(BA66/12))*AX66 -> 945 | BD66: =+BB66*$F$12 -> 3249.6787 | BE66: =+(BB66+BC66+BD66) -> 85436.646
B67: =+B66+1 -> 40 | C67: =+C66+1 -> 61 | D67: =+D66*(1+$F$18) -> 1 | E67: =+IF($C67>=$F$6,0,$F$19*D67) -> 700 | F67: =+IF($C67>=$F$6,0,$F$20) -> 9 | G67: =+E67*F67 -> 6300 | I67: =+I66+1 -> 40 | J67: =+C67 -> 61 | K67: =+IF(AL67<=$AF$11,1,0)*F67 -> 9 | L67: =+IF(AL67>$AF$11,0,IF(E67>500,500*F67,E67*F67)) -> 4500 | M67: =+IF(AL67>$AF$11,0,IF(G67-L67 <= 0,0,G67-L67)) -> 1800 | N67: =+IF($F$7<7,L67+M67,IF(AL67>$AF$11,0,IF($F$2=1,IF($J67<$F$5,IF(G67<=$F$16*12,G67,$F$16*12),G67),G67))) -> 6300 | O67: =+IFERROR(N67/K67,0) -> 700 | Q67: =+I67 -> 40 | R67: =+J67+1 -> 62 | S67: 1 | T67: =+T66 -> 0.1 | U67: =+M67 -> 1800 | V67: =+Y66 -> 16273.647 | W67: =+T67*U67*S67 -> 180 | X67: =+$U$23*V67 -> 650.94588 | Y67: =+(V67+W67+X67) -> 17104.593 | AA67: =+B67 -> 40 | AB67: =+C67+1 -> 62 | AC67: =+IF(C67<$F$5,1,0) -> 0 | AD67: =+AD66 -> 0.15 | AE67: =+IF($F$2=1,IF(G67<=2500*12,G67,2500*12),G67) -> 6300 | AF67: =+AI66 -> 0 | AG67: =+AD67*AE67*$AC67 -> 0 | AH67: =+AF67*$F$11 -> 0 | AI67: =+(AF67+AG67+AH67) -> 0 | AK67: =+AA67 -> 40 | AL67: =+AB67 -> 62 | AM67: 1 | AN67: =+$F$9*AM67 -> 0.135 | AO67: =+AM67*$F$10 -> 0.18 | AP67: =+G67 -> 6300 | AQ67: =+AT66 -> 85436.646 | AR67: =+(AN67*AP67+AO67*(AP67/12))*AM67 -> 945 | AS67: =+AQ67*$F$12 -> 3417.4659 | AT67: =+(AQ67+AR67+AS67) -> 89799.112 | AV67: =+AK67 -> 40 | AW67: =+AL67 -> 62 | AX67: 1 | AY67: =+$F$9*AX67 -> 0.135 | AZ67: =+AX67*$F$10 -> 0.18 | BA67: =+G67 -> 6300 | BB67: =+BE66 -> 85436.646 | BC67: =+(AY67*BA67+AZ67*(BA67/12))*AX67 -> 945 | BD67: =+BB67*$F$12 -> 3417.4659 | BE67: =+(BB67+BC67+BD67) -> 89799.112
B68: =+B67+1 -> 41 | C68: =+C67+1 -> 62 | D68: =+D67*(1+$F$18) -> 1 | E68: =+IF($C68>=$F$6,0,$F$19*D68) -> 0 | F68: =+IF($C68>=$F$6,0,$F$20) -> 0 | G68: =+E68*F68 -> 0 | I68: =+I67+1 -> 41 | J68: =+C68 -> 62 | K68: =+IF(AL68<=$AF$11,1,0)*F68 -> 0 | L68: =+IF(AL68>$AF$11,0,IF(E68>500,500*F68,E68*F68)) -> 0 | M68: =+IF(AL68>$AF$11,0,IF(G68-L68 <= 0,0,G68-L68)) -> 0 | N68: =+IF($F$7<7,L68+M68,IF(AL68>$AF$11,0,IF($F$2=1,IF($J68<$F$5,IF(G68<=$F$16*12,G68,$F$16*12),G68),G68))) -> 0 | O68: =+IFERROR(N68/K68,0) -> 0 | Q68: =+I68 -> 41 | R68: =+J68+1 -> 63 | S68: =+IF(R68<=$AF$11,1,0) -> 0 | T68: =+T67 -> 0.1 | U68: =+M68 -> 0 | V68: =+Y67 -> 17104.593 | W68: =+T68*U68*S68 -> 0 | X68: =+$U$23*V68 -> 684.18371 | Y68: =+(V68+W68+X68) -> 17788.777 | AA68: =+B68 -> 41 | AB68: =+C68+1 -> 63 | AC68: =+IF(C68<$F$5,1,0) -> 0 | AD68: =+AD67 -> 0.15 | AE68: =+IF($F$2=1,IF(G68<=2500*12,G68,2500*12),G68) -> 0 | AF68: =+AI67 -> 0 | AG68: =+AD68*AE68*$AC68 -> 0 | AH68: =+AF68*$F$11 -> 0 | AI68: =+(AF68+AG68+AH68) -> 0 | AK68: =+AA68 -> 41 | AL68: =+AB68 -> 63 | AM68: 0 | AN68: =+$F$9*AM68 -> 0 | AO68: =+AM68*$F$10 -> 0 | AP68: =+G68 -> 0 | AQ68: =+AT67 -> 89799.112 | AR68: =+(AN68*AP68+AO68*(AP68/12))*AM68 -> 0 | AS68: =+AQ68*$F$12 -> 3591.9645 | AT68: =+(AQ68+AR68+AS68) -> 93391.077 | AV68: =+AK68 -> 41 | AW68: =+AL68 -> 63 | AX68: 0 | AY68: =+$F$9*AX68 -> 0 | AZ68: =+AX68*$F$10 -> 0 | BA68: =+G68 -> 0 | BB68: =+BE67 -> 89799.112 | BC68: =+(AY68*BA68+AZ68*(BA68/12))*AX68 -> 0 | BD68: =+BB68*$F$12 -> 3591.9645 | BE68: =+(BB68+BC68+BD68) -> 93391.077
B69: =+B68+1 -> 42 | C69: =+C68+1 -> 63 | D69: =+D68*(1+$F$18) -> 1 | E69: =+IF($C69>=$F$6,0,$F$19*D69) -> 0 | F69: =+IF($C69>=$F$6,0,$F$20) -> 0 | G69: =+E69*F69 -> 0 | I69: =+I68+1 -> 42 | J69: =+C69 -> 63 | K69: =+IF(AL69<=$AF$11,1,0)*F69 -> 0 | L69: =+IF(AL69>$AF$11,0,IF(E69>500,500*F69,E69*F69)) -> 0 | M69: =+IF(AL69>$AF$11,0,IF(G69-L69 <= 0,0,G69-L69)) -> 0 | N69: =+IF($F$7<7,L69+M69,IF(AL69>$AF$11,0,IF($F$2=1,IF($J69<$F$5,IF(G69<=$F$16*12,G69,$F$16*12),G69),G69))) -> 0 | O69: =+IFERROR(N69/K69,0) -> 0 | Q69: =+I69 -> 42 | R69: =+J69+1 -> 64 | S69: =+IF(R69<=$AF$11,1,0) -> 0 | T69: =+T68 -> 0.1 | U69: =+M69 -> 0 | V69: =+Y68 -> 17788.777 | W69: =+T69*U69*S69 -> 0 | X69: =+$U$23*V69 -> 711.55106 | Y69: =+(V69+W69+X69) -> 18500.328 | AA69: =+B69 -> 42 | AB69: =+C69+1 -> 64 | AC69: =+IF(C69<$F$5,1,0) -> 0 | AD69: =+AD68 -> 0.15 | AE69: =+IF($F$2=1,IF(G69<=2500*12,G69,2500*12),G69) -> 0 | AF69: =+AI68 -> 0 | AG69: =+AD69*AE69*$AC69 -> 0 | AH69: =+AF69*$F$11 -> 0 | AI69: =+(AF69+AG69+AH69) -> 0 | AK69: =+AA69 -> 42 | AL69: =+AB69 -> 64 | AM69: 0 | AN69: =+$F$9*AM69 -> 0 | AO69: =+AM69*$F$10 -> 0 | AP69: =+G69 -> 0 | AQ69: =+AT68 -> 93391.077 | AR69: =+(AN69*AP69+AO69*(AP69/12))*AM69 -> 0 | AS69: =+AQ69*$F$12 -> 3735.6431 | AT69: =+(AQ69+AR69+AS69) -> 97126.72 | AV69: =+AK69 -> 42 | AW69: =+AL69 -> 64 | AX69: 0 | AY69: =+$F$9*AX69 -> 0 | AZ69: =+AX69*$F$10 -> 0 | BA69: =+G69 -> 0 | BB69: =+BE68 -> 93391.077 | BC69: =+(AY69*BA69+AZ69*(BA69/12))*AX69 -> 0 | BD69: =+BB69*$F$12 -> 3735.6431 | BE69: =+(BB69+BC69+BD69) -> 97126.72
B70: =+B69+1 -> 43 | C70: =+C69+1 -> 64 | D70: =+D69*(1+$F$18) -> 1 | E70: =+IF($C70>=$F$6,0,$F$19*D70) -> 0 | F70: =+IF($C70>=$F$6,0,$F$20) -> 0 | G70: =+E70*F70 -> 0 | I70: =+I69+1 -> 43 | J70: =+C70 -> 64 | K70: =+IF(AL70<=$AF$11,1,0)*F70 -> 0 | L70: =+IF(AL70>$AF$11,0,IF(E70>500,500*F70,E70*F70)) -> 0 | M70: =+IF(AL70>$AF$11,0,IF(G70-L70 <= 0,0,G70-L70)) -> 0 | N70: =+IF($F$7<7,L70+M70,IF(AL70>$AF$11,0,IF($F$2=1,IF($J70<$F$5,IF(G70<=$F$16*12,G70,$F$16*12),G70),G70))) -> 0 | O70: =+IFERROR(N70/K70,0) -> 0 | Q70: =+I70 -> 43 | R70: =+J70+1 -> 65 | S70: =+IF(R70<=$AF$11,1,0) -> 0 | T70: =+T69 -> 0.1 | U70: =+M70 -> 0 | V70: =+Y69 -> 18500.328 | W70: =+T70*U70*S70 -> 0 | X70: =+$U$23*V70 -> 740.0131 | Y70: =+(V70+W70+X70) -> 19240.341 | AA70: =+B70 -> 43 | AB70: =+C70+1 -> 65 | AC70: =+IF(C70<$F$5,1,0) -> 0 | AD70: =+AD69 -> 0.15 | AE70: =+IF($F$2=1,IF(G70<=2500*12,G70,2500*12),G70) -> 0 | AF70: =+AI69 -> 0 | AG70: =+AD70*AE70*$AC70 -> 0 | AH70: =+AF70*$F$11 -> 0 | AI70: =+(AF70+AG70+AH70) -> 0 | AK70: =+AA70 -> 43 | AL70: =+AB70 -> 65 | AM70: 0 | AN70: =+$F$9*AM70 -> 0 | AO70: =+AM70*$F$10 -> 0 | AP70: =+G70 -> 0 | AQ70: =+AT69 -> 97126.72 | AR70: =+(AN70*AP70+AO70*(AP70/12))*AM70 -> 0 | AS70: =+AQ70*$F$12 -> 3885.0688 | AT70: =+(AQ70+AR70+AS70) -> 101011.79 | AV70: =+AK70 -> 43 | AW70: =+AL70 -> 65 | AX70: 0 | AY70: =+$F$9*AX70 -> 0 | AZ70: =+AX70*$F$10 -> 0 | BA70: =+G70 -> 0 | BB70: =+BE69 -> 97126.72 | BC70: =+(AY70*BA70+AZ70*(BA70/12))*AX70 -> 0 | BD70: =+BB70*$F$12 -> 3885.0688 | BE70: =+(BB70+BC70+BD70) -> 101011.79
B71: =+B70+1 -> 44 | C71: =+C70+1 -> 65 | D71: =+D70*(1+$F$18) -> 1 | E71: =+IF($C71>=$F$6,0,$F$19*D71) -> 0 | F71: =+IF($C71>=$F$6,0,$F$20) -> 0 | G71: =+E71*F71 -> 0 | I71: =+I70+1 -> 44 | J71: =+C71 -> 65 | K71: =+IF(AL71<=$AF$11,1,0)*F71 -> 0 | L71: =+IF(AL71>$AF$11,0,IF(E71>500,500*F71,E71*F71)) -> 0 | M71: =+IF(AL71>$AF$11,0,IF(G71-L71 <= 0,0,G71-L71)) -> 0 | N71: =+IF($F$7<7,L71+M71,IF(AL71>$AF$11,0,IF($F$2=1,IF($J71<$F$5,IF(G71<=$F$16*12,G71,$F$16*12),G71),G71))) -> 0 | O71: =+IFERROR(N71/K71,0) -> 0 | Q71: =+I71 -> 44 | R71: =+J71+1 -> 66 | S71: =+IF(R71<=$AF$11,1,0) -> 0 | T71: =+T70 -> 0.1 | U71: =+M71 -> 0 | V71: =+Y70 -> 19240.341 | W71: =+T71*U71*S71 -> 0 | X71: =+$U$23*V71 -> 769.61363 | Y71: =+(V71+W71+X71) -> 20009.954 | AA71: =+B71 -> 44 | AB71: =+C71+1 -> 66 | AC71: =+IF(C71<$F$5,1,0) -> 0 | AD71: =+AD70 -> 0.15 | AE71: =+IF($F$2=1,IF(G71<=2500*12,G71,2500*12),G71) -> 0 | AF71: =+AI70 -> 0 | AG71: =+AD71*AE71*$AC71 -> 0 | AH71: =+AF71*$F$11 -> 0 | AI71: =+(AF71+AG71+AH71) -> 0 | AK71: =+AA71 -> 44 | AL71: =+AB71 -> 66 | AM71: 0 | AN71: =+$F$9*AM71 -> 0 | AO71: =+AM71*$F$10 -> 0 | AP71: =+G71 -> 0 | AQ71: =+AT70 -> 101011.79 | AR71: =+(AN71*AP71+AO71*(AP71/12))*AM71 -> 0 | AS71: =+AQ71*$F$12 -> 4040.4715 | AT71: =+(AQ71+AR71+AS71) -> 105052.26 | AV71: =+AK71 -> 44 | AW71: =+AL71 -> 66 | AX71: 0 | AY71: =+$F$9*AX71 -> 0 | AZ71: =+AX71*$F$10 -> 0 | BA71: =+G71 -> 0 | BB71: =+BE70 -> 101011.79 | BC71: =+(AY71*BA71+AZ71*(BA71/12))*AX71 -> 0 | BD71: =+BB71*$F$12 -> 4040.4715 | BE71: =+(BB71+BC71+BD71) -> 105052.26
B72: =+B71+1 -> 45 | C72: =+C71+1 -> 66 | D72: =+D71*(1+$F$18) -> 1 | E72: =+IF($C72>=$F$6,0,$F$19*D72) -> 0 | F72: =+IF($C72>=$F$6,0,$F$20) -> 0 | G72: =+E72*F72 -> 0 | I72: =+I71+1 -> 45 | J72: =+C72 -> 66 | K72: =+IF(AL72<=$AF$11,1,0)*F72 -> 0 | L72: =+IF(AL72>$AF$11,0,IF(E72>500,500*F72,E72*F72)) -> 0 | M72: =+IF(AL72>$AF$11,0,IF(G72-L72 <= 0,0,G72-L72)) -> 0 | N72: =+IF($F$7<7,L72+M72,IF(AL72>$AF$11,0,IF($F$2=1,IF($J72<$F$5,IF(G72<=$F$16*12,G72,$F$16*12),G72),G72))) -> 0 | O72: =+IFERROR(N72/K72,0) -> 0 | Q72: =+I72 -> 45 | R72: =+J72+1 -> 67 | S72: =+IF(R72<=$AF$11,1,0) -> 0 | T72: =+T71 -> 0.1 | U72: =+M72 -> 0 | V72: =+Y71 -> 20009.954 | W72: =+T72*U72*S72 -> 0 | X72: =+$U$23*V72 -> 800.39817 | Y72: =+(V72+W72+X72) -> 20810.353 | AA72: =+B72 -> 45 | AB72: =+C72+1 -> 67 | AC72: =+IF(C72<$F$5,1,0) -> 0 | AD72: =+AD71 -> 0.15 | AE72: =+IF($F$2=1,IF(G72<=2500*12,G72,2500*12),G72) -> 0 | AF72: =+AI71 -> 0 | AG72: =+AD72*AE72*$AC72 -> 0 | AH72: =+AF72*$F$11 -> 0 | AI72: =+(AF72+AG72+AH72) -> 0 | AK72: =+AA72 -> 45 | AL72: =+AB72 -> 67 | AM72: 0 | AN72: =+$F$9*AM72 -> 0 | AO72: =+AM72*$F$10 -> 0 | AP72: =+G72 -> 0 | AQ72: =+AT71 -> 105052.26 | AR72: =+(AN72*AP72+AO72*(AP72/12))*AM72 -> 0 | AS72: =+AQ72*$F$12 -> 4202.0904 | AT72: =+(AQ72+AR72+AS72) -> 109254.35 | AV72: =+AK72 -> 45 | AW72: =+AL72 -> 67 | AX72: 0 | AY72: =+$F$9*AX72 -> 0 | AZ72: =+AX72*$F$10 -> 0 | BA72: =+G72 -> 0 | BB72: =+BE71 -> 105052.26 | BC72: =+(AY72*BA72+AZ72*(BA72/12))*AX72 -> 0 | BD72: =+BB72*$F$12 -> 4202.0904 | BE72: =+(BB72+BC72+BD72) -> 109254.35
B73: =+B72+1 -> 46 | C73: =+C72+1 -> 67 | D73: =+D72*(1+$F$18) -> 1 | E73: =+IF($C73>=$F$6,0,$F$19*D73) -> 0 | F73: =+IF($C73>=$F$6,0,$F$20) -> 0 | G73: =+E73*F73 -> 0 | I73: =+I72+1 -> 46 | J73: =+C73 -> 67 | K73: =+IF(AL73<=$AF$11,1,0)*F73 -> 0 | L73: =+IF(AL73>$AF$11,0,IF(E73>500,500*F73,E73*F73)) -> 0 | M73: =+IF(AL73>$AF$11,0,IF(G73-L73 <= 0,0,G73-L73)) -> 0 | N73: =+IF($F$7<7,L73+M73,IF(AL73>$AF$11,0,IF($F$2=1,IF($J73<$F$5,IF(G73<=$F$16*12,G73,$F$16*12),G73),G73))) -> 0 | O73: =+IFERROR(N73/K73,0) -> 0 | Q73: =+I73 -> 46 | R73: =+J73+1 -> 68 | S73: =+IF(R73<=$AF$11,1,0) -> 0 | T73: =+T72 -> 0.1 | U73: =+M73 -> 0 | V73: =+Y72 -> 20810.353 | W73: =+T73*U73*S73 -> 0 | X73: =+$U$23*V73 -> 832.4141 | Y73: =+(V73+W73+X73) -> 21642.767 | AA73: =+B73 -> 46 | AB73: =+C73+1 -> 68 | AC73: =+IF(C73<$F$5,1,0) -> 0 | AD73: =+AD72 -> 0.15 | AE73: =+IF($F$2=1,IF(G73<=2500*12,G73,2500*12),G73) -> 0 | AF73: =+AI72 -> 0 | AG73: =+AD73*AE73*$AC73 -> 0 | AH73: =+AF73*$F$11 -> 0 | AI73: =+(AF73+AG73+AH73) -> 0 | AK73: =+AA73 -> 46 | AL73: =+AB73 -> 68 | AM73: 0 | AN73: =+$F$9*AM73 -> 0 | AO73: =+AM73*$F$10 -> 0 | AP73: =+G73 -> 0 | AQ73: =+AT72 -> 109254.35 | AR73: =+(AN73*AP73+AO73*(AP73/12))*AM73 -> 0 | AS73: =+AQ73*$F$12 -> 4370.174 | AT73: =+(AQ73+AR73+AS73) -> 113624.52 | AV73: =+AK73 -> 46 | AW73: =+AL73 -> 68 | AX73: 0 | AY73: =+$F$9*AX73 -> 0 | AZ73: =+AX73*$F$10 -> 0 | BA73: =+G73 -> 0 | BB73: =+BE72 -> 109254.35 | BC73: =+(AY73*BA73+AZ73*(BA73/12))*AX73 -> 0 | BD73: =+BB73*$F$12 -> 4370.174 | BE73: =+(BB73+BC73+BD73) -> 113624.52
B74: =+B73+1 -> 47 | C74: =+C73+1 -> 68 | D74: =+D73*(1+$F$18) -> 1 | E74: =+IF($C74>=$F$6,0,$F$19*D74) -> 0 | F74: =+IF($C74>=$F$6,0,$F$20) -> 0 | G74: =+E74*F74 -> 0 | I74: =+I73+1 -> 47 | J74: =+C74 -> 68 | K74: =+IF(AL74<=$AF$11,1,0)*F74 -> 0 | L74: =+IF(AL74>$AF$11,0,IF(E74>500,500*F74,E74*F74)) -> 0 | M74: =+IF(AL74>$AF$11,0,IF(G74-L74 <= 0,0,G74-L74)) -> 0 | N74: =+IF($F$7<7,L74+M74,IF(AL74>$AF$11,0,IF($F$2=1,IF($J74<$F$5,IF(G74<=$F$16*12,G74,$F$16*12),G74),G74))) -> 0 | O74: =+IFERROR(N74/K74,0) -> 0 | Q74: =+I74 -> 47 | R74: =+J74+1 -> 69 | S74: =+IF(R74<=$AF$11,1,0) -> 0 | T74: =+T73 -> 0.1 | U74: =+M74 -> 0 | V74: =+Y73 -> 21642.767 | W74: =+T74*U74*S74 -> 0 | X74: =+$U$23*V74 -> 865.71066 | Y74: =+(V74+W74+X74) -> 22508.477 | AA74: =+B74 -> 47 | AB74: =+C74+1 -> 69 | AC74: =+IF(C74<$F$5,1,0) -> 0 | AD74: =+AD73 -> 0.15 | AE74: =+IF($F$2=1,IF(G74<=2500*12,G74,2500*12),G74) -> 0 | AF74: =+AI73 -> 0 | AG74: =+AD74*AE74*$AC74 -> 0 | AH74: =+AF74*$F$11 -> 0 | AI74: =+(AF74+AG74+AH74) -> 0 | AK74: =+AA74 -> 47 | AL74: =+AB74 -> 69 | AM74: 0 | AN74: =+$F$9*AM74 -> 0 | AO74: =+AM74*$F$10 -> 0 | AP74: =+G74 -> 0 | AQ74: =+AT73 -> 113624.52 | AR74: =+(AN74*AP74+AO74*(AP74/12))*AM74 -> 0 | AS74: =+AQ74*$F$12 -> 4544.981 | AT74: =+(AQ74+AR74+AS74) -> 118169.51 | AV74: =+AK74 -> 47 | AW74: =+AL74 -> 69 | AX74: 0 | AY74: =+$F$9*AX74 -> 0 | AZ74: =+AX74*$F$10 -> 0 | BA74: =+G74 -> 0 | BB74: =+BE73 -> 113624.52 | BC74: =+(AY74*BA74+AZ74*(BA74/12))*AX74 -> 0 | BD74: =+BB74*$F$12 -> 4544.981 | BE74: =+(BB74+BC74+BD74) -> 118169.51
B75: =+B74+1 -> 48 | C75: =+C74+1 -> 69 | D75: =+D74*(1+$F$18) -> 1 | E75: =+IF($C75>=$F$6,0,$F$19*D75) -> 0 | F75: =+IF($C75>=$F$6,0,$F$20) -> 0 | G75: =+E75*F75 -> 0 | I75: =+I74+1 -> 48 | J75: =+C75 -> 69 | K75: =+IF(AL75<=$AF$11,1,0)*F75 -> 0 | L75: =+IF(AL75>$AF$11,0,IF(E75>500,500*F75,E75*F75)) -> 0 | M75: =+IF(AL75>$AF$11,0,IF(G75-L75 <= 0,0,G75-L75)) -> 0 | N75: =+IF($F$7<7,L75+M75,IF(AL75>$AF$11,0,IF($F$2=1,IF($J75<$F$5,IF(G75<=$F$16*12,G75,$F$16*12),G75),G75))) -> 0 | O75: =+IFERROR(N75/K75,0) -> 0 | Q75: =+I75 -> 48 | R75: =+J75+1 -> 70 | S75: =+IF(R75<=$AF$11,1,0) -> 0 | T75: =+T74 -> 0.1 | U75: =+M75 -> 0 | V75: =+Y74 -> 22508.477 | W75: =+T75*U75*S75 -> 0 | X75: =+$U$23*V75 -> 900.33909 | Y75: =+(V75+W75+X75) -> 23408.816 | AA75: =+B75 -> 48 | AB75: =+C75+1 -> 70 | AC75: =+IF(C75<$F$5,1,0) -> 0 | AD75: =+AD74 -> 0.15 | AE75: =+IF($F$2=1,IF(G75<=2500*12,G75,2500*12),G75) -> 0 | AF75: =+AI74 -> 0 | AG75: =+AD75*AE75*$AC75 -> 0 | AH75: =+AF75*$F$11 -> 0 | AI75: =+(AF75+AG75+AH75) -> 0 | AK75: =+AA75 -> 48 | AL75: =+AB75 -> 70 | AM75: 0 | AN75: =+$F$9*AM75 -> 0 | AO75: =+AM75*$F$10 -> 0 | AP75: =+G75 -> 0 | AQ75: =+AT74 -> 118169.51 | AR75: =+(AN75*AP75+AO75*(AP75/12))*AM75 -> 0 | AS75: =+AQ75*$F$12 -> 4726.7802 | AT75: =+(AQ75+AR75+AS75) -> 122896.29 | AV75: =+AK75 -> 48 | AW75: =+AL75 -> 70 | AX75: 0 | AY75: =+$F$9*AX75 -> 0 | AZ75: =+AX75*$F$10 -> 0 | BA75: =+G75 -> 0 | BB75: =+BE74 -> 118169.51 | BC75: =+(AY75*BA75+AZ75*(BA75/12))*AX75 -> 0 | BD75: =+BB75*$F$12 -> 4726.7802 | BE75: =+(BB75+BC75+BD75) -> 122896.29
B76: =+B75+1 -> 49 | C76: =+C75+1 -> 70 | D76: =+D75*(1+$F$18) -> 1 | E76: =+IF($C76>=$F$6,0,$F$19*D76) -> 0 | F76: =+IF($C76>=$F$6,0,$F$20) -> 0 | G76: =+E76*F76 -> 0 | I76: =+I75+1 -> 49 | J76: =+C76 -> 70 | K76: =+IF(AL76<=$AF$11,1,0)*F76 -> 0 | L76: =+IF(AL76>$AF$11,0,IF(E76>500,500*F76,E76*F76)) -> 0 | M76: =+IF(AL76>$AF$11,0,IF(G76-L76 <= 0,0,G76-L76)) -> 0 | N76: =+IF($F$7<7,L76+M76,IF(AL76>$AF$11,0,IF($F$2=1,IF($J76<$F$5,IF(G76<=$F$16*12,G76,$F$16*12),G76),G76))) -> 0 | O76: =+IFERROR(N76/K76,0) -> 0 | Q76: =+I76 -> 49 | R76: =+J76+1 -> 71 | S76: =+IF(R76<=$AF$11,1,0) -> 0 | T76: =+T75 -> 0.1 | U76: =+M76 -> 0 | V76: =+Y75 -> 23408.816 | W76: =+T76*U76*S76 -> 0 | X76: =+$U$23*V76 -> 936.35265 | Y76: =+(V76+W76+X76) -> 24345.169 | AA76: =+B76 -> 49 | AB76: =+C76+1 -> 71 | AC76: =+IF(C76<$F$5,1,0) -> 0 | AD76: =+AD75 -> 0.15 | AE76: =+IF($F$2=1,IF(G76<=2500*12,G76,2500*12),G76) -> 0 | AF76: =+AI75 -> 0 | AG76: =+AD76*AE76*$AC76 -> 0 | AH76: =+AF76*$F$11 -> 0 | AI76: =+(AF76+AG76+AH76) -> 0 | AK76: =+AA76 -> 49 | AL76: =+AB76 -> 71 | AM76: 0 | AN76: =+$F$9*AM76 -> 0 | AO76: =+AM76*$F$10 -> 0 | AP76: =+G76 -> 0 | AQ76: =+AT75 -> 122896.29 | AR76: =+(AN76*AP76+AO76*(AP76/12))*AM76 -> 0 | AS76: =+AQ76*$F$12 -> 4915.8514 | AT76: =+(AQ76+AR76+AS76) -> 127812.14 | AV76: =+AK76 -> 49 | AW76: =+AL76 -> 71 | AX76: 0 | AY76: =+$F$9*AX76 -> 0 | AZ76: =+AX76*$F$10 -> 0 | BA76: =+G76 -> 0 | BB76: =+BE75 -> 122896.29 | BC76: =+(AY76*BA76+AZ76*(BA76/12))*AX76 -> 0 | BD76: =+BB76*$F$12 -> 4915.8514 | BE76: =+(BB76+BC76+BD76) -> 127812.14
B93: =+B92/12 -> 0
B95: =+B93-BM8 -> -6300

Sheet CALCULO 35
B1: DATOS BASICOS | BH1: BENEFICIO DE JUBILACION CSS SEBD
B2: SISTEMA | F2: 1 | BH2: CUOTAS APORTADAS | BM2: =+SUM(K28:K76) -> 420
B3: SEXO | F3: =+salidaformulas!B2 -> M | Q3: MIXTO | AA3: CAPITALIZACIÓN SOLIDARIA | BH3: CUOTAS EN EXCESO A DENSIDAD MIN | BM3: =+IF(BM2>240,BM2-F13,0) -> 180
B4: EDAD ENTRADA | F4: =+salidaformulas!B3 -> 22 | I4: SOLIDARIO | BH4: TASA DE REEMPLAZO AJUSTADA SEBD LEY 51 | BM4: =IF(F7<=7,BN4,BN4*AF13) -> 0.7875 | BN4: =IF(AND(BM2>=180,BM2<240),($F$14+INT(BM3/12)*$F$15)*BM2/240,IF(BM2<180,0,($F$14+INT(BM3/12)*$F$15))) -> 0.7875
B5: EDAD ACTUAL DIA DE REFORMA | F5: =+F4 -> 22 | J5: Mej. Salario Anual | K5: Mej Salario Anual | S5: Mej. Salario Anual | T5: Mej Salario Anual | BH5: PENSION ANNUAL A RECIBIR | BM5: =+BM6*12 -> 5788.125
B6: EDAD DE JUBILACION | F6: =+salidaformulas!B4 -> 62 | I6: Mejores Años | J6: TOTAL | K6: Primer Pilar | R6: Mejores Años | S6: TOTAL | T6: Primer Pilar | BH6: PENSION MENSUAL A RECIBIR | BM6: =IF(BM2>=240,MAX(MAX(BL8:BL10),265),MAX(BL8:BL10)) -> 482.34375
B7: AÑOS PARA JUBILARSE | F7: =+F6-F5 -> 40 | I7: 1 | J7: =LARGE($G$28:$G$65,I7) -> 7350 | K7: =LARGE($L$28:$L$65,I7) -> 5250 | R7: 1 | S7: =+J7 -> 7350 | T7: =+K7 -> 5250 | BL7: PENSION | BM7: PROM. ANUAL | BN7: PROM.MENSUAL
B8: % CUOTA APLICADO ANTES VIGENCIA NVA LEY | F8: 0.15 | I8: 2 | J8: =LARGE($G$28:$G$65,I8) -> 7350 | K8: =LARGE($L$28:$L$65,I8) -> 5250 | R8: 2 | S8: =+J8 -> 7350 | T8: =+K8 -> 5250 | BH8: CALCULO DE LOS MEJORES 10 AÑOS | BL8: =+IF($BM$4*BM8/12>1500,1500,$BM$4*BM8/12) -> 482.34375 | BM8: {=+AVERAGE(LARGE($G$28:$G$76,ROW(INDIRECT("1:10"))))} -> 7350
B9: % CUOTA EMPLEADO EMPLEADOR NUEVA LEY | F9: 0.135 | I9: 3 | J9: =LARGE($G$28:$G$65,I9) -> 7350 | K9: =LARGE($L$28:$L$65,I9) -> 5250 | R9: 3 | S9: =+J9 -> 7350 | T9: =+K9 -> 5250 | BH9: CALCULO DE LOS MEJORES 15 AÑOS (300 CUOTAS Y PROM>=$2,000) | BL9: =+IF($BM$4*BM9/12>2000,2000,$BM$4*BM9/12) -> 0 | BM9: {=IF(AND(BM2>300,AVERAGE(LARGE($G$28:$G$76,ROW(INDIRECT("1:15"))))>=24000),AVERAGE(LARGE($G$28:$G$76,ROW(INDIRECT("1:15")))),0)} -> 0
B10: % XIII EMPLEADO EMPLEADOR NUEVA LEY | F10: 0.18 | I10: 4 | J10: =LARGE($G$28:$G$65,I10) -> 7350 | K10: =LARGE($L$28:$L$65,I10) -> 5250 | R10: 4 | S10: =+J10 -> 7350 | T10: =+K10 -> 5250 | AA10: SCGS-CUANDO VIENE DEL SEBD o SM | BH10: CALCULO DE LOS MEJORES 20 AÑOS (360 cuotas y prom>=$2,500) | BL10: =+IF($BM$4*BM10/12>2500,2500,$BM$4*BM10/12) -> 0 | BM10: {=IF(AND(BM2>360,AVERAGE(LARGE($G$28:$G$76,ROW(INDIRECT("1:20"))))>=30000),AVERAGE(LARGE($G$28:$G$76,ROW(INDIRECT("1:20")))),0)} -> 0
B11: TASA DE RETORNO INVERSIONES ANTES VIG LEY | F11: 0.04 | I11: 5 | J11: =LARGE($G$28:$G$65,I11) -> 7350 | K11: =LARGE($L$28:$L$65,I11) -> 5250 | R11: 5 | S11: =+J11 -> 7350 | T11: =+K11 -> 5250 | AA11: EDAD JUBILACION | AF11: =+F6 -> 62 | AK11: RESULTADO COMPARATIVO | AO11: MONTO | AP11: REEMPLAZO MEJ.AÑOS | BH11: TASA DE REEMPLAZO FINAL DE ESTE CALCULO | BM11: =+BM5/VLOOKUP(MAX(BL8:BL10),BL8:BM10,2,0) -> 0.7875
B12: TASA RETORNO INVERSIONES PROMEDIO | F12: 0.04 | I12: 6 | J12: =LARGE($G$28:$G$65,I12) -> 7350 | K12: =LARGE($L$28:$L$65,I12) -> 5250 | R12: 6 | S12: =+J12 -> 7350 | T12: =+K12 -> 5250 | AA12: FONDO AHORRADO COP ANTES VIGENCIA NVA LEY | AF12: =+VLOOKUP(AF11,$AB$28:$AI$76,8,FALSE) -> 0 | AG12: R | AK12: PENSION A RECIBIR DEL SEBD | AO12: =+L18 -> 482.34375 | AP12: =+AO12/(J16/12) -> 0.7875
A13: A | B13: DENSIDAD MINIMA DE CUOTAS LEY 51 | F13: 240 | I13: 7 | J13: =LARGE($G$28:$G$65,I13) -> 7350 | K13: =LARGE($L$28:$L$65,I13) -> 5250 | R13: 7 | S13: =+J13 -> 7350 | T13: =+K13 -> 5250 | W13: VP | X13: RA*ax | AA13: FACTOR DESCUENTO | AF13: =+IF(AND($B$20=1,$F$2<>1),100%,IF($F$3="M",VLOOKUP(AF11,descuento!$A$6:$B$32,2,FALSE),VLOOKUP(AF11,descuento!$C$6:$D$32,2,FALSE))) -> 1 | AK13: PENSION A RECIBIR SISTEMA MIXTO | AO13: =+U22 -> 447.38778 | AP13: =+AO13/(S17/12) -> 0.73042902 | AV13: FONDO TOTAL APLICABLE | BB13: =+VLOOKUP(AF11,$AW$28:$BE$76,9,FALSE) -> 104765.63 | BH13: BENEFICIO DEL SISTEMA MIXTO
A14: B | B14: TASA DE REEMPLAZO INICIAL LEY 51 | F14: 0.6 | I14: 8 | J14: =LARGE($G$28:$G$65,I14) -> 7350 | K14: =LARGE($L$28:$L$65,I14) -> 5250 | R14: 8 | S14: =+J14 -> 7350 | T14: =+K14 -> 5250 | W14: VP/ax | X14: 12*RM | AA14: FONDO AHORRADO COP DESPUES VIGENCIA NVA LEY | AF14: =+VLOOKUP(AF11,$AL$28:$AT$76,9,FALSE) -> 104765.63 | AG14: S | AK14: PENSION A RECIBIR DEL SCGS | AO14: =+AF17 -> 539.99676 | AP14: =+AO14/(S16/12) -> 0.88162736 | AV14: FACTOR PENSION X MIL | BB14: =+AF16 -> 5.1543312
A15: C | B15: TASA DE REEMPLAZO ADICIONAL LEY 51 | F15: 0.0125 | I15: 9 | J15: =LARGE($G$28:$G$65,I15) -> 7350 | K15: =LARGE($L$28:$L$65,I15) -> 5250 | R15: 9 | S15: =+J15 -> 7350 | T15: =+K15 -> 5250 | W15: vp * (1/ax) | AA15: FONDO TOTAL APLICABLE | AF15: =+AF14+AF12*AF13 -> 104765.63 | AG15: T=R+S | AK15: PENSION A RECIBIR SI ENTRA NUEVO | AO15: =+BB15 -> 539.99676 | AP15: =+AO15/(S17/12) -> 0.88162736 | AV15: PENSION SCGS MENSUAL | BB15: =+BB13*0.001*BB14 -> 539.99676 | BH15: PROMEDIO ANUAL MEJORES 10 AÑOS PRIMER PILAR | BM15: {=+AVERAGE(LARGE($L$28:$L$76,ROW(INDIRECT("1:10"))))} -> 5250
B16: SALMAX MENSUAL COTIZADO ANTES VIG NVA LEY | F16: 2500 | I16: 10 | J16: =LARGE($G$28:$G$65,I16) -> 7350 | K16: =LARGE($L$28:$L$65,I16) -> 5250 | R16: 10 | S16: =+J16 -> 7350 | T16: =+K16 -> 5250 | AA16: FACTOR PENSION X MIL | AF16: =+VLOOKUP(AF11,'bases renta'!$K$20:$L$65,2,FALSE) -> 5.1543312 | AG16: U | AV16: REEMPLAZO MEJ.AÑOS | BB16: =+BB15/(J17/12) -> 0.88162736 | BH16: PENSION MENSUAL A RECIBIR PRIMER PILAR | BM16: =+BM15*BM4/12 -> 344.53125
B17: PORCENTAJE DE CUOTA OP DESCONTADA SMP | F17: 0.035 | H17: F | I17: PROMEDIO ANUAL | J17: =+AVERAGE(J7:J16) -> 7350 | K17: =+AVERAGE(K7:K16) -> 5250 | Q17: F | R17: PROMEDIO ANUAL | S17: =+J17 -> 7350 | T17: =+K17 -> 5250 | U17: J | AA17: PENSION SCGS MENSUAL | AF17: =+AF15*0.001*AF16 -> 539.99676 | AG17: V=(T/1000)*U | BH17: AHORRO PENSIONAL EDAD JUBILACION | BM17: =+VLOOKUP(AF11,$R$28:$Y$76,8,FALSE) -> 19955.358
B18: CRECIMIENTO SALARIAL CADA DOS AÑOS | F18: 0 | I18: CUOTAS | J18: =+BM2 -> 420 | K18: PENSION MENSUAL SEBD | L18: =+MIN(J17*J20/12,F16) -> 482.34375 | M18: G=(F*E)/12 | R18: CUOTAS | S18: =+J18 -> 420 | T18: PENSION MENSUAL 1er pilarBD | U18: =+(K17*S20)/12 -> 344.53125 | V18: K=(E*J)/12 | W18: REEMPLAZO MEJ.AÑOS | X18: =+U22/(J17/12) -> 0.73042902 | Y18: P=O/(E/12) | AA18: REEMPLAZO MEJ.AÑOS | AF18: =+AF17/(J17/12) -> 0.88162736 | AG18: W=V/(E/12) | BH18: FACTOR DE PENSIONAMIENTO XMIL | BM18: =+AF16 -> 5.1543312
B19: SALARIO INICIAL | F19: =+salidaformulas!A10 -> 700 | H19: D | I19: EXCESO DENSIDAD | J19: =+BM3 -> 180 | K19: SALARIO PROMEDIO TOTAL MENSUAL COTIZADO | L19: =+F23 -> 612.5 | M19: H | R19: EXCESO DENSIDAD | S19: =+J19 -> 180 | T19: AHORRO PERSONAL | U19: =+BM17 -> 19955.358 | V19: L | W19: SALARIO PROMEDIO TOTAL MENSUAL COTIZADO | X19: =+L19 -> 612.5 | Y19: =+M19 -> H | AA19: SALARIO PROMEDIO TOTAL MENSUAL COTIZADO | AF19: =+X19 -> 612.5 | AG19: H | BH19: PENSION MENSUAL 2do PILAR | BM19: =+(BM17/1000)*BM18 -> 102.85653
B20: cuotas pagadas por año | F20: 10.5 | H20: E=B+C*D | I20: REEMPLAZO MEJ.AÑOS | J20: =+BM4 -> 0.7875 | K20: TASA BRUTA REEMPLAZO | L20: =+L18/L19 -> 0.7875 | M20: I=G/H | Q20: E | R20: REEMPLAZO MEJ.AÑOS | S20: =+J20 -> 0.7875 | T20: FACTOR PENSIONAMIENTO VITALICIO | U20: =+BM18 -> 5.1543312 | V20: M | W20: TASA BRUTA REEMPLAZO | X20: =+U22/L19 -> 0.73042902 | Y20: Q=O/H | AA20: TASA BRUTA REEMPLAZO | AF20: =+AF17/L19 -> 0.88162736 | AG20: X=V/H | BH20: PENSION FINAL SISTEMA MIXTO | BM20: =IF(BM2>=240,MAX(BM16+BM19,265),BM16+BM19) -> 447.38778
C21: TOTAL CUOTAS MENSUALES | F21: =+SUMIF(F28:F76,">0") -> 420 | G21: =+F21/12 -> 35 | T21: PENSION MENSUAL 2do PILAR | U21: =+U19*0.001*U20 -> 102.85653 | V21: N=(L/1000)*M | BH21: TASA DE REEMPLAZO FINAL DE ESTE CALCULO | BM21: =+BM20*12/VLOOKUP(MAX($BL$8:$BL$10),$BL$8:$BN$10,2,0) -> 0.73042902
